Workbook

Sheet Matriz_DD_Unificada
A1: # item | B1: Dominio | C1: Subdominio | D1: Requerimiento | E1: Detalle del requerimiento | F1: Artículo / Ítem / Lugar | G1: Normativa | H1: Normativa específica / Fuente | I1: Qué se debe realizar / Documento-Control-Evidencia | J1: Valor cumplimiento (0, 0.5, 1, N/A) | K1: Estado automático | L1: Evidencia levantada | M1: Brecha / observación | N1: Responsable sugerido | O1: Prioridad | P1: Periodicidad / Plazo | Q1: Cruce / equivalencia normativa | R1: Revisión exhaustiva DD | S1: Control ISO/IEC 27001:2022 asociado | T1: Criterio de decisión | U1: Acción sugerida para cierre | V1: Plazo sugerido de atención | W1: Peso de atención | X1: Fase sugerida del plan
A2: 1 | B2: Contexto y alcance | C2: Aplicabilidad normativa | D2: Determinar aplicabilidad SB/SEPS por entidad, servicio y régimen | E2: Identificar si la entidad está controlada por SB, SEPS o ambas; para SEPS, definir segmento/régimen (general, especial o simplificado) y tipo de servicio auxiliar aplicable. | F2: SEPS Art. 1-3; SB Art. 1 | G2: Ambas | H2: SEPS Res. 2022-002; SB Libro I, Título IX, Cap. V | I2: Matriz de aplicabilidad normativa, acta de validación con Legal/Compliance, alcance por empresa y servicio, identificación de régimen SEPS y alcance SB. | J2: 1 | K2: =IF(TRIM(J2&"")="","Por evaluar",IF(UPPER(TRIM(J2&""))="N/A","No aplica",IF(OR(J2=1,J2="1"),"Cumple",IF(OR(J2=0.5,J2="0.5"),"Parcial",IF(OR(J2=0,J2="0"),"No cumple","Revisar valor"))))) -> Cumple | N2: Legal / Cumplimiento / CISO | O2: Alta | P2: Inicial y ante cambio regulatorio o de servicio | Q2: Base para definir qué filas aplican y evitar falsos incumplimientos. | R2: R1 normativa + R2 anexos + R3 cruce | S2: Cl. 4.1, 4.2, 4.3; A.5.31 Requisitos legales, estatutarios, regulatorios y contractuales | T2: =IF(K2="Cumple","Mantener / evidenciar",IF(K2="Parcial","Cerrar brecha parcial",IF(K2="No cumple","Implementar control",IF(K2="No aplica","Sin acción","Levantar evidencia")))) -> Mantener / evidenciar | U2: =IF(K2="Cumple","Mantener evidencia y revisión periódica",IF(K2="No aplica","Documentar justificación de no aplicabilidad",IF(K2="Por evaluar","Levantar evidencia y confirmar aplicabilidad",IF(K2="Parcial","Completar documentación/control y validar efectividad",IF(K2="No cumple","Diseñar, aprobar e implementar control requerido","Corregir valor de cumplimiento"))))) -> Mantener evidencia y revisión periódica | V2: =IF(K2="No cumple",IF(O2="Alta","0-30 días",IF(O2="Media","31-60 días","61-90 días")),IF(K2="Parcial",IF(O2="Alta","0-45 días",IF(O2="Media","31-75 días","61-120 días")),IF(K2="Por evaluar",IF(O2="Alta","0-15 días","0-30 días"),IF(K2="Cumple","Revisión periódica","No aplica")))) -> Revisión periódica | W2: =IF(K2="No cumple",IF(O2="Alta",3,IF(O2="Media",2,1)),IF(K2="Parcial",IF(O2="Alta",2,IF(O2="Media",1.5,1)),IF(K2="Por evaluar",IF(O2="Alta",1.5,IF(O2="Media",1,0.5)),0))) -> 0 | X2: =IF(K2="No aplica","No aplica",IF(K2="Cumple","Mantenimiento",IF(K2="Por evaluar","Fase 0 - Evidencia/aplicabilidad",IF(OR(B2="Gobernanza",B2="SGSI",B2="Contexto y alcance"),"Fase 1 - Gobierno y SGSI",IF(OR(B2="Riesgos",B2="Procesos",B2="Personas"),"Fase 2 - Riesgos y operación",IF(OR(B2="Terceros",B2="Continuidad"),"Fase 3 - Continuidad y terceros",IF(OR(B2="Tecnología",B2="Accesos",B2="Ciberseguridad",B2="Vulnerabilidades",B2="Incidentes",B2="Monitoreo"),"Fase 4 - Controles técnicos","Fase 5 - Canales y datos"))))))) -> Mantenimiento
A3: 2 | B3: Contexto y alcance | C3: Objeto de seguridad | D3: Preservar confidencialidad, integridad y disponibilidad de activos e información | E3: El programa debe proteger información y activos de información, incluyendo datos físicos, digitales, infraestructura, servicios, software, hardware y terceros. | F3: SEPS Art. 2 y 4; SB Art. 2 núm. 50; SB Art. 24 | G3: Ambas | H3: SEPS Res. 2022-002; SB Riesgo Operativo | I3: Declaración formal del objetivo del SGSI, política de seguridad de la información y alcance documentado de activos, servicios y procesos. | J3: 0.5 | K3: =IF(TRIM(J3&"")="","Por evaluar",IF(UPPER(TRIM(J3&""))="N/A","No aplica",IF(OR(J3=1,J3="1"),"Cumple",IF(OR(J3=0.5,J3="0.5"),"Parcial",IF(OR(J3=0,J3="0"),"No cumple","Revisar valor"))))) -> Parcial | M3: Procesos pendiente, no se entrega desde el área de procesos | N3: CISO | O3: Alta | P3: Anual | Q3: CID como principio común de ambas normas. | R3: R1 normativa + R2 anexos + R3 cruce | S3: Cl. 5.2, 6.2; A.5.1 Políticas de SI; A.5.9 Inventario de activos; A.5.12 Clasificación de la información | T3: =IF(K3="Cumple","Mantener / evidenciar",IF(K3="Parcial","Cerrar brecha parcial",IF(K3="No cumple","Implementar control",IF(K3="No aplica","Sin acción","Levantar evidencia")))) -> Cerrar brecha parcial | U3: =IF(K3="Cumple","Mantener evidencia y revisión periódica",IF(K3="No aplica","Documentar justificación de no aplicabilidad",IF(K3="Por evaluar","Levantar evidencia y confirmar aplicabilidad",IF(K3="Parcial","Completar documentación/control y validar efectividad",IF(K3="No cumple","Diseñar, aprobar e implementar control requerido","Corregir valor de cumplimiento"))))) -> Completar documentación/control y validar efectividad | V3: =IF(K3="No cumple",IF(O3="Alta","0-30 días",IF(O3="Media","31-60 días","61-90 días")),IF(K3="Parcial",IF(O3="Alta","0-45 días",IF(O3="Media","31-75 días","61-120 días")),IF(K3="Por evaluar",IF(O3="Alta","0-15 días","0-30 días"),IF(K3="Cumple","Revisión periódica","No aplica")))) -> 0-45 días | W3: =IF(K3="No cumple",IF(O3="Alta",3,IF(O3="Media",2,1)),IF(K3="Parcial",IF(O3="Alta",2,IF(O3="Media",1.5,1)),IF(K3="Por evaluar",IF(O3="Alta",1.5,IF(O3="Media",1,0.5)),0))) -> 2 | X3: =IF(K3="No aplica","No aplica",IF(K3="Cumple","Mantenimiento",IF(K3="Por evaluar","Fase 0 - Evidencia/aplicabilidad",IF(OR(B3="Gobernanza",B3="SGSI",B3="Contexto y alcance"),"Fase 1 - Gobierno y SGSI",IF(OR(B3="Riesgos",B3="Procesos",B3="Personas"),"Fase 2 - Riesgos y operación",IF(OR(B3="Terceros",B3="Continuidad"),"Fase 3 - Continuidad y terceros",IF(OR(B3="Tecnología",B3="Accesos",B3="Ciberseguridad",B3="Vulnerabilidades",B3="Incidentes",B3="Monitoreo"),"Fase 4 - Controles técnicos","Fase 5 - Canales y datos"))))))) -> Fase 1 - Gobierno y SGSI
A4: 3 | B4: Contexto y alcance | C4: Alcance SGSI | D4: Definir alcance del SGSI | E4: El alcance debe considerar tipos de información, procesos críticos/agregadores, personas, unidades, infraestructura tecnológica, ubicaciones físicas y relaciones con terceros que acceden a información crítica o sensible. | F4: SEPS Art. 10; SB Art. 25 núm. 1 | G4: Ambas | H4: SEPS Art. 10; SB Art. 25 | I4: Documento de alcance del SGSI aprobado, mapa de procesos y activos dentro/fuera de alcance, justificación de exclusiones. | J4: 1 | K4: =IF(TRIM(J4&"")="","Por evaluar",IF(UPPER(TRIM(J4&""))="N/A","No aplica",IF(OR(J4=1,J4="1"),"Cumple",IF(OR(J4=0.5,J4="0.5"),"Parcial",IF(OR(J4=0,J4="0"),"No cumple","Revisar valor"))))) -> Cumple | N4: CISO / Dueños de procesos | O4: Alta | P4: Anual o ante cambios | Q4: Requerimiento homologado SEPS-SB. | R4: R1 normativa + R2 anexos + R3 cruce | S4: Cl. 4.3, 4.4; A.5.9 Inventario de activos; A.5.12 Clasificación; A.5.19 Relación con proveedores | T4: =IF(K4="Cumple","Mantener / evidenciar",IF(K4="Parcial","Cerrar brecha parcial",IF(K4="No cumple","Implementar control",IF(K4="No aplica","Sin acción","Levantar evidencia")))) -> Mantener / evidenciar | U4: =IF(K4="Cumple","Mantener evidencia y revisión periódica",IF(K4="No aplica","Documentar justificación de no aplicabilidad",IF(K4="Por evaluar","Levantar evidencia y confirmar aplicabilidad",IF(K4="Parcial","Completar documentación/control y validar efectividad",IF(K4="No cumple","Diseñar, aprobar e implementar control requerido","Corregir valor de cumplimiento"))))) -> Mantener evidencia y revisión periódica | V4: =IF(K4="No cumple",IF(O4="Alta","0-30 días",IF(O4="Media","31-60 días","61-90 días")),IF(K4="Parcial",IF(O4="Alta","0-45 días",IF(O4="Media","31-75 días","61-120 días")),IF(K4="Por evaluar",IF(O4="Alta","0-15 días","0-30 días"),IF(K4="Cumple","Revisión periódica","No aplica")))) -> Revisión periódica | W4: =IF(K4="No cumple",IF(O4="Alta",3,IF(O4="Media",2,1)),IF(K4="Parcial",IF(O4="Alta",2,IF(O4="Media",1.5,1)),IF(K4="Por evaluar",IF(O4="Alta",1.5,IF(O4="Media",1,0.5)),0))) -> 0 | X4: =IF(K4="No aplica","No aplica",IF(K4="Cumple","Mantenimiento",IF(K4="Por evaluar","Fase 0 - Evidencia/aplicabilidad",IF(OR(B4="Gobernanza",B4="SGSI",B4="Contexto y alcance"),"Fase 1 - Gobierno y SGSI",IF(OR(B4="Riesgos",B4="Procesos",B4="Personas"),"Fase 2 - Riesgos y operación",IF(OR(B4="Terceros",B4="Continuidad"),"Fase 3 - Continuidad y terceros",IF(OR(B4="Tecnología",B4="Accesos",B4="Ciberseguridad",B4="Vulnerabilidades",B4="Incidentes",B4="Monitoreo"),"Fase 4 - Controles técnicos","Fase 5 - Canales y datos"))))))) -> Mantenimiento
A5: 4 | B5: Contexto y alcance | C5: Normas de referencia | D5: Adoptar estándares reconocidos para SGSI, controles, continuidad y riesgos | E5: SEPS refiere ISO/IEC 27000 y controles ISO/IEC 27002; SB refiere ISO/IEC 27000, buenas prácticas internacionales de ciberseguridad y continuidad basada en ISO 22301. | F5: SEPS Art. 10-11; SB Art. 18, 24, 25, 26 | G5: Ambas | H5: SEPS y SB | I5: Mapa normativo interno que relacione ISO 27001/27002, ISO 22301, NIST/CSF u otro marco adoptado, con los requisitos SB/SEPS. | J5: 1 | K5: =IF(TRIM(J5&"")="","Por evaluar",IF(UPPER(TRIM(J5&""))="N/A","No aplica",IF(OR(J5=1,J5="1"),"Cumple",IF(OR(J5=0.5,J5="0.5"),"Parcial",IF(OR(J5=0,J5="0"),"No cumple","Revisar valor"))))) -> Cumple | M5: ISO 27001, NIST, CIS controls | N5: CISO / Riesgos / Continuidad | O5: Media | P5: Anual | Q5: Permite evidenciar criterio técnico de control. | R5: R1 normativa + R2 anexos + R3 cruce | S5: Cl. 6.1, 7.5; A.5.31 Requisitos regulatorios; A.5.36 Cumplimiento de políticas y estándares | T5: =IF(K5="Cumple","Mantener / evidenciar",IF(K5="Parcial","Cerrar brecha parcial",IF(K5="No cumple","Implementar control",IF(K5="No aplica","Sin acción","Levantar evidencia")))) -> Mantener / evidenciar | U5: =IF(K5="Cumple","Mantener evidencia y revisión periódica",IF(K5="No aplica","Documentar justificación de no aplicabilidad",IF(K5="Por evaluar","Levantar evidencia y confirmar aplicabilidad",IF(K5="Parcial","Completar documentación/control y validar efectividad",IF(K5="No cumple","Diseñar, aprobar e implementar control requerido","Corregir valor de cumplimiento"))))) -> Mantener evidencia y revisión periódica | V5: =IF(K5="No cumple",IF(O5="Alta","0-30 días",IF(O5="Media","31-60 días","61-90 días")),IF(K5="Parcial",IF(O5="Alta","0-45 días",IF(O5="Media","31-75 días","61-120 días")),IF(K5="Por evaluar",IF(O5="Alta","0-15 días","0-30 días"),IF(K5="Cumple","Revisión periódica","No aplica")))) -> Revisión periódica | W5: =IF(K5="No cumple",IF(O5="Alta",3,IF(O5="Media",2,1)),IF(K5="Parcial",IF(O5="Alta",2,IF(O5="Media",1.5,1)),IF(K5="Por evaluar",IF(O5="Alta",1.5,IF(O5="Media",1,0.5)),0))) -> 0 | X5: =IF(K5="No aplica","No aplica",IF(K5="Cumple","Mantenimiento",IF(K5="Por evaluar","Fase 0 - Evidencia/aplicabilidad",IF(OR(B5="Gobernanza",B5="SGSI",B5="Contexto y alcance"),"Fase 1 - Gobierno y SGSI",IF(OR(B5="Riesgos",B5="Procesos",B5="Personas"),"Fase 2 - Riesgos y operación",IF(OR(B5="Terceros",B5="Continuidad"),"Fase 3 - Continuidad y terceros",IF(OR(B5="Tecnología",B5="Accesos",B5="Ciberseguridad",B5="Vulnerabilidades",B5="Incidentes",B5="Monitoreo"),"Fase 4 - Controles técnicos","Fase 5 - Canales y datos"))))))) -> Mantenimiento
A6: 5 | B6: Gobernanza | C6: Órgano de gobierno | D6: Aprobación formal por Directorio/Consejo | E6: El órgano de gobierno debe aprobar planes, políticas, recursos, roles, responsabilidades, capacitación y gestión de riesgos de seguridad de la información. | F6: SEPS Art. 12, 20, 26; SB Art. 1, 24, 25 | G6: Ambas | H6: SEPS capítulos II-IV; SB Art. 24-25 | I6: Actas de Directorio/Consejo, resoluciones de aprobación, versiones controladas de PESI, políticas, plan de recursos, plan de riesgos y plan de capacitación. | J6: 0.5 | K6: =IF(TRIM(J6&"")="","Por evaluar",IF(UPPER(TRIM(J6&""))="N/A","No aplica",IF(OR(J6=1,J6="1"),"Cumple",IF(OR(J6=0.5,J6="0.5"),"Parcial",IF(OR(J6=0,J6="0"),"No cumple","Revisar valor"))))) -> Parcial | M6: PESI Plan de recursos y riesgos no se tiene Plan de capacitación SI | N6: Directorio / Consejo / Gerencia General | O6: Alta | P6: Según calendario de comités y aprobación anual | Q6: Requisito de gobierno común. | R6: R1 normativa + R2 anexos + R3 cruce | S6: Cl. 5.1, 5.2, 5.3, 6.2; A.5.1 Políticas; A.5.2 Roles y responsabilidades; A.5.36 Cumplimiento | T6: =IF(K6="Cumple","Mantener / evidenciar",IF(K6="Parcial","Cerrar brecha parcial",IF(K6="No cumple","Implementar control",IF(K6="No aplica","Sin acción","Levantar evidencia")))) -> Cerrar brecha parcial | U6: =IF(K6="Cumple","Mantener evidencia y revisión periódica",IF(K6="No aplica","Documentar justificación de no aplicabilidad",IF(K6="Por evaluar","Levantar evidencia y confirmar aplicabilidad",IF(K6="Parcial","Completar documentación/control y validar efectividad",IF(K6="No cumple","Diseñar, aprobar e implementar control requerido","Corregir valor de cumplimiento"))))) -> Completar documentación/control y validar efectividad | V6: =IF(K6="No cumple",IF(O6="Alta","0-30 días",IF(O6="Media","31-60 días","61-90 días")),IF(K6="Parcial",IF(O6="Alta","0-45 días",IF(O6="Media","31-75 días","61-120 días")),IF(K6="Por evaluar",IF(O6="Alta","0-15 días","0-30 días"),IF(K6="Cumple","Revisión periódica","No aplica")))) -> 0-45 días | W6: =IF(K6="No cumple",IF(O6="Alta",3,IF(O6="Media",2,1)),IF(K6="Parcial",IF(O6="Alta",2,IF(O6="Media",1.5,1)),IF(K6="Por evaluar",IF(O6="Alta",1.5,IF(O6="Media",1,0.5)),0))) -> 2 | X6: =IF(K6="No aplica","No aplica",IF(K6="Cumple","Mantenimiento",IF(K6="Por evaluar","Fase 0 - Evidencia/aplicabilidad",IF(OR(B6="Gobernanza",B6="SGSI",B6="Contexto y alcance"),"Fase 1 - Gobierno y SGSI",IF(OR(B6="Riesgos",B6="Procesos",B6="Personas"),"Fase 2 - Riesgos y operación",IF(OR(B6="Terceros",B6="Continuidad"),"Fase 3 - Continuidad y terceros",IF(OR(B6="Tecnología",B6="Accesos",B6="Ciberseguridad",B6="Vulnerabilidades",B6="Incidentes",B6="Monitoreo"),"Fase 4 - Controles técnicos","Fase 5 - Canales y datos"))))))) -> Fase 1 - Gobierno y SGSI
A7: 6 | B7: Gobernanza | C7: Comité de Seguridad | D7: Conformar Comité de Seguridad de la Información | E7: Debe existir un CSI con participación de gobierno, gerencia, riesgos, tecnología y seguridad; en SEPS el presidente del Comité de Administración Integral de Riesgos preside para régimen general/especial; en SB lo preside un miembro del Directorio. | F7: SEPS Art. 6, 15; SB Art. 24 | G7: Ambas | H7: SEPS Art. 6 y 15; SB Art. 24 | I7: Resolución de conformación, reglamento del comité, nómina de miembros titulares, cargos no delegables cuando aplique, matriz de roles y voto/voz. | J7: 1 | K7: =IF(TRIM(J7&"")="","Por evaluar",IF(UPPER(TRIM(J7&""))="N/A","No aplica",IF(OR(J7=1,J7="1"),"Cumple",IF(OR(J7=0.5,J7="0.5"),"Parcial",IF(OR(J7=0,J7="0"),"No cumple","Revisar valor"))))) -> Cumple | N7: Gerencia General / Directorio / CISO | O7: Alta | P7: Conformación inicial y actualización por cambios | Q7: Aplicar criterio más exigente si la entidad está bajo SB. | R7: R1 normativa + R2 anexos + R3 cruce | S7: Cl. 5.3; A.5.2 Roles y responsabilidades; A.5.4 Responsabilidades de la dirección; A.5.35 Revisión independiente | T7: =IF(K7="Cumple","Mantener / evidenciar",IF(K7="Parcial","Cerrar brecha parcial",IF(K7="No cumple","Implementar control",IF(K7="No aplica","Sin acción","Levantar evidencia")))) -> Mantener / evidenciar | U7: =IF(K7="Cumple","Mantener evidencia y revisión periódica",IF(K7="No aplica","Documentar justificación de no aplicabilidad",IF(K7="Por evaluar","Levantar evidencia y confirmar aplicabilidad",IF(K7="Parcial","Completar documentación/control y validar efectividad",IF(K7="No cumple","Diseñar, aprobar e implementar control requerido","Corregir valor de cumplimiento"))))) -> Mantener evidencia y revisión periódica | V7: =IF(K7="No cumple",IF(O7="Alta","0-30 días",IF(O7="Media","31-60 días","61-90 días")),IF(K7="Parcial",IF(O7="Alta","0-45 días",IF(O7="Media","31-75 días","61-120 días")),IF(K7="Por evaluar",IF(O7="Alta","0-15 días","0-30 días"),IF(K7="Cumple","Revisión periódica","No aplica")))) -> Revisión periódica | W7: =IF(K7="No cumple",IF(O7="Alta",3,IF(O7="Media",2,1)),IF(K7="Parcial",IF(O7="Alta",2,IF(O7="Media",1.5,1)),IF(K7="Por evaluar",IF(O7="Alta",1.5,IF(O7="Media",1,0.5)),0))) -> 0 | X7: =IF(K7="No aplica","No aplica",IF(K7="Cumple","Mantenimiento",IF(K7="Por evaluar","Fase 0 - Evidencia/aplicabilidad",IF(OR(B7="Gobernanza",B7="SGSI",B7="Contexto y alcance"),"Fase 1 - Gobierno y SGSI",IF(OR(B7="Riesgos",B7="Procesos",B7="Personas"),"Fase 2 - Riesgos y operación",IF(OR(B7="Terceros",B7="Continuidad"),"Fase 3 - Continuidad y terceros",IF(OR(B7="Tecnología",B7="Accesos",B7="Ciberseguridad",B7="Vulnerabilidades",B7="Incidentes",B7="Monitoreo"),"Fase 4 - Controles técnicos","Fase 5 - Canales y datos"))))))) -> Mantenimiento
A8: 7 | B8: Gobernanza | C8: Sesiones CSI | D8: Sesionar, documentar y custodiar actas del CSI | E8: SEPS exige sesiones ordinarias al menos dos veces al año en régimen general; SB exige reuniones al menos trimestrales y reporte directo al Directorio/Alta Gerencia/CAIR. | F8: SEPS Art. 7; SB Art. 24 | G8: Ambas | H8: SEPS Art. 7; SB Art. 24 | I8: Calendario anual de sesiones, convocatorias, quórum, actas numeradas y firmadas, matriz de compromisos y seguimiento. | J8: 1 | K8: =IF(TRIM(J8&"")="","Por evaluar",IF(UPPER(TRIM(J8&""))="N/A","No aplica",IF(OR(J8=1,J8="1"),"Cumple",IF(OR(J8=0.5,J8="0.5"),"Parcial",IF(OR(J8=0,J8="0"),"No cumple","Revisar valor"))))) -> Cumple | N8: Presidente CSI / Secretario CSI | O8: Alta | P8: Trimestral si aplica SB; mínimo semestral si solo SEPS general/especial | Q8: Criterio más estricto: trimestral. | R8: R1 normativa + R2 anexos + R3 cruce | S8: Cl. 9.3; A.5.35 Revisión independiente; A.5.36 Cumplimiento; A.5.37 Procedimientos operativos documentados | T8: =IF(K8="Cumple","Mantener / evidenciar",IF(K8="Parcial","Cerrar brecha parcial",IF(K8="No cumple","Implementar control",IF(K8="No aplica","Sin acción","Levantar evidencia")))) -> Mantener / evidenciar | U8: =IF(K8="Cumple","Mantener evidencia y revisión periódica",IF(K8="No aplica","Documentar justificación de no aplicabilidad",IF(K8="Por evaluar","Levantar evidencia y confirmar aplicabilidad",IF(K8="Parcial","Completar documentación/control y validar efectividad",IF(K8="No cumple","Diseñar, aprobar e implementar control requerido","Corregir valor de cumplimiento"))))) -> Mantener evidencia y revisión periódica | V8: =IF(K8="No cumple",IF(O8="Alta","0-30 días",IF(O8="Media","31-60 días","61-90 días")),IF(K8="Parcial",IF(O8="Alta","0-45 días",IF(O8="Media","31-75 días","61-120 días")),IF(K8="Por evaluar",IF(O8="Alta","0-15 días","0-30 días"),IF(K8="Cumple","Revisión periódica","No aplica")))) -> Revisión periódica | W8: =IF(K8="No cumple",IF(O8="Alta",3,IF(O8="Media",2,1)),IF(K8="Parcial",IF(O8="Alta",2,IF(O8="Media",1.5,1)),IF(K8="Por evaluar",IF(O8="Alta",1.5,IF(O8="Media",1,0.5)),0))) -> 0 | X8: =IF(K8="No aplica","No aplica",IF(K8="Cumple","Mantenimiento",IF(K8="Por evaluar","Fase 0 - Evidencia/aplicabilidad",IF(OR(B8="Gobernanza",B8="SGSI",B8="Contexto y alcance"),"Fase 1 - Gobierno y SGSI",IF(OR(B8="Riesgos",B8="Procesos",B8="Personas"),"Fase 2 - Riesgos y operación",IF(OR(B8="Terceros",B8="Continuidad"),"Fase 3 - Continuidad y terceros",IF(OR(B8="Tecnología",B8="Accesos",B8="Ciberseguridad",B8="Vulnerabilidades",B8="Incidentes",B8="Monitoreo"),"Fase 4 - Controles técnicos","Fase 5 - Canales y datos"))))))) -> Mantenimiento
A9: 8 | B9: Gobernanza | C9: Reglamento CSI | D9: Expedir reglamento del Comité de Seguridad | E9: SB exige reglamento con objetivo, funciones y responsabilidades; SEPS exige estructura y responsabilidades del comité, por lo que conviene formalizarlo también para SEPS. | F9: SB Art. 24; SEPS Art. 6-7 | G9: Ambas | H9: SB Art. 24; SEPS Art. 6-7 | I9: Reglamento del CSI aprobado, objetivo, funciones, miembros, quórum, voto, frecuencia, reportes, custodia de actas y flujo de escalamiento. | J9: 1 | K9: =IF(TRIM(J9&"")="","Por evaluar",IF(UPPER(TRIM(J9&""))="N/A","No aplica",IF(OR(J9=1,J9="1"),"Cumple",IF(OR(J9=0.5,J9="0.5"),"Parcial",IF(OR(J9=0,J9="0"),"No cumple","Revisar valor"))))) -> Cumple | N9: CISO / Secretaría CSI | O9: Alta | P9: Inicial y anual | Q9: Control unificador de gobernanza. | R9: R1 normativa + R2 anexos + R3 cruce | S9: Cl. 5.3, 7.5; A.5.2 Roles y responsabilidades; A.5.3 Segregación de funciones; A.5.36 Cumplimiento; A.5.37 Procedimientos documentados | T9: =IF(K9="Cumple","Mantener / evidenciar",IF(K9="Parcial","Cerrar brecha parcial",IF(K9="No cumple","Implementar control",IF(K9="No aplica","Sin acción","Levantar evidencia")))) -> Mantener / evidenciar | U9: =IF(K9="Cumple","Mantener evidencia y revisión periódica",IF(K9="No aplica","Documentar justificación de no aplicabilidad",IF(K9="Por evaluar","Levantar evidencia y confirmar aplicabilidad",IF(K9="Parcial","Completar documentación/control y validar efectividad",IF(K9="No cumple","Diseñar, aprobar e implementar control requerido","Corregir valor de cumplimiento"))))) -> Mantener evidencia y revisión periódica | V9: =IF(K9="No cumple",IF(O9="Alta","0-30 días",IF(O9="Media","31-60 días","61-90 días")),IF(K9="Parcial",IF(O9="Alta","0-45 días",IF(O9="Media","31-75 días","61-120 días")),IF(K9="Por evaluar",IF(O9="Alta","0-15 días","0-30 días"),IF(K9="Cumple","Revisión periódica","No aplica")))) -> Revisión periódica | W9: =IF(K9="No cumple",IF(O9="Alta",3,IF(O9="Media",2,1)),IF(K9="Parcial",IF(O9="Alta",2,IF(O9="Media",1.5,1)),IF(K9="Por evaluar",IF(O9="Alta",1.5,IF(O9="Media",1,0.5)),0))) -> 0 | X9: =IF(K9="No aplica","No aplica",IF(K9="Cumple","Mantenimiento",IF(K9="Por evaluar","Fase 0 - Evidencia/aplicabilidad",IF(OR(B9="Gobernanza",B9="SGSI",B9="Contexto y alcance"),"Fase 1 - Gobierno y SGSI",IF(OR(B9="Riesgos",B9="Procesos",B9="Personas"),"Fase 2 - Riesgos y operación",IF(OR(B9="Terceros",B9="Continuidad"),"Fase 3 - Continuidad y terceros",IF(OR(B9="Tecnología",B9="Accesos",B9="Ciberseguridad",B9="Vulnerabilidades",B9="Incidentes",B9="Monitoreo"),"Fase 4 - Controles técnicos","Fase 5 - Canales y datos"))))))) -> Mantenimiento
A10: 9 | B10: Gobernanza | C10: Área de Seguridad | D10: Contar con área/unidad independiente de Seguridad de la Información | E10: SB exige área independiente y especializada que reporte a máxima autoridad gerencial, separada de negocio, tecnología, riesgos y auditoría. SEPS exige Unidad/Departamento para régimen general adscrito a Gerencia General. | F10: SEPS Art. 8; SB Art. 24 | G10: Ambas | H10: SEPS Art. 8; SB Art. 24 | I10: Organigrama aprobado, descripción de puesto, dependencia jerárquica, independencia funcional, perfil del equipo y evidencia de recursos. | J10: 1 | K10: =IF(TRIM(J10&"")="","Por evaluar",IF(UPPER(TRIM(J10&""))="N/A","No aplica",IF(OR(J10=1,J10="1"),"Cumple",IF(OR(J10=0.5,J10="0.5"),"Parcial",IF(OR(J10=0,J10="0"),"No cumple","Revisar valor"))))) -> Cumple | N10: Gerencia General / CISO | O10: Alta | P10: Inicial y ante cambios organizacionales | Q10: Independencia funcional es más explícita en SB. | R10: R1 normativa + R2 anexos + R3 cruce | S10: Cl. 5.3, 7.1; A.5.2 Roles y responsabilidades; A.5.3 Segregación de funciones; A.5.4 Responsabilidades de la dirección | T10: =IF(K10="Cumple","Mantener / evidenciar",IF(K10="Parcial","Cerrar brecha parcial",IF(K10="No cumple","Implementar control",IF(K10="No aplica","Sin acción","Levantar evidencia")))) -> Mantener / evidenciar | U10: =IF(K10="Cumple","Mantener evidencia y revisión periódica",IF(K10="No aplica","Documentar justificación de no aplicabilidad",IF(K10="Por evaluar","Levantar evidencia y confirmar aplicabilidad",IF(K10="Parcial","Completar documentación/control y validar efectividad",IF(K10="No cumple","Diseñar, aprobar e implementar control requerido","Corregir valor de cumplimiento"))))) -> Mantener evidencia y revisión periódica | V10: =IF(K10="No cumple",IF(O10="Alta","0-30 días",IF(O10="Media","31-60 días","61-90 días")),IF(K10="Parcial",IF(O10="Alta","0-45 días",IF(O10="Media","31-75 días","61-120 días")),IF(K10="Por evaluar",IF(O10="Alta","0-15 días","0-30 días"),IF(K10="Cumple","Revisión periódica","No aplica")))) -> Revisión periódica | W10: =IF(K10="No cumple",IF(O10="Alta",3,IF(O10="Media",2,1)),IF(K10="Parcial",IF(O10="Alta",2,IF(O10="Media",1.5,1)),IF(K10="Por evaluar",IF(O10="Alta",1.5,IF(O10="Media",1,0.5)),0))) -> 0 | X10: =IF(K10="No aplica","No aplica",IF(K10="Cumple","Mantenimiento",IF(K10="Por evaluar","Fase 0 - Evidencia/aplicabilidad",IF(OR(B10="Gobernanza",B10="SGSI",B10="Contexto y alcance"),"Fase 1 - Gobierno y SGSI",IF(OR(B10="Riesgos",B10="Procesos",B10="Personas"),"Fase 2 - Riesgos y operación",IF(OR(B10="Terceros",B10="Continuidad"),"Fase 3 - Continuidad y terceros",IF(OR(B10="Tecnología",B10="Accesos",B10="Ciberseguridad",B10="Vulnerabilidades",B10="Incidentes",B10="Monitoreo"),"Fase 4 - Controles técnicos","Fase 5 - Canales y datos"))))))) -> Mantenimiento
A11: 10 | B11: Gobernanza | C11: Responsable/OSI | D11: Designar Oficial o Responsable de Seguridad de la Información | E11: Debe existir un OSI/responsable con funciones de definición, supervisión, ejecución y mejora de la gestión de seguridad de la información; SEPS define requisitos de capacitación y experiencia según régimen. | F11: SEPS Art. 8, 12, 17, 20, 23, 26; SB Art. 24 | G11: Ambas | H11: SEPS y SB | I11: Nombramiento formal, perfil de cargo, hoja de vida, certificaciones/capacitaciones, matriz RACI y plan de sustitución. | J11: 1 | K11: =IF(TRIM(J11&"")="","Por evaluar",IF(UPPER(TRIM(J11&""))="N/A","No aplica",IF(OR(J11=1,J11="1"),"Cumple",IF(OR(J11=0.5,J11="0.5"),"Parcial",IF(OR(J11=0,J11="0"),"No cumple","Revisar valor"))))) -> Cumple | N11: Gerencia General | O11: Alta | P11: Inicial y ante cambios | Q11: Equivalencia OSI SEPS / responsable área SI SB. | R11: R1 normativa + R2 anexos + R3 cruce | S11: Cl. 5.3, 7.2; A.5.2 Roles y responsabilidades; A.6.3 Concienciación, educación y formación | T11: =IF(K11="Cumple","Mantener / evidenciar",IF(K11="Parcial","Cerrar brecha parcial",IF(K11="No cumple","Implementar control",IF(K11="No aplica","Sin acción","Levantar evidencia")))) -> Mantener / evidenciar | U11: =IF(K11="Cumple","Mantener evidencia y revisión periódica",IF(K11="No aplica","Documentar justificación de no aplicabilidad",IF(K11="Por evaluar","Levantar evidencia y confirmar aplicabilidad",IF(K11="Parcial","Completar documentación/control y validar efectividad",IF(K11="No cumple","Diseñar, aprobar e implementar control requerido","Corregir valor de cumplimiento"))))) -> Mantener evidencia y revisión periódica | V11: =IF(K11="No cumple",IF(O11="Alta","0-30 días",IF(O11="Media","31-60 días","61-90 días")),IF(K11="Parcial",IF(O11="Alta","0-45 días",IF(O11="Media","31-75 días","61-120 días")),IF(K11="Por evaluar",IF(O11="Alta","0-15 días","0-30 días"),IF(K11="Cumple","Revisión periódica","No aplica")))) -> Revisión periódica | W11: =IF(K11="No cumple",IF(O11="Alta",3,IF(O11="Media",2,1)),IF(K11="Parcial",IF(O11="Alta",2,IF(O11="Media",1.5,1)),IF(K11="Por evaluar",IF(O11="Alta",1.5,IF(O11="Media",1,0.5)),0))) -> 0 | X11: =IF(K11="No aplica","No aplica",IF(K11="Cumple","Mantenimiento",IF(K11="Por evaluar","Fase 0 - Evidencia/aplicabilidad",IF(OR(B11="Gobernanza",B11="SGSI",B11="Contexto y alcance"),"Fase 1 - Gobierno y SGSI",IF(OR(B11="Riesgos",B11="Procesos",B11="Personas"),"Fase 2 - Riesgos y operación",IF(OR(B11="Terceros",B11="Continuidad"),"Fase 3 - Continuidad y terceros",IF(OR(B11="Tecnología",B11="Accesos",B11="Ciberseguridad",B11="Vulnerabilidades",B11="Incidentes",B11="Monitoreo"),"Fase 4 - Controles técnicos","Fase 5 - Canales y datos"))))))) -> Mantenimiento
A12: 11 | B12: Gobernanza | C12: Recursos | D12: Asignar recursos humanos, técnicos y financieros | E12: Deben existir recursos aprobados para gestión de seguridad, controles, capacitación, riesgos, auditorías y tecnologías de seguridad. | F12: SEPS Art. 9, 18, 24; SB Art. 15, 24, 25 | G12: Ambas | H12: SEPS Art. 9/18/24; SB Art. 15/25 | I12: Plan de recursos, presupuesto anual, plan operativo, requerimientos de herramientas, personal, capacitación, consultorías y licencias. | J12: 0 | K12: =IF(TRIM(J12&"")="","Por evaluar",IF(UPPER(TRIM(J12&""))="N/A","No aplica",IF(OR(J12=1,J12="1"),"Cumple",IF(OR(J12=0.5,J12="0.5"),"Parcial",IF(OR(J12=0,J12="0"),"No cumple","Revisar valor"))))) -> No cumple | N12: Directorio / Gerencia General / CISO | O12: Alta | P12: Anual | Q12: Control habilitante para todo el programa. | R12: R1 normativa + R2 anexos + R3 cruce | S12: Cl. 7.1, 7.2; A.5.2 Roles y responsabilidades; A.6.3 Formación y concienciación | T12: =IF(K12="Cumple","Mantener / evidenciar",IF(K12="Parcial","Cerrar brecha parcial",IF(K12="No cumple","Implementar control",IF(K12="No aplica","Sin acción","Levantar evidencia")))) -> Implementar control | U12: =IF(K12="Cumple","Mantener evidencia y revisión periódica",IF(K12="No aplica","Documentar justificación de no aplicabilidad",IF(K12="Por evaluar","Levantar evidencia y confirmar aplicabilidad",IF(K12="Parcial","Completar documentación/control y validar efectividad",IF(K12="No cumple","Diseñar, aprobar e implementar control requerido","Corregir valor de cumplimiento"))))) -> Diseñar, aprobar e implementar control requerido | V12: =IF(K12="No cumple",IF(O12="Alta","0-30 días",IF(O12="Media","31-60 días","61-90 días")),IF(K12="Parcial",IF(O12="Alta","0-45 días",IF(O12="Media","31-75 días","61-120 días")),IF(K12="Por evaluar",IF(O12="Alta","0-15 días","0-30 días"),IF(K12="Cumple","Revisión periódica","No aplica")))) -> 0-30 días | W12: =IF(K12="No cumple",IF(O12="Alta",3,IF(O12="Media",2,1)),IF(K12="Parcial",IF(O12="Alta",2,IF(O12="Media",1.5,1)),IF(K12="Por evaluar",IF(O12="Alta",1.5,IF(O12="Media",1,0.5)),0))) -> 3 | X12: =IF(K12="No aplica","No aplica",IF(K12="Cumple","Mantenimiento",IF(K12="Por evaluar","Fase 0 - Evidencia/aplicabilidad",IF(OR(B12="Gobernanza",B12="SGSI",B12="Contexto y alcance"),"Fase 1 - Gobierno y SGSI",IF(OR(B12="Riesgos",B12="Procesos",B12="Personas"),"Fase 2 - Riesgos y operación",IF(OR(B12="Terceros",B12="Continuidad"),"Fase 3 - Continuidad y terceros",IF(OR(B12="Tecnología",B12="Accesos",B12="Ciberseguridad",B12="Vulnerabilidades",B12="Incidentes",B12="Monitoreo"),"Fase 4 - Controles técnicos","Fase 5 - Canales y datos"))))))) -> Fase 1 - Gobierno y SGSI
A13: 12 | B13: Gobernanza | C13: Gerencia General | D13: Liderar y promover la gestión de Seguridad de la Información | E13: La gerencia debe liderar la gestión, designar al OSI/responsable y promover la participación de partes interesadas. | F13: SEPS Art. 12, 20, 26; SB Art. 24 | G13: Ambas | H13: SEPS y SB | I13: Acta de designación, comunicaciones de patrocinio, participación en comité, matriz de stakeholders y seguimiento de recursos. | J13: 1 | K13: =IF(TRIM(J13&"")="","Por evaluar",IF(UPPER(TRIM(J13&""))="N/A","No aplica",IF(OR(J13=1,J13="1"),"Cumple",IF(OR(J13=0.5,J13="0.5"),"Parcial",IF(OR(J13=0,J13="0"),"No cumple","Revisar valor"))))) -> Cumple | M13: Generar carta de compromiso de la gerencia | N13: Gerencia General | O13: Alta | P13: Permanente | Q13: Gobierno y tone at the top. | R13: R1 normativa + R2 anexos + R3 cruce | S13: Cl. 5.1; A.5.4 Responsabilidades de la dirección; A.5.1 Políticas de SI | T13: =IF(K13="Cumple","Mantener / evidenciar",IF(K13="Parcial","Cerrar brecha parcial",IF(K13="No cumple","Implementar control",IF(K13="No aplica","Sin acción","Levantar evidencia")))) -> Mantener / evidenciar | U13: =IF(K13="Cumple","Mantener evidencia y revisión periódica",IF(K13="No aplica","Documentar justificación de no aplicabilidad",IF(K13="Por evaluar","Levantar evidencia y confirmar aplicabilidad",IF(K13="Parcial","Completar documentación/control y validar efectividad",IF(K13="No cumple","Diseñar, aprobar e implementar control requerido","Corregir valor de cumplimiento"))))) -> Mantener evidencia y revisión periódica | V13: =IF(K13="No cumple",IF(O13="Alta","0-30 días",IF(O13="Media","31-60 días","61-90 días")),IF(K13="Parcial",IF(O13="Alta","0-45 días",IF(O13="Media","31-75 días","61-120 días")),IF(K13="Por evaluar",IF(O13="Alta","0-15 días","0-30 días"),IF(K13="Cumple","Revisión periódica","No aplica")))) -> Revisión periódica | W13: =IF(K13="No cumple",IF(O13="Alta",3,IF(O13="Media",2,1)),IF(K13="Parcial",IF(O13="Alta",2,IF(O13="Media",1.5,1)),IF(K13="Por evaluar",IF(O13="Alta",1.5,IF(O13="Media",1,0.5)),0))) -> 0 | X13: =IF(K13="No aplica","No aplica",IF(K13="Cumple","Mantenimiento",IF(K13="Por evaluar","Fase 0 - Evidencia/aplicabilidad",IF(OR(B13="Gobernanza",B13="SGSI",B13="Contexto y alcance"),"Fase 1 - Gobierno y SGSI",IF(OR(B13="Riesgos",B13="Procesos",B13="Personas"),"Fase 2 - Riesgos y operación",IF(OR(B13="Terceros",B13="Continuidad"),"Fase 3 - Continuidad y terceros",IF(OR(B13="Tecnología",B13="Accesos",B13="Ciberseguridad",B13="Vulnerabilidades",B13="Incidentes",B13="Monitoreo"),"Fase 4 - Controles técnicos","Fase 5 - Canales y datos"))))))) -> Mantenimiento
A14: 13 | B14: Gobernanza | C14: Auditoría interna / vigilancia | D14: Verificar eficacia del SGSI y controles | E14: SB exige revisión periódica de efectividad del SGSI y continuidad; SEPS asigna funciones a Auditor Interno/Consejo de Vigilancia para verificar medidas, custodiar informes y recomendar correcciones. | F14: SEPS Art. 12, 20, 26; SB Art. 11 | G14: Ambas | H14: SEPS y SB | I14: Plan anual de auditoría, informes de revisión, pruebas de efectividad, evidencias de hallazgos, planes de acción y seguimiento. | J14: 0.5 | K14: =IF(TRIM(J14&"")="","Por evaluar",IF(UPPER(TRIM(J14&""))="N/A","No aplica",IF(OR(J14=1,J14="1"),"Cumple",IF(OR(J14=0.5,J14="0.5"),"Parcial",IF(OR(J14=0,J14="0"),"No cumple","Revisar valor"))))) -> Parcial | M14: En fase inicial | N14: Auditoría Interna / Consejo de Vigilancia | O14: Alta | P14: Anual y según plan | Q14: Tercera línea de defensa. | R14: R1 normativa + R2 anexos + R3 cruce | S14: Cl. 9.2, 9.3; A.5.35 Revisión independiente de SI; A.8.34 Protección durante pruebas de auditoría | T14: =IF(K14="Cumple","Mantener / evidenciar",IF(K14="Parcial","Cerrar brecha parcial",IF(K14="No cumple","Implementar control",IF(K14="No aplica","Sin acción","Levantar evidencia")))) -> Cerrar brecha parcial | U14: =IF(K14="Cumple","Mantener evidencia y revisión periódica",IF(K14="No aplica","Documentar justificación de no aplicabilidad",IF(K14="Por evaluar","Levantar evidencia y confirmar aplicabilidad",IF(K14="Parcial","Completar documentación/control y validar efectividad",IF(K14="No cumple","Diseñar, aprobar e implementar control requerido","Corregir valor de cumplimiento"))))) -> Completar documentación/control y validar efectividad | V14: =IF(K14="No cumple",IF(O14="Alta","0-30 días",IF(O14="Media","31-60 días","61-90 días")),IF(K14="Parcial",IF(O14="Alta","0-45 días",IF(O14="Media","31-75 días","61-120 días")),IF(K14="Por evaluar",IF(O14="Alta","0-15 días","0-30 días"),IF(K14="Cumple","Revisión periódica","No aplica")))) -> 0-45 días | W14: =IF(K14="No cumple",IF(O14="Alta",3,IF(O14="Media",2,1)),IF(K14="Parcial",IF(O14="Alta",2,IF(O14="Media",1.5,1)),IF(K14="Por evaluar",IF(O14="Alta",1.5,IF(O14="Media",1,0.5)),0))) -> 2 | X14: =IF(K14="No aplica","No aplica",IF(K14="Cumple","Mantenimiento",IF(K14="Por evaluar","Fase 0 - Evidencia/aplicabilidad",IF(OR(B14="Gobernanza",B14="SGSI",B14="Contexto y alcance"),"Fase 1 - Gobierno y SGSI",IF(OR(B14="Riesgos",B14="Procesos",B14="Personas"),"Fase 2 - Riesgos y operación",IF(OR(B14="Terceros",B14="Continuidad"),"Fase 3 - Continuidad y terceros",IF(OR(B14="Tecnología",B14="Accesos",B14="Ciberseguridad",B14="Vulnerabilidades",B14="Incidentes",B14="Monitoreo"),"Fase 4 - Controles técnicos","Fase 5 - Canales y datos"))))))) -> Fase 1 - Gobierno y SGSI
A15: 14 | B15: Gobernanza | C15: Revisión documental | D15: Revisar y actualizar documentación de seguridad | E15: SEPS exige revisión anual y actualización cuando corresponda; SB exige revisión anual o ante cambios significativos para políticas, metodologías y continuidad. | F15: SEPS Art. 21 y 27; SB Art. 19, 25 | G15: Ambas | H15: SEPS Art. 21/27; SB Art. 19/25 | I15: Calendario de revisión documental, control de versiones, aprobaciones, historial de cambios y evidencia de difusión. | J15: 0.5 | K15: =IF(TRIM(J15&"")="","Por evaluar",IF(UPPER(TRIM(J15&""))="N/A","No aplica",IF(OR(J15=1,J15="1"),"Cumple",IF(OR(J15=0.5,J15="0.5"),"Parcial",IF(OR(J15=0,J15="0"),"No cumple","Revisar valor"))))) -> Parcial | M15: Se va a colocar en Eramba | N15: CISO / Dueños de documentos | O15: Media | P15: Anual o ante cambios | Q15: Requisito recurrente. | R15: R1 normativa + R2 anexos + R3 cruce | S15: Cl. 7.5, 9.3, 10.1; A.5.36 Cumplimiento de políticas; A.5.37 Procedimientos operativos documentados | T15: =IF(K15="Cumple","Mantener / evidenciar",IF(K15="Parcial","Cerrar brecha parcial",IF(K15="No cumple","Implementar control",IF(K15="No aplica","Sin acción","Levantar evidencia")))) -> Cerrar brecha parcial | U15: =IF(K15="Cumple","Mantener evidencia y revisión periódica",IF(K15="No aplica","Documentar justificación de no aplicabilidad",IF(K15="Por evaluar","Levantar evidencia y confirmar aplicabilidad",IF(K15="Parcial","Completar documentación/control y validar efectividad",IF(K15="No cumple","Diseñar, aprobar e implementar control requerido","Corregir valor de cumplimiento"))))) -> Completar documentación/control y validar efectividad | V15: =IF(K15="No cumple",IF(O15="Alta","0-30 días",IF(O15="Media","31-60 días","61-90 días")),IF(K15="Parcial",IF(O15="Alta","0-45 días",IF(O15="Media","31-75 días","61-120 días")),IF(K15="Por evaluar",IF(O15="Alta","0-15 días","0-30 días"),IF(K15="Cumple","Revisión periódica","No aplica")))) -> 31-75 días | W15: =IF(K15="No cumple",IF(O15="Alta",3,IF(O15="Media",2,1)),IF(K15="Parcial",IF(O15="Alta",2,IF(O15="Media",1.5,1)),IF(K15="Por evaluar",IF(O15="Alta",1.5,IF(O15="Media",1,0.5)),0))) -> 1.5 | X15: =IF(K15="No aplica","No aplica",IF(K15="Cumple","Mantenimiento",IF(K15="Por evaluar","Fase 0 - Evidencia/aplicabilidad",IF(OR(B15="Gobernanza",B15="SGSI",B15="Contexto y alcance"),"Fase 1 - Gobierno y SGSI",IF(OR(B15="Riesgos",B15="Procesos",B15="Personas"),"Fase 2 - Riesgos y operación",IF(OR(B15="Terceros",B15="Continuidad"),"Fase 3 - Continuidad y terceros",IF(OR(B15="Tecnología",B15="Accesos",B15="Ciberseguridad",B15="Vulnerabilidades",B15="Incidentes",B15="Monitoreo"),"Fase 4 - Controles técnicos","Fase 5 - Canales y datos"))))))) -> Fase 1 - Gobierno y SGSI
A16: 15 | B16: SGSI | C16: Sistema de gestión | D16: Implementar, mantener y mejorar continuamente el SGSI | E16: Debe existir un SGSI que gestione seguridad de la información y ciberseguridad, alineado a estándares reconocidos y normativa aplicable. | F16: SEPS Art. 10; SB Art. 24-25 | G16: Ambas | H16: SEPS Art. 10; SB Art. 24-25 | I16: Manual/Modelo SGSI, alcance, política, objetivos, mapa de procesos, matriz de riesgos, controles, indicadores, auditorías y mejora continua. | J16: 0.5 | K16: =IF(TRIM(J16&"")="","Por evaluar",IF(UPPER(TRIM(J16&""))="N/A","No aplica",IF(OR(J16=1,J16="1"),"Cumple",IF(OR(J16=0.5,J16="0.5"),"Parcial",IF(OR(J16=0,J16="0"),"No cumple","Revisar valor"))))) -> Parcial | M16: Aplicabilidad de CIS Controls alineado a NIST CSF | N16: CISO | O16: Alta | P16: Permanente | Q16: Núcleo de cumplimiento. | R16: R1 normativa + R2 anexos + R3 cruce | S16: Cl. 4.4, 5.2, 6.1, 8.1, 9.1, 10.2; A.5.1 Políticas de SI | T16: =IF(K16="Cumple","Mantener / evidenciar",IF(K16="Parcial","Cerrar brecha parcial",IF(K16="No cumple","Implementar control",IF(K16="No aplica","Sin acción","Levantar evidencia")))) -> Cerrar brecha parcial | U16: =IF(K16="Cumple","Mantener evidencia y revisión periódica",IF(K16="No aplica","Documentar justificación de no aplicabilidad",IF(K16="Por evaluar","Levantar evidencia y confirmar aplicabilidad",IF(K16="Parcial","Completar documentación/control y validar efectividad",IF(K16="No cumple","Diseñar, aprobar e implementar control requerido","Corregir valor de cumplimiento"))))) -> Completar documentación/control y validar efectividad | V16: =IF(K16="No cumple",IF(O16="Alta","0-30 días",IF(O16="Media","31-60 días","61-90 días")),IF(K16="Parcial",IF(O16="Alta","0-45 días",IF(O16="Media","31-75 días","61-120 días")),IF(K16="Por evaluar",IF(O16="Alta","0-15 días","0-30 días"),IF(K16="Cumple","Revisión periódica","No aplica")))) -> 0-45 días | W16: =IF(K16="No cumple",IF(O16="Alta",3,IF(O16="Media",2,1)),IF(K16="Parcial",IF(O16="Alta",2,IF(O16="Media",1.5,1)),IF(K16="Por evaluar",IF(O16="Alta",1.5,IF(O16="Media",1,0.5)),0))) -> 2 | X16: =IF(K16="No aplica","No aplica",IF(K16="Cumple","Mantenimiento",IF(K16="Por evaluar","Fase 0 - Evidencia/aplicabilidad",IF(OR(B16="Gobernanza",B16="SGSI",B16="Contexto y alcance"),"Fase 1 - Gobierno y SGSI",IF(OR(B16="Riesgos",B16="Procesos",B16="Personas"),"Fase 2 - Riesgos y operación",IF(OR(B16="Terceros",B16="Continuidad"),"Fase 3 - Continuidad y terceros",IF(OR(B16="Tecnología",B16="Accesos",B16="Ciberseguridad",B16="Vulnerabilidades",B16="Incidentes",B16="Monitoreo"),"Fase 4 - Controles técnicos","Fase 5 - Canales y datos"))))))) -> Fase 1 - Gobierno y SGSI
A17: 16 | B17: SGSI | C17: Políticas y procedimientos | D17: Definir políticas, procesos, procedimientos, roles y responsabilidades | E17: Las normas exigen normativa interna documentada, difundida, alineada a objetivos de negocio y con consecuencias por incumplimiento. | F17: SEPS Art. 9, 18, 24; Anexo 1; SB Art. 25 | G17: Ambas | H17: SEPS Anexo 1; SB Art. 25 | I17: Política de Seguridad de la Información, procedimientos, instructivos, RACI, flujos de aprobación y registro de difusión/aceptación. | J17: 0.5 | K17: =IF(TRIM(J17&"")="","Por evaluar",IF(UPPER(TRIM(J17&""))="N/A","No aplica",IF(OR(J17=1,J17="1"),"Cumple",IF(OR(J17=0.5,J17="0.5"),"Parcial",IF(OR(J17=0,J17="0"),"No cumple","Revisar valor"))))) -> Parcial | M17: Inicial, en construcción | N17: CISO / Procesos | O17: Alta | P17: Anual | Q17: Incluye ciberseguridad en SB. | R17: R1 normativa + R2 anexos + R3 cruce | S17: Cl. 5.2, 5.3, 7.5; A.5.1 Políticas; A.5.2 Roles; A.5.36 Cumplimiento; A.5.37 Procedimientos documentados | T17: =IF(K17="Cumple","Mantener / evidenciar",IF(K17="Parcial","Cerrar brecha parcial",IF(K17="No cumple","Implementar control",IF(K17="No aplica","Sin acción","Levantar evidencia")))) -> Cerrar brecha parcial | U17: =IF(K17="Cumple","Mantener evidencia y revisión periódica",IF(K17="No aplica","Documentar justificación de no aplicabilidad",IF(K17="Por evaluar","Levantar evidencia y confirmar aplicabilidad",IF(K17="Parcial","Completar documentación/control y validar efectividad",IF(K17="No cumple","Diseñar, aprobar e implementar control requerido","Corregir valor de cumplimiento"))))) -> Completar documentación/control y validar efectividad | V17: =IF(K17="No cumple",IF(O17="Alta","0-30 días",IF(O17="Media","31-60 días","61-90 días")),IF(K17="Parcial",IF(O17="Alta","0-45 días",IF(O17="Media","31-75 días","61-120 días")),IF(K17="Por evaluar",IF(O17="Alta","0-15 días","0-30 días"),IF(K17="Cumple","Revisión periódica","No aplica")))) -> 0-45 días | W17: =IF(K17="No cumple",IF(O17="Alta",3,IF(O17="Media",2,1)),IF(K17="Parcial",IF(O17="Alta",2,IF(O17="Media",1.5,1)),IF(K17="Por evaluar",IF(O17="Alta",1.5,IF(O17="Media",1,0.5)),0))) -> 2 | X17: =IF(K17="No aplica","No aplica",IF(K17="Cumple","Mantenimiento",IF(K17="Por evaluar","Fase 0 - Evidencia/aplicabilidad",IF(OR(B17="Gobernanza",B17="SGSI",B17="Contexto y alcance"),"Fase 1 - Gobierno y SGSI",IF(OR(B17="Riesgos",B17="Procesos",B17="Personas"),"Fase 2 - Riesgos y operación",IF(OR(B17="Terceros",B17="Continuidad"),"Fase 3 - Continuidad y terceros",IF(OR(B17="Tecnología",B17="Accesos",B17="Ciberseguridad",B17="Vulnerabilidades",B17="Incidentes",B17="Monitoreo"),"Fase 4 - Controles técnicos","Fase 5 - Canales y datos"))))))) -> Fase 1 - Gobierno y SGSI
A18: 17 | B18: SGSI | C18: Plan estratégico | D18: Contar con Plan Estratégico de Seguridad de la Información | E18: SEPS régimen general exige PESI; SB exige estrategia y objetivos de SI alineados a estrategia institucional. | F18: SEPS Art. 9 y 12; SB Art. 24 | G18: Ambas | H18: SEPS Art. 9/12; SB Art. 24 | I18: PESI aprobado, objetivos, iniciativas, responsables, presupuesto, indicadores, relación con plan estratégico institucional y seguimiento. | J18: 0.5 | K18: =IF(TRIM(J18&"")="","Por evaluar",IF(UPPER(TRIM(J18&""))="N/A","No aplica",IF(OR(J18=1,J18="1"),"Cumple",IF(OR(J18=0.5,J18="0.5"),"Parcial",IF(OR(J18=0,J18="0"),"No cumple","Revisar valor"))))) -> Parcial | M18: Se tiene pero en reforma | N18: CISO / Directorio | O18: Alta | P18: Anual o plurianual con seguimiento | Q18: Unifica PESI con estrategia SB. | R18: R1 normativa + R2 anexos + R3 cruce | S18: Cl. 6.2, 6.3; A.5.1 Políticas de SI; A.5.8 Seguridad en gestión de proyectos | T18: =IF(K18="Cumple","Mantener / evidenciar",IF(K18="Parcial","Cerrar brecha parcial",IF(K18="No cumple","Implementar control",IF(K18="No aplica","Sin acción","Levantar evidencia")))) -> Cerrar brecha parcial | U18: =IF(K18="Cumple","Mantener evidencia y revisión periódica",IF(K18="No aplica","Documentar justificación de no aplicabilidad",IF(K18="Por evaluar","Levantar evidencia y confirmar aplicabilidad",IF(K18="Parcial","Completar documentación/control y validar efectividad",IF(K18="No cumple","Diseñar, aprobar e implementar control requerido","Corregir valor de cumplimiento"))))) -> Completar documentación/control y validar efectividad | V18: =IF(K18="No cumple",IF(O18="Alta","0-30 días",IF(O18="Media","31-60 días","61-90 días")),IF(K18="Parcial",IF(O18="Alta","0-45 días",IF(O18="Media","31-75 días","61-120 días")),IF(K18="Por evaluar",IF(O18="Alta","0-15 días","0-30 días"),IF(K18="Cumple","Revisión periódica","No aplica")))) -> 0-45 días | W18: =IF(K18="No cumple",IF(O18="Alta",3,IF(O18="Media",2,1)),IF(K18="Parcial",IF(O18="Alta",2,IF(O18="Media",1.5,1)),IF(K18="Por evaluar",IF(O18="Alta",1.5,IF(O18="Media",1,0.5)),0))) -> 2 | X18: =IF(K18="No aplica","No aplica",IF(K18="Cumple","Mantenimiento",IF(K18="Por evaluar","Fase 0 - Evidencia/aplicabilidad",IF(OR(B18="Gobernanza",B18="SGSI",B18="Contexto y alcance"),"Fase 1 - Gobierno y SGSI",IF(OR(B18="Riesgos",B18="Procesos",B18="Personas"),"Fase 2 - Riesgos y operación",IF(OR(B18="Terceros",B18="Continuidad"),"Fase 3 - Continuidad y terceros",IF(OR(B18="Tecnología",B18="Accesos",B18="Ciberseguridad",B18="Vulnerabilidades",B18="Incidentes",B18="Monitoreo"),"Fase 4 - Controles técnicos","Fase 5 - Canales y datos"))))))) -> Fase 1 - Gobierno y SGSI
A19: 18 | B19: SGSI | C19: Plan operativo / plan de seguridad | D19: Planificar controles y acciones de mejora | E19: El plan debe permitir implementar controles identificados, acciones de mejora y mitigación de riesgos de SI y ciberseguridad. | F19: SB Art. 25; SEPS Anexo 1 y 2 | G19: Ambas | H19: SB Art. 25; SEPS Anexo 2 | I19: Plan de seguridad de la información, cartera de controles, plan de tratamiento, cronograma, responsables, costos, estado y evidencia de cierre. | J19: 0 | K19: =IF(TRIM(J19&"")="","Por evaluar",IF(UPPER(TRIM(J19&""))="N/A","No aplica",IF(OR(J19=1,J19="1"),"Cumple",IF(OR(J19=0.5,J19="0.5"),"Parcial",IF(OR(J19=0,J19="0"),"No cumple","Revisar valor"))))) -> No cumple | M19: Fase inicial, aun no se contempla | N19: CISO | O19: Alta | P19: Trimestral seguimiento / anual planificación | Q19: Equivale a plan de tratamiento y plan de controles. | R19: R1 normativa + R2 anexos + R3 cruce | S19: Cl. 6.1, 6.2, 8.1; A.5.8 Seguridad en proyectos; A.5.36 Cumplimiento | T19: =IF(K19="Cumple","Mantener / evidenciar",IF(K19="Parcial","Cerrar brecha parcial",IF(K19="No cumple","Implementar control",IF(K19="No aplica","Sin acción","Levantar evidencia")))) -> Implementar control | U19: =IF(K19="Cumple","Mantener evidencia y revisión periódica",IF(K19="No aplica","Documentar justificación de no aplicabilidad",IF(K19="Por evaluar","Levantar evidencia y confirmar aplicabilidad",IF(K19="Parcial","Completar documentación/control y validar efectividad",IF(K19="No cumple","Diseñar, aprobar e implementar control requerido","Corregir valor de cumplimiento"))))) -> Diseñar, aprobar e implementar control requerido | V19: =IF(K19="No cumple",IF(O19="Alta","0-30 días",IF(O19="Media","31-60 días","61-90 días")),IF(K19="Parcial",IF(O19="Alta","0-45 días",IF(O19="Media","31-75 días","61-120 días")),IF(K19="Por evaluar",IF(O19="Alta","0-15 días","0-30 días"),IF(K19="Cumple","Revisión periódica","No aplica")))) -> 0-30 días | W19: =IF(K19="No cumple",IF(O19="Alta",3,IF(O19="Media",2,1)),IF(K19="Parcial",IF(O19="Alta",2,IF(O19="Media",1.5,1)),IF(K19="Por evaluar",IF(O19="Alta",1.5,IF(O19="Media",1,0.5)),0))) -> 3 | X19: =IF(K19="No aplica","No aplica",IF(K19="Cumple","Mantenimiento",IF(K19="Por evaluar","Fase 0 - Evidencia/aplicabilidad",IF(OR(B19="Gobernanza",B19="SGSI",B19="Contexto y alcance"),"Fase 1 - Gobierno y SGSI",IF(OR(B19="Riesgos",B19="Procesos",B19="Personas"),"Fase 2 - Riesgos y operación",IF(OR(B19="Terceros",B19="Continuidad"),"Fase 3 - Continuidad y terceros",IF(OR(B19="Tecnología",B19="Accesos",B19="Ciberseguridad",B19="Vulnerabilidades",B19="Incidentes",B19="Monitoreo"),"Fase 4 - Controles técnicos","Fase 5 - Canales y datos"))))))) -> Fase 1 - Gobierno y SGSI
A20: 19 | B20: SGSI | C20: Capacitación y cultura | D20: Ejecutar plan de concienciación y formación | E20: SEPS exige plan/actividades de concienciación y formación; Anexo 1 pide evaluar el plan, medir madurez y capacitar a personal, proveedores, clientes, socios y usuarios. SB exige capacitación a empleados y clientes según alcance. | F20: SEPS Art. 9, 18, 24, Anexo 1; SB Art. 25, 27 | G20: Ambas | H20: SEPS Art. 9/Anexo 1; SB Art. 25/27 | I20: Plan anual de capacitación, campañas, registros de asistencia, evaluaciones, indicadores de madurez, campañas a clientes/proveedores cuando aplique. | J20: 1 | K20: =IF(TRIM(J20&"")="","Por evaluar",IF(UPPER(TRIM(J20&""))="N/A","No aplica",IF(OR(J20=1,J20="1"),"Cumple",IF(OR(J20=0.5,J20="0.5"),"Parcial",IF(OR(J20=0,J20="0"),"No cumple","Revisar valor"))))) -> Cumple | M20: Creada campaña anual | N20: CISO / Talento Humano / Marketing | O20: Media | P20: Anual con ejecución continua | Q20: Incluye cultura interna y externa. | R20: R1 normativa + R2 anexos + R3 cruce | S20: Cl. 7.2, 7.3; A.6.3 Concienciación, educación y formación en SI | T20: =IF(K20="Cumple","Mantener / evidenciar",IF(K20="Parcial","Cerrar brecha parcial",IF(K20="No cumple","Implementar control",IF(K20="No aplica","Sin acción","Levantar evidencia")))) -> Mantener / evidenciar | U20: =IF(K20="Cumple","Mantener evidencia y revisión periódica",IF(K20="No aplica","Documentar justificación de no aplicabilidad",IF(K20="Por evaluar","Levantar evidencia y confirmar aplicabilidad",IF(K20="Parcial","Completar documentación/control y validar efectividad",IF(K20="No cumple","Diseñar, aprobar e implementar control requerido","Corregir valor de cumplimiento"))))) -> Mantener evidencia y revisión periódica | V20: =IF(K20="No cumple",IF(O20="Alta","0-30 días",IF(O20="Media","31-60 días","61-90 días")),IF(K20="Parcial",IF(O20="Alta","0-45 días",IF(O20="Media","31-75 días","61-120 días")),IF(K20="Por evaluar",IF(O20="Alta","0-15 días","0-30 días"),IF(K20="Cumple","Revisión periódica","No aplica")))) -> Revisión periódica | W20: =IF(K20="No cumple",IF(O20="Alta",3,IF(O20="Media",2,1)),IF(K20="Parcial",IF(O20="Alta",2,IF(O20="Media",1.5,1)),IF(K20="Por evaluar",IF(O20="Alta",1.5,IF(O20="Media",1,0.5)),0))) -> 0 | X20: =IF(K20="No aplica","No aplica",IF(K20="Cumple","Mantenimiento",IF(K20="Por evaluar","Fase 0 - Evidencia/aplicabilidad",IF(OR(B20="Gobernanza",B20="SGSI",B20="Contexto y alcance"),"Fase 1 - Gobierno y SGSI",IF(OR(B20="Riesgos",B20="Procesos",B20="Personas"),"Fase 2 - Riesgos y operación",IF(OR(B20="Terceros",B20="Continuidad"),"Fase 3 - Continuidad y terceros",IF(OR(B20="Tecnología",B20="Accesos",B20="Ciberseguridad",B20="Vulnerabilidades",B20="Incidentes",B20="Monitoreo"),"Fase 4 - Controles técnicos","Fase 5 - Canales y datos"))))))) -> Mantenimiento
A21: 20 | B21: SGSI | C21: Evidencia documental | D21: Generar y conservar documentación de la gestión | E21: SEPS exige que el OSI/responsable genere documentación que evidencie la gestión; SB exige evidencias de comités, informes, monitoreos, auditorías, pruebas y reportes. | F21: SEPS Art. 12, 20, 26; SB Art. 24-27 | G21: Ambas | H21: SEPS y SB | I21: Repositorio SGSI con control de versiones, evidencias por requisito, actas, informes, tickets, aprobaciones, reportes y matrices. | J21: 0 | K21: =IF(TRIM(J21&"")="","Por evaluar",IF(UPPER(TRIM(J21&""))="N/A","No aplica",IF(OR(J21=1,J21="1"),"Cumple",IF(OR(J21=0.5,J21="0.5"),"Parcial",IF(OR(J21=0,J21="0"),"No cumple","Revisar valor"))))) -> No cumple | M21: Aún no se ejecuta CSI, pero se va a ejecutar | N21: CISO / PMO / Procesos | O21: Alta | P21: Permanente | Q21: Necesario para due diligence y supervisión. | R21: R1 normativa + R2 anexos + R3 cruce | S21: Cl. 7.5; A.5.33 Protección de registros; A.5.37 Procedimientos operativos documentados | T21: =IF(K21="Cumple","Mantener / evidenciar",IF(K21="Parcial","Cerrar brecha parcial",IF(K21="No cumple","Implementar control",IF(K21="No aplica","Sin acción","Levantar evidencia")))) -> Implementar control | U21: =IF(K21="Cumple","Mantener evidencia y revisión periódica",IF(K21="No aplica","Documentar justificación de no aplicabilidad",IF(K21="Por evaluar","Levantar evidencia y confirmar aplicabilidad",IF(K21="Parcial","Completar documentación/control y validar efectividad",IF(K21="No cumple","Diseñar, aprobar e implementar control requerido","Corregir valor de cumplimiento"))))) -> Diseñar, aprobar e implementar control requerido | V21: =IF(K21="No cumple",IF(O21="Alta","0-30 días",IF(O21="Media","31-60 días","61-90 días")),IF(K21="Parcial",IF(O21="Alta","0-45 días",IF(O21="Media","31-75 días","61-120 días")),IF(K21="Por evaluar",IF(O21="Alta","0-15 días","0-30 días"),IF(K21="Cumple","Revisión periódica","No aplica")))) -> 0-30 días | W21: =IF(K21="No cumple",IF(O21="Alta",3,IF(O21="Media",2,1)),IF(K21="Parcial",IF(O21="Alta",2,IF(O21="Media",1.5,1)),IF(K21="Por evaluar",IF(O21="Alta",1.5,IF(O21="Media",1,0.5)),0))) -> 3 | X21: =IF(K21="No aplica","No aplica",IF(K21="Cumple","Mantenimiento",IF(K21="Por evaluar","Fase 0 - Evidencia/aplicabilidad",IF(OR(B21="Gobernanza",B21="SGSI",B21="Contexto y alcance"),"Fase 1 - Gobierno y SGSI",IF(OR(B21="Riesgos",B21="Procesos",B21="Personas"),"Fase 2 - Riesgos y operación",IF(OR(B21="Terceros",B21="Continuidad"),"Fase 3 - Continuidad y terceros",IF(OR(B21="Tecnología",B21="Accesos",B21="Ciberseguridad",B21="Vulnerabilidades",B21="Incidentes",B21="Monitoreo"),"Fase 4 - Controles técnicos","Fase 5 - Canales y datos"))))))) -> Fase 1 - Gobierno y SGSI
A22: 21 | B22: SGSI | C22: Políticas específicas SEPS | D22: Mantener normativa interna mínima de seguridad | E22: SEPS Anexo 1 menciona políticas/control de clasificación, gestión de riesgos, accesos físicos y tecnológicos, incidentes, software, infraestructura tecnológica, recursos humanos, seguridad física, terceros y ciberseguridad. | F22: SEPS Anexo 1, páginas controles obligatorios | G22: SEPS | H22: SEPS Anexo 1 | I22: Catálogo de políticas y procedimientos mínimos: clasificación, riesgos SI, accesos, incidentes, software, infraestructura, RRHH, seguridad física, terceros, ciberseguridad. | J22: 0.5 | K22: =IF(TRIM(J22&"")="","Por evaluar",IF(UPPER(TRIM(J22&""))="N/A","No aplica",IF(OR(J22=1,J22="1"),"Cumple",IF(OR(J22=0.5,J22="0.5"),"Parcial",IF(OR(J22=0,J22="0"),"No cumple","Revisar valor"))))) -> Parcial | M22: En elaboración, pendiente: Accesos Incidentes SW Infraestructura TTHH Seg. Física Terceros Ciberseguridad | N22: CISO / TIC / Talento Humano | O22: Alta | P22: Anual | Q22: Sin equivalente exacto como listado en SB; se cruza con Art. 25. | R22: R1 normativa + R2 anexos + R3 cruce | S22: Cl. 5.2, 7.5; A.5.1 Políticas; A.5.10 Uso aceptable; A.5.14 Transferencia de información; A.5.15 Control de acceso; A.8.13 Respaldo; A.8.24 Criptografía; A.8.32 Gestión de cambios | T22: =IF(K22="Cumple","Mantener / evidenciar",IF(K22="Parcial","Cerrar brecha parcial",IF(K22="No cumple","Implementar control",IF(K22="No aplica","Sin acción","Levantar evidencia")))) -> Cerrar brecha parcial | U22: =IF(K22="Cumple","Mantener evidencia y revisión periódica",IF(K22="No aplica","Documentar justificación de no aplicabilidad",IF(K22="Por evaluar","Levantar evidencia y confirmar aplicabilidad",IF(K22="Parcial","Completar documentación/control y validar efectividad",IF(K22="No cumple","Diseñar, aprobar e implementar control requerido","Corregir valor de cumplimiento"))))) -> Completar documentación/control y validar efectividad | V22: =IF(K22="No cumple",IF(O22="Alta","0-30 días",IF(O22="Media","31-60 días","61-90 días")),IF(K22="Parcial",IF(O22="Alta","0-45 días",IF(O22="Media","31-75 días","61-120 días")),IF(K22="Por evaluar",IF(O22="Alta","0-15 días","0-30 días"),IF(K22="Cumple","Revisión periódica","No aplica")))) -> 0-45 días | W22: =IF(K22="No cumple",IF(O22="Alta",3,IF(O22="Media",2,1)),IF(K22="Parcial",IF(O22="Alta",2,IF(O22="Media",1.5,1)),IF(K22="Por evaluar",IF(O22="Alta",1.5,IF(O22="Media",1,0.5)),0))) -> 2 | X22: =IF(K22="No aplica","No aplica",IF(K22="Cumple","Mantenimiento",IF(K22="Por evaluar","Fase 0 - Evidencia/aplicabilidad",IF(OR(B22="Gobernanza",B22="SGSI",B22="Contexto y alcance"),"Fase 1 - Gobierno y SGSI",IF(OR(B22="Riesgos",B22="Procesos",B22="Personas"),"Fase 2 - Riesgos y operación",IF(OR(B22="Terceros",B22="Continuidad"),"Fase 3 - Continuidad y terceros",IF(OR(B22="Tecnología",B22="Accesos",B22="Ciberseguridad",B22="Vulnerabilidades",B22="Incidentes",B22="Monitoreo"),"Fase 4 - Controles técnicos","Fase 5 - Canales y datos"))))))) -> Fase 1 - Gobierno y SGSI
A23: 22 | B23: Riesgos | C23: Metodología | D23: Definir metodología de riesgos de seguridad de la información | E23: Debe identificar, medir, controlar/mitigar y monitorear riesgos asociados a activos de información; SEPS permite tomar como referencia Anexo 2 y SB exige alineación con riesgo operativo. | F23: SEPS Art. 9, 18, 24, Anexo 2; SB Art. 25 | G23: Ambas | H23: SEPS Anexo 2; SB Art. 25 | I23: Metodología de riesgos SI aprobada, escalas de probabilidad/impacto, criterios de CID/privacidad, apetito/tolerancia, cálculo inherente/residual y tratamiento. | J23: 0.5 | K23: =IF(TRIM(J23&"")="","Por evaluar",IF(UPPER(TRIM(J23&""))="N/A","No aplica",IF(OR(J23=1,J23="1"),"Cumple",IF(OR(J23=0.5,J23="0.5"),"Parcial",IF(OR(J23=0,J23="0"),"No cumple","Revisar valor"))))) -> Parcial | M23: Realizada en revisión, procesos | N23: CISO / Riesgos | O23: Alta | P23: Anual | Q23: Alineada a riesgo operativo. | R23: R1 normativa + R2 anexos + R3 cruce | S23: Cl. 6.1, 8.2, 8.3; A.5.7 Inteligencia de amenazas; A.5.36 Cumplimiento de políticas y estándares | T23: =IF(K23="Cumple","Mantener / evidenciar",IF(K23="Parcial","Cerrar brecha parcial",IF(K23="No cumple","Implementar control",IF(K23="No aplica","Sin acción","Levantar evidencia")))) -> Cerrar brecha parcial | U23: =IF(K23="Cumple","Mantener evidencia y revisión periódica",IF(K23="No aplica","Documentar justificación de no aplicabilidad",IF(K23="Por evaluar","Levantar evidencia y confirmar aplicabilidad",IF(K23="Parcial","Completar documentación/control y validar efectividad",IF(K23="No cumple","Diseñar, aprobar e implementar control requerido","Corregir valor de cumplimiento"))))) -> Completar documentación/control y validar efectividad | V23: =IF(K23="No cumple",IF(O23="Alta","0-30 días",IF(O23="Media","31-60 días","61-90 días")),IF(K23="Parcial",IF(O23="Alta","0-45 días",IF(O23="Media","31-75 días","61-120 días")),IF(K23="Por evaluar",IF(O23="Alta","0-15 días","0-30 días"),IF(K23="Cumple","Revisión periódica","No aplica")))) -> 0-45 días | W23: =IF(K23="No cumple",IF(O23="Alta",3,IF(O23="Media",2,1)),IF(K23="Parcial",IF(O23="Alta",2,IF(O23="Media",1.5,1)),IF(K23="Por evaluar",IF(O23="Alta",1.5,IF(O23="Media",1,0.5)),0))) -> 2 | X23: =IF(K23="No aplica","No aplica",IF(K23="Cumple","Mantenimiento",IF(K23="Por evaluar","Fase 0 - Evidencia/aplicabilidad",IF(OR(B23="Gobernanza",B23="SGSI",B23="Contexto y alcance"),"Fase 1 - Gobierno y SGSI",IF(OR(B23="Riesgos",B23="Procesos",B23="Personas"),"Fase 2 - Riesgos y operación",IF(OR(B23="Terceros",B23="Continuidad"),"Fase 3 - Continuidad y terceros",IF(OR(B23="Tecnología",B23="Accesos",B23="Ciberseguridad",B23="Vulnerabilidades",B23="Incidentes",B23="Monitoreo"),"Fase 4 - Controles técnicos","Fase 5 - Canales y datos"))))))) -> Fase 2 - Riesgos y operación
A24: 23 | B24: Riesgos | C24: Identificación | D24: Identificar amenazas, vulnerabilidades, causas, eventos y consecuencias | E24: SEPS Anexo 2 exige describir evento/amenaza, causa/vulnerabilidad y consecuencia; SB exige identificar riesgos por proceso, línea de negocio, tipo de evento, factor y fallas/insuficiencias. | F24: SEPS Anexo 2; SB Art. 5 y 8 | G24: Ambas | H24: SEPS Anexo 2; SB Art. 5/8 | I24: Matriz de riesgos SI/operativos con causa, evento, consecuencia, activo, proceso, responsable, controles existentes y brecha. | J24: 0.5 | K24: =IF(TRIM(J24&"")="","Por evaluar",IF(UPPER(TRIM(J24&""))="N/A","No aplica",IF(OR(J24=1,J24="1"),"Cumple",IF(OR(J24=0.5,J24="0.5"),"Parcial",IF(OR(J24=0,J24="0"),"No cumple","Revisar valor"))))) -> Parcial | M24: En construcción | N24: CISO / Riesgos / Dueños de procesos | O24: Alta | P24: Semestral o ante cambios | Q24: Cumple trazabilidad de riesgo. | R24: R1 normativa + R2 anexos + R3 cruce | S24: Cl. 6.1, 8.2; A.5.7 Inteligencia de amenazas; A.8.8 Gestión de vulnerabilidades técnicas | T24: =IF(K24="Cumple","Mantener / evidenciar",IF(K24="Parcial","Cerrar brecha parcial",IF(K24="No cumple","Implementar control",IF(K24="No aplica","Sin acción","Levantar evidencia")))) -> Cerrar brecha parcial | U24: =IF(K24="Cumple","Mantener evidencia y revisión periódica",IF(K24="No aplica","Documentar justificación de no aplicabilidad",IF(K24="Por evaluar","Levantar evidencia y confirmar aplicabilidad",IF(K24="Parcial","Completar documentación/control y validar efectividad",IF(K24="No cumple","Diseñar, aprobar e implementar control requerido","Corregir valor de cumplimiento"))))) -> Completar documentación/control y validar efectividad | V24: =IF(K24="No cumple",IF(O24="Alta","0-30 días",IF(O24="Media","31-60 días","61-90 días")),IF(K24="Parcial",IF(O24="Alta","0-45 días",IF(O24="Media","31-75 días","61-120 días")),IF(K24="Por evaluar",IF(O24="Alta","0-15 días","0-30 días"),IF(K24="Cumple","Revisión periódica","No aplica")))) -> 0-45 días | W24: =IF(K24="No cumple",IF(O24="Alta",3,IF(O24="Media",2,1)),IF(K24="Parcial",IF(O24="Alta",2,IF(O24="Media",1.5,1)),IF(K24="Por evaluar",IF(O24="Alta",1.5,IF(O24="Media",1,0.5)),0))) -> 2 | X24: =IF(K24="No aplica","No aplica",IF(K24="Cumple","Mantenimiento",IF(K24="Por evaluar","Fase 0 - Evidencia/aplicabilidad",IF(OR(B24="Gobernanza",B24="SGSI",B24="Contexto y alcance"),"Fase 1 - Gobierno y SGSI",IF(OR(B24="Riesgos",B24="Procesos",B24="Personas"),"Fase 2 - Riesgos y operación",IF(OR(B24="Terceros",B24="Continuidad"),"Fase 3 - Continuidad y terceros",IF(OR(B24="Tecnología",B24="Accesos",B24="Ciberseguridad",B24="Vulnerabilidades",B24="Incidentes",B24="Monitoreo"),"Fase 4 - Controles técnicos","Fase 5 - Canales y datos"))))))) -> Fase 2 - Riesgos y operación
A25: 24 | B25: Riesgos | C25: Medición | D25: Medir riesgo inherente y residual | E25: SEPS propone nivel de riesgo = probabilidad x impacto y probabilidad = amenaza x vulnerabilidad; SB exige medición por probabilidad e impacto y reevaluación periódica por eventos de pérdida. | F25: SEPS Anexo 2; SB Art. 6 | G25: Ambas | H25: SEPS Anexo 2; SB Art. 6 | I25: Matriz de valoración inherente/residual, mapa de calor, criterios aprobados y evidencia de reevaluación por eventos/incidentes. | J25: 0.5 | K25: =IF(TRIM(J25&"")="","Por evaluar",IF(UPPER(TRIM(J25&""))="N/A","No aplica",IF(OR(J25=1,J25="1"),"Cumple",IF(OR(J25=0.5,J25="0.5"),"Parcial",IF(OR(J25=0,J25="0"),"No cumple","Revisar valor"))))) -> Parcial | M25: En construcción | N25: Riesgos / CISO | O25: Alta | P25: Trimestral/Semestral | Q25: Base de priorización. | R25: R1 normativa + R2 anexos + R3 cruce | S25: Cl. 6.1, 9.1; A.5.36 Cumplimiento de políticas y estándares | T25: =IF(K25="Cumple","Mantener / evidenciar",IF(K25="Parcial","Cerrar brecha parcial",IF(K25="No cumple","Implementar control",IF(K25="No aplica","Sin acción","Levantar evidencia")))) -> Cerrar brecha parcial | U25: =IF(K25="Cumple","Mantener evidencia y revisión periódica",IF(K25="No aplica","Documentar justificación de no aplicabilidad",IF(K25="Por evaluar","Levantar evidencia y confirmar aplicabilidad",IF(K25="Parcial","Completar documentación/control y validar efectividad",IF(K25="No cumple","Diseñar, aprobar e implementar control requerido","Corregir valor de cumplimiento"))))) -> Completar documentación/control y validar efectividad | V25: =IF(K25="No cumple",IF(O25="Alta","0-30 días",IF(O25="Media","31-60 días","61-90 días")),IF(K25="Parcial",IF(O25="Alta","0-45 días",IF(O25="Media","31-75 días","61-120 días")),IF(K25="Por evaluar",IF(O25="Alta","0-15 días","0-30 días"),IF(K25="Cumple","Revisión periódica","No aplica")))) -> 0-45 días | W25: =IF(K25="No cumple",IF(O25="Alta",3,IF(O25="Media",2,1)),IF(K25="Parcial",IF(O25="Alta",2,IF(O25="Media",1.5,1)),IF(K25="Por evaluar",IF(O25="Alta",1.5,IF(O25="Media",1,0.5)),0))) -> 2 | X25: =IF(K25="No aplica","No aplica",IF(K25="Cumple","Mantenimiento",IF(K25="Por evaluar","Fase 0 - Evidencia/aplicabilidad",IF(OR(B25="Gobernanza",B25="SGSI",B25="Contexto y alcance"),"Fase 1 - Gobierno y SGSI",IF(OR(B25="Riesgos",B25="Procesos",B25="Personas"),"Fase 2 - Riesgos y operación",IF(OR(B25="Terceros",B25="Continuidad"),"Fase 3 - Continuidad y terceros",IF(OR(B25="Tecnología",B25="Accesos",B25="Ciberseguridad",B25="Vulnerabilidades",B25="Incidentes",B25="Monitoreo"),"Fase 4 - Controles técnicos","Fase 5 - Canales y datos"))))))) -> Fase 2 - Riesgos y operación
A26: 25 | B26: Riesgos | C26: Controles y mitigación | D26: Implementar controles y planes de mitigación | E26: SB exige planes de mitigación formalmente establecidos y validados; SEPS exige controles para mitigar riesgos identificados considerando presupuesto y criticidad. | F26: SEPS Anexo 2; SB Art. 7 | G26: Ambas | H26: SEPS Anexo 2; SB Art. 7 | I26: Plan de tratamiento de riesgos, controles asociados, responsables, plazos, presupuesto, seguimiento y validación de eficacia. | J26: 0 | K26: =IF(TRIM(J26&"")="","Por evaluar",IF(UPPER(TRIM(J26&""))="N/A","No aplica",IF(OR(J26=1,J26="1"),"Cumple",IF(OR(J26=0.5,J26="0.5"),"Parcial",IF(OR(J26=0,J26="0"),"No cumple","Revisar valor"))))) -> No cumple | M26: Noviembre | N26: CISO / Dueños de proceso | O26: Alta | P26: Mensual seguimiento / anual revisión | Q26: Vincula riesgos con controles. | R26: R1 normativa + R2 anexos + R3 cruce | S26: Cl. 8.3, 10.1; A.5.36 Cumplimiento; A.8.8 Gestión de vulnerabilidades técnicas | T26: =IF(K26="Cumple","Mantener / evidenciar",IF(K26="Parcial","Cerrar brecha parcial",IF(K26="No cumple","Implementar control",IF(K26="No aplica","Sin acción","Levantar evidencia")))) -> Implementar control | U26: =IF(K26="Cumple","Mantener evidencia y revisión periódica",IF(K26="No aplica","Documentar justificación de no aplicabilidad",IF(K26="Por evaluar","Levantar evidencia y confirmar aplicabilidad",IF(K26="Parcial","Completar documentación/control y validar efectividad",IF(K26="No cumple","Diseñar, aprobar e implementar control requerido","Corregir valor de cumplimiento"))))) -> Diseñar, aprobar e implementar control requerido | V26: =IF(K26="No cumple",IF(O26="Alta","0-30 días",IF(O26="Media","31-60 días","61-90 días")),IF(K26="Parcial",IF(O26="Alta","0-45 días",IF(O26="Media","31-75 días","61-120 días")),IF(K26="Por evaluar",IF(O26="Alta","0-15 días","0-30 días"),IF(K26="Cumple","Revisión periódica","No aplica")))) -> 0-30 días | W26: =IF(K26="No cumple",IF(O26="Alta",3,IF(O26="Media",2,1)),IF(K26="Parcial",IF(O26="Alta",2,IF(O26="Media",1.5,1)),IF(K26="Por evaluar",IF(O26="Alta",1.5,IF(O26="Media",1,0.5)),0))) -> 3 | X26: =IF(K26="No aplica","No aplica",IF(K26="Cumple","Mantenimiento",IF(K26="Por evaluar","Fase 0 - Evidencia/aplicabilidad",IF(OR(B26="Gobernanza",B26="SGSI",B26="Contexto y alcance"),"Fase 1 - Gobierno y SGSI",IF(OR(B26="Riesgos",B26="Procesos",B26="Personas"),"Fase 2 - Riesgos y operación",IF(OR(B26="Terceros",B26="Continuidad"),"Fase 3 - Continuidad y terceros",IF(OR(B26="Tecnología",B26="Accesos",B26="Ciberseguridad",B26="Vulnerabilidades",B26="Incidentes",B26="Monitoreo"),"Fase 4 - Controles técnicos","Fase 5 - Canales y datos"))))))) -> Fase 2 - Riesgos y operación
A27: 26 | B27: Riesgos | C27: Efectividad de controles | D27: Evaluar diseño, formalización, ejecución y eficacia de controles | E27: SEPS Anexo 2 clasifica controles de efectivo a inexistente/inefectivo; SB exige evaluar diseño y efectividad de controles en primera línea y auditoría. | F27: SEPS Anexo 2; SB Art. 4, 7, 11, 25 | G27: Ambas | H27: SEPS Anexo 2; SB Art. 4/7/11/25 | I27: Matriz de evaluación de controles, pruebas de diseño/operación, resultados, evidencia y planes correctivos. | J27: 0 | K27: =IF(TRIM(J27&"")="","Por evaluar",IF(UPPER(TRIM(J27&""))="N/A","No aplica",IF(OR(J27=1,J27="1"),"Cumple",IF(OR(J27=0.5,J27="0.5"),"Parcial",IF(OR(J27=0,J27="0"),"No cumple","Revisar valor"))))) -> No cumple | M27: 2027 | N27: CISO / Riesgos / Auditoría | O27: Alta | P27: Semestral/Anual | Q27: Control de segunda/tercera línea. | R27: R1 normativa + R2 anexos + R3 cruce | S27: Cl. 9.1, 9.2; A.5.35 Revisión independiente; A.5.36 Cumplimiento | T27: =IF(K27="Cumple","Mantener / evidenciar",IF(K27="Parcial","Cerrar brecha parcial",IF(K27="No cumple","Implementar control",IF(K27="No aplica","Sin acción","Levantar evidencia")))) -> Implementar control | U27: =IF(K27="Cumple","Mantener evidencia y revisión periódica",IF(K27="No aplica","Documentar justificación de no aplicabilidad",IF(K27="Por evaluar","Levantar evidencia y confirmar aplicabilidad",IF(K27="Parcial","Completar documentación/control y validar efectividad",IF(K27="No cumple","Diseñar, aprobar e implementar control requerido","Corregir valor de cumplimiento"))))) -> Diseñar, aprobar e implementar control requerido | V27: =IF(K27="No cumple",IF(O27="Alta","0-30 días",IF(O27="Media","31-60 días","61-90 días")),IF(K27="Parcial",IF(O27="Alta","0-45 días",IF(O27="Media","31-75 días","61-120 días")),IF(K27="Por evaluar",IF(O27="Alta","0-15 días","0-30 días"),IF(K27="Cumple","Revisión periódica","No aplica")))) -> 0-30 días | W27: =IF(K27="No cumple",IF(O27="Alta",3,IF(O27="Media",2,1)),IF(K27="Parcial",IF(O27="Alta",2,IF(O27="Media",1.5,1)),IF(K27="Por evaluar",IF(O27="Alta",1.5,IF(O27="Media",1,0.5)),0))) -> 3 | X27: =IF(K27="No aplica","No aplica",IF(K27="Cumple","Mantenimiento",IF(K27="Por evaluar","Fase 0 - Evidencia/aplicabilidad",IF(OR(B27="Gobernanza",B27="SGSI",B27="Contexto y alcance"),"Fase 1 - Gobierno y SGSI",IF(OR(B27="Riesgos",B27="Procesos",B27="Personas"),"Fase 2 - Riesgos y operación",IF(OR(B27="Terceros",B27="Continuidad"),"Fase 3 - Continuidad y terceros",IF(OR(B27="Tecnología",B27="Accesos",B27="Ciberseguridad",B27="Vulnerabilidades",B27="Incidentes",B27="Monitoreo"),"Fase 4 - Controles técnicos","Fase 5 - Canales y datos"))))))) -> Fase 2 - Riesgos y operación
A28: 27 | B28: Riesgos | C28: Reportes | D28: Monitorear y reportar riesgos, indicadores, mapas y planes | E28: SB exige reportes de KRI, cumplimiento de planes, matriz y mapas de riesgos, e informes trimestrales al CAIR; SEPS exige consolidar riesgos SI en matriz de riesgos y seguimiento. | F28: SEPS Art. 12/20; SB Art. 8 | G28: Ambas | H28: SEPS Art. 12/20; SB Art. 8 | I28: Informe trimestral de riesgos SI/operativos, KRI/KPI, mapa de calor, avance de mitigación, conclusiones y recomendaciones. | J28: 0 | K28: =IF(TRIM(J28&"")="","Por evaluar",IF(UPPER(TRIM(J28&""))="N/A","No aplica",IF(OR(J28=1,J28="1"),"Cumple",IF(OR(J28=0.5,J28="0.5"),"Parcial",IF(OR(J28=0,J28="0"),"No cumple","Revisar valor"))))) -> No cumple | M28: 2027 | N28: Riesgos / CISO | O28: Alta | P28: Trimestral | Q28: Requisito más estricto SB trimestral. | R28: R1 normativa + R2 anexos + R3 cruce | S28: Cl. 9.1, 9.3; A.5.36 Cumplimiento de políticas, reglas y estándares | T28: =IF(K28="Cumple","Mantener / evidenciar",IF(K28="Parcial","Cerrar brecha parcial",IF(K28="No cumple","Implementar control",IF(K28="No aplica","Sin acción","Levantar evidencia")))) -> Implementar control | U28: =IF(K28="Cumple","Mantener evidencia y revisión periódica",IF(K28="No aplica","Documentar justificación de no aplicabilidad",IF(K28="Por evaluar","Levantar evidencia y confirmar aplicabilidad",IF(K28="Parcial","Completar documentación/control y validar efectividad",IF(K28="No cumple","Diseñar, aprobar e implementar control requerido","Corregir valor de cumplimiento"))))) -> Diseñar, aprobar e implementar control requerido | V28: =IF(K28="No cumple",IF(O28="Alta","0-30 días",IF(O28="Media","31-60 días","61-90 días")),IF(K28="Parcial",IF(O28="Alta","0-45 días",IF(O28="Media","31-75 días","61-120 días")),IF(K28="Por evaluar",IF(O28="Alta","0-15 días","0-30 días"),IF(K28="Cumple","Revisión periódica","No aplica")))) -> 0-30 días | W28: =IF(K28="No cumple",IF(O28="Alta",3,IF(O28="Media",2,1)),IF(K28="Parcial",IF(O28="Alta",2,IF(O28="Media",1.5,1)),IF(K28="Por evaluar",IF(O28="Alta",1.5,IF(O28="Media",1,0.5)),0))) -> 3 | X28: =IF(K28="No aplica","No aplica",IF(K28="Cumple","Mantenimiento",IF(K28="Por evaluar","Fase 0 - Evidencia/aplicabilidad",IF(OR(B28="Gobernanza",B28="SGSI",B28="Contexto y alcance"),"Fase 1 - Gobierno y SGSI",IF(OR(B28="Riesgos",B28="Procesos",B28="Personas"),"Fase 2 - Riesgos y operación",IF(OR(B28="Terceros",B28="Continuidad"),"Fase 3 - Continuidad y terceros",IF(OR(B28="Tecnología",B28="Accesos",B28="Ciberseguridad",B28="Vulnerabilidades",B28="Incidentes",B28="Monitoreo"),"Fase 4 - Controles técnicos","Fase 5 - Canales y datos"))))))) -> Fase 2 - Riesgos y operación
A29: 28 | B29: Riesgos | C29: Base de eventos | D29: Mantener base/bitácora de eventos de riesgo | E29: SB exige base centralizada de eventos de riesgo operativo, incluidos seguridad de la información, terceros y continuidad; SEPS simplificado exige registro en bitácora de eventos de riesgo. | F29: SEPS Art. 24; SB Art. 9 | G29: Ambas | H29: SEPS Art. 24; SB Art. 9 | I29: Base centralizada de eventos/incidentes, campos de clasificación, pérdida cuantitativa, frecuencia, probabilidad, causa raíz, acciones y responsables. | J29: 1 | K29: =IF(TRIM(J29&"")="","Por evaluar",IF(UPPER(TRIM(J29&""))="N/A","No aplica",IF(OR(J29=1,J29="1"),"Cumple",IF(OR(J29=0.5,J29="0.5"),"Parcial",IF(OR(J29=0,J29="0"),"No cumple","Revisar valor"))))) -> Cumple | M29: Eramba | N29: Riesgos / CISO / Mesa de ayuda | O29: Alta | P29: Permanente | Q29: Puede integrarse con GLPI/SIEM/GRC. | R29: R1 normativa + R2 anexos + R3 cruce | S29: A.5.24 Planificación de incidentes; A.5.25 Evaluación de eventos; A.5.26 Respuesta a incidentes; A.5.27 Aprendizaje; A.5.28 Evidencia; A.5.33 Registros | T29: =IF(K29="Cumple","Mantener / evidenciar",IF(K29="Parcial","Cerrar brecha parcial",IF(K29="No cumple","Implementar control",IF(K29="No aplica","Sin acción","Levantar evidencia")))) -> Mantener / evidenciar | U29: =IF(K29="Cumple","Mantener evidencia y revisión periódica",IF(K29="No aplica","Documentar justificación de no aplicabilidad",IF(K29="Por evaluar","Levantar evidencia y confirmar aplicabilidad",IF(K29="Parcial","Completar documentación/control y validar efectividad",IF(K29="No cumple","Diseñar, aprobar e implementar control requerido","Corregir valor de cumplimiento"))))) -> Mantener evidencia y revisión periódica | V29: =IF(K29="No cumple",IF(O29="Alta","0-30 días",IF(O29="Media","31-60 días","61-90 días")),IF(K29="Parcial",IF(O29="Alta","0-45 días",IF(O29="Media","31-75 días","61-120 días")),IF(K29="Por evaluar",IF(O29="Alta","0-15 días","0-30 días"),IF(K29="Cumple","Revisión periódica","No aplica")))) -> Revisión periódica | W29: =IF(K29="No cumple",IF(O29="Alta",3,IF(O29="Media",2,1)),IF(K29="Parcial",IF(O29="Alta",2,IF(O29="Media",1.5,1)),IF(K29="Por evaluar",IF(O29="Alta",1.5,IF(O29="Media",1,0.5)),0))) -> 0 | X29: =IF(K29="No aplica","No aplica",IF(K29="Cumple","Mantenimiento",IF(K29="Por evaluar","Fase 0 - Evidencia/aplicabilidad",IF(OR(B29="Gobernanza",B29="SGSI",B29="Contexto y alcance"),"Fase 1 - Gobierno y SGSI",IF(OR(B29="Riesgos",B29="Procesos",B29="Personas"),"Fase 2 - Riesgos y operación",IF(OR(B29="Terceros",B29="Continuidad"),"Fase 3 - Continuidad y terceros",IF(OR(B29="Tecnología",B29="Accesos",B29="Ciberseguridad",B29="Vulnerabilidades",B29="Incidentes",B29="Monitoreo"),"Fase 4 - Controles técnicos","Fase 5 - Canales y datos"))))))) -> Mantenimiento
A30: 29 | B30: Riesgos | C30: Comunicación | D30: Definir política formal de comunicación de eventos | E30: SB exige política de comunicación formal sobre eventos de riesgo operativo que deban informarse interna o externamente y evaluación del impacto de la información a comunicar. | F30: SB Art. 10 | G30: SB | H30: SB Art. 10 | I30: Política/procedimiento de comunicación de eventos, criterios de severidad, canales, aprobadores, comunicación a regulador/clientes/proveedores y plantillas. | J30: 0 | K30: =IF(TRIM(J30&"")="","Por evaluar",IF(UPPER(TRIM(J30&""))="N/A","No aplica",IF(OR(J30=1,J30="1"),"Cumple",IF(OR(J30=0.5,J30="0.5"),"Parcial",IF(OR(J30=0,J30="0"),"No cumple","Revisar valor"))))) -> No cumple | N30: Riesgos / CISO / Comunicaciones / Legal | O30: Alta | P30: Anual | Q30: Complementa notificación de incidentes. | R30: R1 normativa + R2 anexos + R3 cruce | S30: A.5.5 Contacto con autoridades; A.5.24 Gestión de incidentes; A.6.8 Reporte de eventos de SI | T30: =IF(K30="Cumple","Mantener / evidenciar",IF(K30="Parcial","Cerrar brecha parcial",IF(K30="No cumple","Implementar control",IF(K30="No aplica","Sin acción","Levantar evidencia")))) -> Implementar control | U30: =IF(K30="Cumple","Mantener evidencia y revisión periódica",IF(K30="No aplica","Documentar justificación de no aplicabilidad",IF(K30="Por evaluar","Levantar evidencia y confirmar aplicabilidad",IF(K30="Parcial","Completar documentación/control y validar efectividad",IF(K30="No cumple","Diseñar, aprobar e implementar control requerido","Corregir valor de cumplimiento"))))) -> Diseñar, aprobar e implementar control requerido | V30: =IF(K30="No cumple",IF(O30="Alta","0-30 días",IF(O30="Media","31-60 días","61-90 días")),IF(K30="Parcial",IF(O30="Alta","0-45 días",IF(O30="Media","31-75 días","61-120 días")),IF(K30="Por evaluar",IF(O30="Alta","0-15 días","0-30 días"),IF(K30="Cumple","Revisión periódica","No aplica")))) -> 0-30 días | W30: =IF(K30="No cumple",IF(O30="Alta",3,IF(O30="Media",2,1)),IF(K30="Parcial",IF(O30="Alta",2,IF(O30="Media",1.5,1)),IF(K30="Por evaluar",IF(O30="Alta",1.5,IF(O30="Media",1,0.5)),0))) -> 3 | X30: =IF(K30="No aplica","No aplica",IF(K30="Cumple","Mantenimiento",IF(K30="Por evaluar","Fase 0 - Evidencia/aplicabilidad",IF(OR(B30="Gobernanza",B30="SGSI",B30="Contexto y alcance"),"Fase 1 - Gobierno y SGSI",IF(OR(B30="Riesgos",B30="Procesos",B30="Personas"),"Fase 2 - Riesgos y operación",IF(OR(B30="Terceros",B30="Continuidad"),"Fase 3 - Continuidad y terceros",IF(OR(B30="Tecnología",B30="Accesos",B30="Ciberseguridad",B30="Vulnerabilidades",B30="Incidentes",B30="Monitoreo"),"Fase 4 - Controles técnicos","Fase 5 - Canales y datos"))))))) -> Fase 2 - Riesgos y operación
A31: 30 | B31: Riesgos | C31: Taxonomía Basel | D31: Usar catálogo de eventos de riesgo operativo | E31: SB Anexo 1 lista categorías de riesgo operativo, incluyendo fraude interno/externo, prácticas con clientes, daños a activos, interrupción por fallas de TI y deficiencias con procesos/proveedores. | F31: SB Anexo 1 | G31: SB | H31: SB Anexo 1 | I31: Catálogo de eventos de riesgo operativo mapeado a SI/ciberseguridad, continuidad, terceros, fraude, privacidad y tecnología. | J31: 0 | K31: =IF(TRIM(J31&"")="","Por evaluar",IF(UPPER(TRIM(J31&""))="N/A","No aplica",IF(OR(J31=1,J31="1"),"Cumple",IF(OR(J31=0.5,J31="0.5"),"Parcial",IF(OR(J31=0,J31="0"),"No cumple","Revisar valor"))))) -> No cumple | N31: Riesgos | O31: Media | P31: Anual | Q31: Usar para clasificar eventos en la base centralizada. | R31: R1 normativa + R2 anexos + R3 cruce | S31: Cl. 6.1; A.5.24 Planificación de incidentes; A.5.25 Evaluación de eventos; A.5.27 Aprendizaje | T31: =IF(K31="Cumple","Mantener / evidenciar",IF(K31="Parcial","Cerrar brecha parcial",IF(K31="No cumple","Implementar control",IF(K31="No aplica","Sin acción","Levantar evidencia")))) -> Implementar control | U31: =IF(K31="Cumple","Mantener evidencia y revisión periódica",IF(K31="No aplica","Documentar justificación de no aplicabilidad",IF(K31="Por evaluar","Levantar evidencia y confirmar aplicabilidad",IF(K31="Parcial","Completar documentación/control y validar efectividad",IF(K31="No cumple","Diseñar, aprobar e implementar control requerido","Corregir valor de cumplimiento"))))) -> Diseñar, aprobar e implementar control requerido | V31: =IF(K31="No cumple",IF(O31="Alta","0-30 días",IF(O31="Media","31-60 días","61-90 días")),IF(K31="Parcial",IF(O31="Alta","0-45 días",IF(O31="Media","31-75 días","61-120 días")),IF(K31="Por evaluar",IF(O31="Alta","0-15 días","0-30 días"),IF(K31="Cumple","Revisión periódica","No aplica")))) -> 31-60 días | W31: =IF(K31="No cumple",IF(O31="Alta",3,IF(O31="Media",2,1)),IF(K31="Parcial",IF(O31="Alta",2,IF(O31="Media",1.5,1)),IF(K31="Por evaluar",IF(O31="Alta",1.5,IF(O31="Media",1,0.5)),0))) -> 2 | X31: =IF(K31="No aplica","No aplica",IF(K31="Cumple","Mantenimiento",IF(K31="Por evaluar","Fase 0 - Evidencia/aplicabilidad",IF(OR(B31="Gobernanza",B31="SGSI",B31="Contexto y alcance"),"Fase 1 - Gobierno y SGSI",IF(OR(B31="Riesgos",B31="Procesos",B31="Personas"),"Fase 2 - Riesgos y operación",IF(OR(B31="Terceros",B31="Continuidad"),"Fase 3 - Continuidad y terceros",IF(OR(B31="Tecnología",B31="Accesos",B31="Ciberseguridad",B31="Vulnerabilidades",B31="Incidentes",B31="Monitoreo"),"Fase 4 - Controles técnicos","Fase 5 - Canales y datos"))))))) -> Fase 2 - Riesgos y operación
A32: 31 | B32: Activos e información | C32: Inventario | D32: Mantener inventario de activos de información | E32: Debe existir inventario acorde al alcance del SGSI con clasificación, valor, requerimientos legales, sensibilidad, criticidad, propietario, custodio y ubicación. | F32: SEPS Art. 10, 18, Anexo 1; SB Art. 25 | G32: Ambas | H32: SEPS Art. 10/Anexo 1; SB Art. 25 | I32: Inventario de activos, CMDB o matriz de activos, identificación de activos críticos/sensibles, propietario/custodio, ubicación física/lógica y relación con procesos. | J32: 0.5 | K32: =IF(TRIM(J32&"")="","Por evaluar",IF(UPPER(TRIM(J32&""))="N/A","No aplica",IF(OR(J32=1,J32="1"),"Cumple",IF(OR(J32=0.5,J32="0.5"),"Parcial",IF(OR(J32=0,J32="0"),"No cumple","Revisar valor"))))) -> Parcial | M32: En proceso | N32: CISO / TIC / Dueños de activos | O32: Alta | P32: Trimestral/Semestral | Q32: Control básico de SGSI. | R32: R1 normativa + R2 anexos + R3 cruce | S32: A.5.9 Inventario de información y activos asociados | T32: =IF(K32="Cumple","Mantener / evidenciar",IF(K32="Parcial","Cerrar brecha parcial",IF(K32="No cumple","Implementar control",IF(K32="No aplica","Sin acción","Levantar evidencia")))) -> Cerrar brecha parcial | U32: =IF(K32="Cumple","Mantener evidencia y revisión periódica",IF(K32="No aplica","Documentar justificación de no aplicabilidad",IF(K32="Por evaluar","Levantar evidencia y confirmar aplicabilidad",IF(K32="Parcial","Completar documentación/control y validar efectividad",IF(K32="No cumple","Diseñar, aprobar e implementar control requerido","Corregir valor de cumplimiento"))))) -> Completar documentación/control y validar efectividad | V32: =IF(K32="No cumple",IF(O32="Alta","0-30 días",IF(O32="Media","31-60 días","61-90 días")),IF(K32="Parcial",IF(O32="Alta","0-45 días",IF(O32="Media","31-75 días","61-120 días")),IF(K32="Por evaluar",IF(O32="Alta","0-15 días","0-30 días"),IF(K32="Cumple","Revisión periódica","No aplica")))) -> 0-45 días | W32: =IF(K32="No cumple",IF(O32="Alta",3,IF(O32="Media",2,1)),IF(K32="Parcial",IF(O32="Alta",2,IF(O32="Media",1.5,1)),IF(K32="Por evaluar",IF(O32="Alta",1.5,IF(O32="Media",1,0.5)),0))) -> 2 | X32: =IF(K32="No aplica","No aplica",IF(K32="Cumple","Mantenimiento",IF(K32="Por evaluar","Fase 0 - Evidencia/aplicabilidad",IF(OR(B32="Gobernanza",B32="SGSI",B32="Contexto y alcance"),"Fase 1 - Gobierno y SGSI",IF(OR(B32="Riesgos",B32="Procesos",B32="Personas"),"Fase 2 - Riesgos y operación",IF(OR(B32="Terceros",B32="Continuidad"),"Fase 3 - Continuidad y terceros",IF(OR(B32="Tecnología",B32="Accesos",B32="Ciberseguridad",B32="Vulnerabilidades",B32="Incidentes",B32="Monitoreo"),"Fase 4 - Controles técnicos","Fase 5 - Canales y datos"))))))) -> Fase 5 - Canales y datos
A33: 32 | B33: Activos e información | C33: Clasificación | D33: Clasificar información y activos | E33: SEPS exige identificación y clasificación de tipos y activos de información con criterios CID; Anexo 2 pide privacidad público/uso interno/restringido. SB exige clasificación por valor, requerimiento legal, sensibilidad y criticidad. | F33: SEPS Art. 10 y Anexo 2; SB Art. 25 | G33: Ambas | H33: SEPS Anexo 2; SB Art. 25 | I33: Procedimiento de clasificación, etiquetas, criterios CID/privacidad/legal/criticidad, matriz de clasificación y controles por nivel. | J33: 0.5 | K33: =IF(TRIM(J33&"")="","Por evaluar",IF(UPPER(TRIM(J33&""))="N/A","No aplica",IF(OR(J33=1,J33="1"),"Cumple",IF(OR(J33=0.5,J33="0.5"),"Parcial",IF(OR(J33=0,J33="0"),"No cumple","Revisar valor"))))) -> Parcial | N33: CISO / Dueños de información | O33: Alta | P33: Anual y al crear/modificar activos | Q33: Homologar categorías para ambas normas. | R33: R1 normativa + R2 anexos + R3 cruce | S33: A.5.12 Clasificación de la información; A.5.13 Etiquetado de la información | T33: =IF(K33="Cumple","Mantener / evidenciar",IF(K33="Parcial","Cerrar brecha parcial",IF(K33="No cumple","Implementar control",IF(K33="No aplica","Sin acción","Levantar evidencia")))) -> Cerrar brecha parcial | U33: =IF(K33="Cumple","Mantener evidencia y revisión periódica",IF(K33="No aplica","Documentar justificación de no aplicabilidad",IF(K33="Por evaluar","Levantar evidencia y confirmar aplicabilidad",IF(K33="Parcial","Completar documentación/control y validar efectividad",IF(K33="No cumple","Diseñar, aprobar e implementar control requerido","Corregir valor de cumplimiento"))))) -> Completar documentación/control y validar efectividad | V33: =IF(K33="No cumple",IF(O33="Alta","0-30 días",IF(O33="Media","31-60 días","61-90 días")),IF(K33="Parcial",IF(O33="Alta","0-45 días",IF(O33="Media","31-75 días","61-120 días")),IF(K33="Por evaluar",IF(O33="Alta","0-15 días","0-30 días"),IF(K33="Cumple","Revisión periódica","No aplica")))) -> 0-45 días | W33: =IF(K33="No cumple",IF(O33="Alta",3,IF(O33="Media",2,1)),IF(K33="Parcial",IF(O33="Alta",2,IF(O33="Media",1.5,1)),IF(K33="Por evaluar",IF(O33="Alta",1.5,IF(O33="Media",1,0.5)),0))) -> 2 | X33: =IF(K33="No aplica","No aplica",IF(K33="Cumple","Mantenimiento",IF(K33="Por evaluar","Fase 0 - Evidencia/aplicabilidad",IF(OR(B33="Gobernanza",B33="SGSI",B33="Contexto y alcance"),"Fase 1 - Gobierno y SGSI",IF(OR(B33="Riesgos",B33="Procesos",B33="Personas"),"Fase 2 - Riesgos y operación",IF(OR(B33="Terceros",B33="Continuidad"),"Fase 3 - Continuidad y terceros",IF(OR(B33="Tecnología",B33="Accesos",B33="Ciberseguridad",B33="Vulnerabilidades",B33="Incidentes",B33="Monitoreo"),"Fase 4 - Controles técnicos","Fase 5 - Canales y datos"))))))) -> Fase 5 - Canales y datos
A34: 33 | B34: Activos e información | C34: Propietarios | D34: Designar propietarios de activos de información | E34: SB define responsabilidades de propietarios: clasificar, revisar inventario, definir restricciones de uso/acceso y autorizar cambios funcionales o directos a bases de datos. | F34: SB Art. 25 | G34: SB | H34: SB Art. 25 | I34: Matriz de propietarios/custodios, responsabilidades formalizadas, flujo de autorización de cambios y revisión periódica de accesos. | J34: 0.5 | K34: =IF(TRIM(J34&"")="","Por evaluar",IF(UPPER(TRIM(J34&""))="N/A","No aplica",IF(OR(J34=1,J34="1"),"Cumple",IF(OR(J34=0.5,J34="0.5"),"Parcial",IF(OR(J34=0,J34="0"),"No cumple","Revisar valor"))))) -> Parcial | N34: CISO / Dueños de información | O34: Alta | P34: Anual | Q34: Complementa custodia/responsable SEPS. | R34: R1 normativa + R2 anexos + R3 cruce | S34: A.5.2 Roles y responsabilidades; A.5.9 Inventario de activos | T34: =IF(K34="Cumple","Mantener / evidenciar",IF(K34="Parcial","Cerrar brecha parcial",IF(K34="No cumple","Implementar control",IF(K34="No aplica","Sin acción","Levantar evidencia")))) -> Cerrar brecha parcial | U34: =IF(K34="Cumple","Mantener evidencia y revisión periódica",IF(K34="No aplica","Documentar justificación de no aplicabilidad",IF(K34="Por evaluar","Levantar evidencia y confirmar aplicabilidad",IF(K34="Parcial","Completar documentación/control y validar efectividad",IF(K34="No cumple","Diseñar, aprobar e implementar control requerido","Corregir valor de cumplimiento"))))) -> Completar documentación/control y validar efectividad | V34: =IF(K34="No cumple",IF(O34="Alta","0-30 días",IF(O34="Media","31-60 días","61-90 días")),IF(K34="Parcial",IF(O34="Alta","0-45 días",IF(O34="Media","31-75 días","61-120 días")),IF(K34="Por evaluar",IF(O34="Alta","0-15 días","0-30 días"),IF(K34="Cumple","Revisión periódica","No aplica")))) -> 0-45 días | W34: =IF(K34="No cumple",IF(O34="Alta",3,IF(O34="Media",2,1)),IF(K34="Parcial",IF(O34="Alta",2,IF(O34="Media",1.5,1)),IF(K34="Por evaluar",IF(O34="Alta",1.5,IF(O34="Media",1,0.5)),0))) -> 2 | X34: =IF(K34="No aplica","No aplica",IF(K34="Cumple","Mantenimiento",IF(K34="Por evaluar","Fase 0 - Evidencia/aplicabilidad",IF(OR(B34="Gobernanza",B34="SGSI",B34="Contexto y alcance"),"Fase 1 - Gobierno y SGSI",IF(OR(B34="Riesgos",B34="Procesos",B34="Personas"),"Fase 2 - Riesgos y operación",IF(OR(B34="Terceros",B34="Continuidad"),"Fase 3 - Continuidad y terceros",IF(OR(B34="Tecnología",B34="Accesos",B34="Ciberseguridad",B34="Vulnerabilidades",B34="Incidentes",B34="Monitoreo"),"Fase 4 - Controles técnicos","Fase 5 - Canales y datos"))))))) -> Fase 5 - Canales y datos
A35: 34 | B35: Activos e información | C35: Protección de información | D35: Proteger documentos, medios, dispositivos e intercambio electrónico | E35: Deben existir medidas para proteger información en documentos, medios de almacenamiento, dispositivos externos e intercambio electrónico contra robo, uso o divulgación no autorizada. | F35: SB Art. 25; SEPS Anexo 1 | G35: Ambas | H35: SB Art. 25; SEPS Anexo 1 | I35: Procedimiento de manejo de información, controles de DLP, cifrado, almacenamiento seguro, envío seguro, gestión de medios y autorización de traslado. | J35: 0 | K35: =IF(TRIM(J35&"")="","Por evaluar",IF(UPPER(TRIM(J35&""))="N/A","No aplica",IF(OR(J35=1,J35="1"),"Cumple",IF(OR(J35=0.5,J35="0.5"),"Parcial",IF(OR(J35=0,J35="0"),"No cumple","Revisar valor"))))) -> No cumple | N35: CISO / TIC / Usuarios custodios | O35: Alta | P35: Permanente | Q35: Abarca información física y digital. | R35: R1 normativa + R2 anexos + R3 cruce | S35: A.5.10 Uso aceptable; A.5.14 Transferencia de información; A.7.10 Medios de almacenamiento; A.8.12 Prevención de fuga de datos | T35: =IF(K35="Cumple","Mantener / evidenciar",IF(K35="Parcial","Cerrar brecha parcial",IF(K35="No cumple","Implementar control",IF(K35="No aplica","Sin acción","Levantar evidencia")))) -> Implementar control | U35: =IF(K35="Cumple","Mantener evidencia y revisión periódica",IF(K35="No aplica","Documentar justificación de no aplicabilidad",IF(K35="Por evaluar","Levantar evidencia y confirmar aplicabilidad",IF(K35="Parcial","Completar documentación/control y validar efectividad",IF(K35="No cumple","Diseñar, aprobar e implementar control requerido","Corregir valor de cumplimiento"))))) -> Diseñar, aprobar e implementar control requerido | V35: =IF(K35="No cumple",IF(O35="Alta","0-30 días",IF(O35="Media","31-60 días","61-90 días")),IF(K35="Parcial",IF(O35="Alta","0-45 días",IF(O35="Media","31-75 días","61-120 días")),IF(K35="Por evaluar",IF(O35="Alta","0-15 días","0-30 días"),IF(K35="Cumple","Revisión periódica","No aplica")))) -> 0-30 días | W35: =IF(K35="No cumple",IF(O35="Alta",3,IF(O35="Media",2,1)),IF(K35="Parcial",IF(O35="Alta",2,IF(O35="Media",1.5,1)),IF(K35="Por evaluar",IF(O35="Alta",1.5,IF(O35="Media",1,0.5)),0))) -> 3 | X35: =IF(K35="No aplica","No aplica",IF(K35="Cumple","Mantenimiento",IF(K35="Por evaluar","Fase 0 - Evidencia/aplicabilidad",IF(OR(B35="Gobernanza",B35="SGSI",B35="Contexto y alcance"),"Fase 1 - Gobierno y SGSI",IF(OR(B35="Riesgos",B35="Procesos",B35="Personas"),"Fase 2 - Riesgos y operación",IF(OR(B35="Terceros",B35="Continuidad"),"Fase 3 - Continuidad y terceros",IF(OR(B35="Tecnología",B35="Accesos",B35="Ciberseguridad",B35="Vulnerabilidades",B35="Incidentes",B35="Monitoreo"),"Fase 4 - Controles técnicos","Fase 5 - Canales y datos"))))))) -> Fase 5 - Canales y datos
A36: 35 | B36: Activos e información | C36: Eliminación segura | D36: Eliminar información crítica de forma segura | E36: SB exige procedimientos de eliminación segura de información crítica y control de eliminación en bases de datos/repositorios de proveedores después del servicio. | F36: SB Art. 25 | G36: SB | H36: SB Art. 25 | I36: Procedimiento de eliminación segura, actas de destrucción, borrado seguro, certificados de proveedores y retención legal/regulatoria. | J36: 0 | K36: =IF(TRIM(J36&"")="","Por evaluar",IF(UPPER(TRIM(J36&""))="N/A","No aplica",IF(OR(J36=1,J36="1"),"Cumple",IF(OR(J36=0.5,J36="0.5"),"Parcial",IF(OR(J36=0,J36="0"),"No cumple","Revisar valor"))))) -> No cumple | N36: CISO / TIC / Proveedores | O36: Media | P36: Según evento y revisión anual | Q36: Clave para salida de servicios. | R36: R1 normativa + R2 anexos + R3 cruce | S36: A.8.10 Eliminación de información; A.7.14 Eliminación o reutilización segura de equipos | T36: =IF(K36="Cumple","Mantener / evidenciar",IF(K36="Parcial","Cerrar brecha parcial",IF(K36="No cumple","Implementar control",IF(K36="No aplica","Sin acción","Levantar evidencia")))) -> Implementar control | U36: =IF(K36="Cumple","Mantener evidencia y revisión periódica",IF(K36="No aplica","Documentar justificación de no aplicabilidad",IF(K36="Por evaluar","Levantar evidencia y confirmar aplicabilidad",IF(K36="Parcial","Completar documentación/control y validar efectividad",IF(K36="No cumple","Diseñar, aprobar e implementar control requerido","Corregir valor de cumplimiento"))))) -> Diseñar, aprobar e implementar control requerido | V36: =IF(K36="No cumple",IF(O36="Alta","0-30 días",IF(O36="Media","31-60 días","61-90 días")),IF(K36="Parcial",IF(O36="Alta","0-45 días",IF(O36="Media","31-75 días","61-120 días")),IF(K36="Por evaluar",IF(O36="Alta","0-15 días","0-30 días"),IF(K36="Cumple","Revisión periódica","No aplica")))) -> 31-60 días | W36: =IF(K36="No cumple",IF(O36="Alta",3,IF(O36="Media",2,1)),IF(K36="Parcial",IF(O36="Alta",2,IF(O36="Media",1.5,1)),IF(K36="Por evaluar",IF(O36="Alta",1.5,IF(O36="Media",1,0.5)),0))) -> 2 | X36: =IF(K36="No aplica","No aplica",IF(K36="Cumple","Mantenimiento",IF(K36="Por evaluar","Fase 0 - Evidencia/aplicabilidad",IF(OR(B36="Gobernanza",B36="SGSI",B36="Contexto y alcance"),"Fase 1 - Gobierno y SGSI",IF(OR(B36="Riesgos",B36="Procesos",B36="Personas"),"Fase 2 - Riesgos y operación",IF(OR(B36="Terceros",B36="Continuidad"),"Fase 3 - Continuidad y terceros",IF(OR(B36="Tecnología",B36="Accesos",B36="Ciberseguridad",B36="Vulnerabilidades",B36="Incidentes",B36="Monitoreo"),"Fase 4 - Controles técnicos","Fase 5 - Canales y datos"))))))) -> Fase 5 - Canales y datos
A37: 36 | B37: Activos e información | C37: Respaldo y resguardo | D37: Respaldar información sensible o crítica y probar respaldos | E37: SEPS exige respaldar información sensible/crítica en ubicaciones adecuadas y evidenciar funcionamiento; SB exige respaldos periódicos con frecuencia, verificación, eliminación y transporte seguro a ubicación remota. | F37: SEPS Anexo 1; SB Art. 15 | G37: Ambas | H37: SEPS Anexo 1; SB Art. 15 | I37: Política de backups, calendario, pruebas de restauración, evidencias de respaldos, cifrado, resguardo remoto y reporte de éxito/fallas. | J37: 0.5 | K37: =IF(TRIM(J37&"")="","Por evaluar",IF(UPPER(TRIM(J37&""))="N/A","No aplica",IF(OR(J37=1,J37="1"),"Cumple",IF(OR(J37=0.5,J37="0.5"),"Parcial",IF(OR(J37=0,J37="0"),"No cumple","Revisar valor"))))) -> Parcial | N37: TIC / CISO / Continuidad | O37: Alta | P37: Según criticidad; prueba al menos anual | Q37: Relacionado con BCP/DRP. | R37: R1 normativa + R2 anexos + R3 cruce | S37: A.8.13 Respaldo de información; A.5.30 Preparación TIC para continuidad | T37: =IF(K37="Cumple","Mantener / evidenciar",IF(K37="Parcial","Cerrar brecha parcial",IF(K37="No cumple","Implementar control",IF(K37="No aplica","Sin acción","Levantar evidencia")))) -> Cerrar brecha parcial | U37: =IF(K37="Cumple","Mantener evidencia y revisión periódica",IF(K37="No aplica","Documentar justificación de no aplicabilidad",IF(K37="Por evaluar","Levantar evidencia y confirmar aplicabilidad",IF(K37="Parcial","Completar documentación/control y validar efectividad",IF(K37="No cumple","Diseñar, aprobar e implementar control requerido","Corregir valor de cumplimiento"))))) -> Completar documentación/control y validar efectividad | V37: =IF(K37="No cumple",IF(O37="Alta","0-30 días",IF(O37="Media","31-60 días","61-90 días")),IF(K37="Parcial",IF(O37="Alta","0-45 días",IF(O37="Media","31-75 días","61-120 días")),IF(K37="Por evaluar",IF(O37="Alta","0-15 días","0-30 días"),IF(K37="Cumple","Revisión periódica","No aplica")))) -> 0-45 días | W37: =IF(K37="No cumple",IF(O37="Alta",3,IF(O37="Media",2,1)),IF(K37="Parcial",IF(O37="Alta",2,IF(O37="Media",1.5,1)),IF(K37="Por evaluar",IF(O37="Alta",1.5,IF(O37="Media",1,0.5)),0))) -> 2 | X37: =IF(K37="No aplica","No aplica",IF(K37="Cumple","Mantenimiento",IF(K37="Por evaluar","Fase 0 - Evidencia/aplicabilidad",IF(OR(B37="Gobernanza",B37="SGSI",B37="Contexto y alcance"),"Fase 1 - Gobierno y SGSI",IF(OR(B37="Riesgos",B37="Procesos",B37="Personas"),"Fase 2 - Riesgos y operación",IF(OR(B37="Terceros",B37="Continuidad"),"Fase 3 - Continuidad y terceros",IF(OR(B37="Tecnología",B37="Accesos",B37="Ciberseguridad",B37="Vulnerabilidades",B37="Incidentes",B37="Monitoreo"),"Fase 4 - Controles técnicos","Fase 5 - Canales y datos"))))))) -> Fase 5 - Canales y datos
A38: 37 | B38: Procesos | C38: Mapa de procesos | D38: Identificar procesos agregadores, críticos y de soporte | E38: SEPS Anexo 1 exige documento de procesos agregadores; SB Art. 13 exige mapa de procesos gobernantes, productivos y habilitantes, asignados a líneas de negocio y metodología de diseño/control/actualización. | F38: SEPS Anexo 1; SB Art. 13 | G38: Ambas | H38: SEPS Anexo 1; SB Art. 13 | I38: Mapa de procesos, inventario de procesos críticos/agregadores, dueños, diagramas, controles, riesgos asociados y actualización. | J38: 0 | K38: =IF(TRIM(J38&"")="","Por evaluar",IF(UPPER(TRIM(J38&""))="N/A","No aplica",IF(OR(J38=1,J38="1"),"Cumple",IF(OR(J38=0.5,J38="0.5"),"Parcial",IF(OR(J38=0,J38="0"),"No cumple","Revisar valor"))))) -> No cumple | M38: Procesos | N38: Procesos / CISO / Riesgos | O38: Alta | P38: Anual | Q38: Base para alcance SGSI y BIA. | R38: R1 normativa + R2 anexos + R3 cruce | S38: Cl. 4.4; A.5.8 Seguridad en gestión de proyectos; A.5.29 SI durante interrupciones; A.5.30 Preparación TIC para continuidad | T38: =IF(K38="Cumple","Mantener / evidenciar",IF(K38="Parcial","Cerrar brecha parcial",IF(K38="No cumple","Implementar control",IF(K38="No aplica","Sin acción","Levantar evidencia")))) -> Implementar control | U38: =IF(K38="Cumple","Mantener evidencia y revisión periódica",IF(K38="No aplica","Documentar justificación de no aplicabilidad",IF(K38="Por evaluar","Levantar evidencia y confirmar aplicabilidad",IF(K38="Parcial","Completar documentación/control y validar efectividad",IF(K38="No cumple","Diseñar, aprobar e implementar control requerido","Corregir valor de cumplimiento"))))) -> Diseñar, aprobar e implementar control requerido | V38: =IF(K38="No cumple",IF(O38="Alta","0-30 días",IF(O38="Media","31-60 días","61-90 días")),IF(K38="Parcial",IF(O38="Alta","0-45 días",IF(O38="Media","31-75 días","61-120 días")),IF(K38="Por evaluar",IF(O38="Alta","0-15 días","0-30 días"),IF(K38="Cumple","Revisión periódica","No aplica")))) -> 0-30 días | W38: =IF(K38="No cumple",IF(O38="Alta",3,IF(O38="Media",2,1)),IF(K38="Parcial",IF(O38="Alta",2,IF(O38="Media",1.5,1)),IF(K38="Por evaluar",IF(O38="Alta",1.5,IF(O38="Media",1,0.5)),0))) -> 3 | X38: =IF(K38="No aplica","No aplica",IF(K38="Cumple","Mantenimiento",IF(K38="Por evaluar","Fase 0 - Evidencia/aplicabilidad",IF(OR(B38="Gobernanza",B38="SGSI",B38="Contexto y alcance"),"Fase 1 - Gobierno y SGSI",IF(OR(B38="Riesgos",B38="Procesos",B38="Personas"),"Fase 2 - Riesgos y operación",IF(OR(B38="Terceros",B38="Continuidad"),"Fase 3 - Continuidad y terceros",IF(OR(B38="Tecnología",B38="Accesos",B38="Ciberseguridad",B38="Vulnerabilidades",B38="Incidentes",B38="Monitoreo"),"Fase 4 - Controles técnicos","Fase 5 - Canales y datos"))))))) -> Fase 2 - Riesgos y operación
A39: 38 | B39: Procesos | C39: Controles de proceso | D39: Definir responsables, controles y planes de acción por proceso | E39: SB exige responsables de procesos, identificación de clientes, productos/servicios, riesgos, controles y planes de mitigación para reducir eventos de riesgo operativo. | F39: SB Art. 13 | G39: SB | H39: SB Art. 13 | I39: Caracterización de procesos, matriz RACI, controles, indicadores, riesgos y planes de acción por proceso. | J39: 0 | K39: =IF(TRIM(J39&"")="","Por evaluar",IF(UPPER(TRIM(J39&""))="N/A","No aplica",IF(OR(J39=1,J39="1"),"Cumple",IF(OR(J39=0.5,J39="0.5"),"Parcial",IF(OR(J39=0,J39="0"),"No cumple","Revisar valor"))))) -> No cumple | M39: Procesos | N39: Procesos / Dueños de proceso / Riesgos | O39: Media | P39: Anual | Q39: Apoya gestión integral de riesgos. | R39: R1 normativa + R2 anexos + R3 cruce | S39: Cl. 8.1, 9.1; A.5.36 Cumplimiento; A.5.37 Procedimientos operativos documentados | T39: =IF(K39="Cumple","Mantener / evidenciar",IF(K39="Parcial","Cerrar brecha parcial",IF(K39="No cumple","Implementar control",IF(K39="No aplica","Sin acción","Levantar evidencia")))) -> Implementar control | U39: =IF(K39="Cumple","Mantener evidencia y revisión periódica",IF(K39="No aplica","Documentar justificación de no aplicabilidad",IF(K39="Por evaluar","Levantar evidencia y confirmar aplicabilidad",IF(K39="Parcial","Completar documentación/control y validar efectividad",IF(K39="No cumple","Diseñar, aprobar e implementar control requerido","Corregir valor de cumplimiento"))))) -> Diseñar, aprobar e implementar control requerido | V39: =IF(K39="No cumple",IF(O39="Alta","0-30 días",IF(O39="Media","31-60 días","61-90 días")),IF(K39="Parcial",IF(O39="Alta","0-45 días",IF(O39="Media","31-75 días","61-120 días")),IF(K39="Por evaluar",IF(O39="Alta","0-15 días","0-30 días"),IF(K39="Cumple","Revisión periódica","No aplica")))) -> 31-60 días | W39: =IF(K39="No cumple",IF(O39="Alta",3,IF(O39="Media",2,1)),IF(K39="Parcial",IF(O39="Alta",2,IF(O39="Media",1.5,1)),IF(K39="Por evaluar",IF(O39="Alta",1.5,IF(O39="Media",1,0.5)),0))) -> 2 | X39: =IF(K39="No aplica","No aplica",IF(K39="Cumple","Mantenimiento",IF(K39="Por evaluar","Fase 0 - Evidencia/aplicabilidad",IF(OR(B39="Gobernanza",B39="SGSI",B39="Contexto y alcance"),"Fase 1 - Gobierno y SGSI",IF(OR(B39="Riesgos",B39="Procesos",B39="Personas"),"Fase 2 - Riesgos y operación",IF(OR(B39="Terceros",B39="Continuidad"),"Fase 3 - Continuidad y terceros",IF(OR(B39="Tecnología",B39="Accesos",B39="Ciberseguridad",B39="Vulnerabilidades",B39="Incidentes",B39="Monitoreo"),"Fase 4 - Controles técnicos","Fase 5 - Canales y datos"))))))) -> Fase 2 - Riesgos y operación
A40: 39 | B40: Personas | C40: Ciclo de vida laboral | D40: Gestionar incorporación, permanencia y desvinculación con enfoque de riesgo | E40: SB exige políticas, procesos y procedimientos para incorporación, permanencia y desvinculación; debe considerar competencias, puestos críticos, reemplazos y continuidad. | F40: SB Art. 14 | G40: SB | H40: SB Art. 14 | I40: Procedimiento de ciclo de vida de personal, checklist de ingreso/cambio/salida, inducción, capacitación, matriz de reemplazo y control de accesos. | J40: 1 | K40: =IF(TRIM(J40&"")="","Por evaluar",IF(UPPER(TRIM(J40&""))="N/A","No aplica",IF(OR(J40=1,J40="1"),"Cumple",IF(OR(J40=0.5,J40="0.5"),"Parcial",IF(OR(J40=0,J40="0"),"No cumple","Revisar valor"))))) -> Cumple | M40: Ejecuta TTHH | N40: Talento Humano / CISO / TIC | O40: Alta | P40: Cada ingreso/cambio/salida | Q40: Integra Seguridad RRHH. | R40: R1 normativa + R2 anexos + R3 cruce | S40: A.6.1 Investigación previa; A.6.2 Términos laborales; A.6.5 Responsabilidades tras terminación/cambio; A.5.11 Devolución de activos | T40: =IF(K40="Cumple","Mantener / evidenciar",IF(K40="Parcial","Cerrar brecha parcial",IF(K40="No cumple","Implementar control",IF(K40="No aplica","Sin acción","Levantar evidencia")))) -> Mantener / evidenciar | U40: =IF(K40="Cumple","Mantener evidencia y revisión periódica",IF(K40="No aplica","Documentar justificación de no aplicabilidad",IF(K40="Por evaluar","Levantar evidencia y confirmar aplicabilidad",IF(K40="Parcial","Completar documentación/control y validar efectividad",IF(K40="No cumple","Diseñar, aprobar e implementar control requerido","Corregir valor de cumplimiento"))))) -> Mantener evidencia y revisión periódica | V40: =IF(K40="No cumple",IF(O40="Alta","0-30 días",IF(O40="Media","31-60 días","61-90 días")),IF(K40="Parcial",IF(O40="Alta","0-45 días",IF(O40="Media","31-75 días","61-120 días")),IF(K40="Por evaluar",IF(O40="Alta","0-15 días","0-30 días"),IF(K40="Cumple","Revisión periódica","No aplica")))) -> Revisión periódica | W40: =IF(K40="No cumple",IF(O40="Alta",3,IF(O40="Media",2,1)),IF(K40="Parcial",IF(O40="Alta",2,IF(O40="Media",1.5,1)),IF(K40="Por evaluar",IF(O40="Alta",1.5,IF(O40="Media",1,0.5)),0))) -> 0 | X40: =IF(K40="No aplica","No aplica",IF(K40="Cumple","Mantenimiento",IF(K40="Por evaluar","Fase 0 - Evidencia/aplicabilidad",IF(OR(B40="Gobernanza",B40="SGSI",B40="Contexto y alcance"),"Fase 1 - Gobierno y SGSI",IF(OR(B40="Riesgos",B40="Procesos",B40="Personas"),"Fase 2 - Riesgos y operación",IF(OR(B40="Terceros",B40="Continuidad"),"Fase 3 - Continuidad y terceros",IF(OR(B40="Tecnología",B40="Accesos",B40="Ciberseguridad",B40="Vulnerabilidades",B40="Incidentes",B40="Monitoreo"),"Fase 4 - Controles técnicos","Fase 5 - Canales y datos"))))))) -> Mantenimiento
A41: 40 | B41: Personas | C41: Confidencialidad | D41: Mantener acuerdos de confidencialidad actualizados | E41: SB exige acuerdos de confidencialidad relacionados con procesos y riesgos, incluyendo deberes que permanecen luego del cambio de funciones o terminación laboral. | F41: SB Art. 14; SEPS Disposición General Tercera | G41: Ambas | H41: SB Art. 14; SEPS Disposición General Tercera | I41: NDA/contratos actualizados, cláusulas post-empleo, registro de aceptación, matriz de personal/proveedor con acuerdos vigentes. | J41: 0.5 | K41: =IF(TRIM(J41&"")="","Por evaluar",IF(UPPER(TRIM(J41&""))="N/A","No aplica",IF(OR(J41=1,J41="1"),"Cumple",IF(OR(J41=0.5,J41="0.5"),"Parcial",IF(OR(J41=0,J41="0"),"No cumple","Revisar valor"))))) -> Parcial | M41: Clausulas post empleo pendientes | N41: Legal / Talento Humano / CISO | O41: Alta | P41: Ingreso, cambio y salida | Q41: Aplica a empleados y terceros. | R41: R1 normativa + R2 anexos + R3 cruce | S41: A.6.6 Acuerdos de confidencialidad o no divulgación; A.6.2 Términos laborales | T41: =IF(K41="Cumple","Mantener / evidenciar",IF(K41="Parcial","Cerrar brecha parcial",IF(K41="No cumple","Implementar control",IF(K41="No aplica","Sin acción","Levantar evidencia")))) -> Cerrar brecha parcial | U41: =IF(K41="Cumple","Mantener evidencia y revisión periódica",IF(K41="No aplica","Documentar justificación de no aplicabilidad",IF(K41="Por evaluar","Levantar evidencia y confirmar aplicabilidad",IF(K41="Parcial","Completar documentación/control y validar efectividad",IF(K41="No cumple","Diseñar, aprobar e implementar control requerido","Corregir valor de cumplimiento"))))) -> Completar documentación/control y validar efectividad | V41: =IF(K41="No cumple",IF(O41="Alta","0-30 días",IF(O41="Media","31-60 días","61-90 días")),IF(K41="Parcial",IF(O41="Alta","0-45 días",IF(O41="Media","31-75 días","61-120 días")),IF(K41="Por evaluar",IF(O41="Alta","0-15 días","0-30 días"),IF(K41="Cumple","Revisión periódica","No aplica")))) -> 0-45 días | W41: =IF(K41="No cumple",IF(O41="Alta",3,IF(O41="Media",2,1)),IF(K41="Parcial",IF(O41="Alta",2,IF(O41="Media",1.5,1)),IF(K41="Por evaluar",IF(O41="Alta",1.5,IF(O41="Media",1,0.5)),0))) -> 2 | X41: =IF(K41="No aplica","No aplica",IF(K41="Cumple","Mantenimiento",IF(K41="Por evaluar","Fase 0 - Evidencia/aplicabilidad",IF(OR(B41="Gobernanza",B41="SGSI",B41="Contexto y alcance"),"Fase 1 - Gobierno y SGSI",IF(OR(B41="Riesgos",B41="Procesos",B41="Personas"),"Fase 2 - Riesgos y operación",IF(OR(B41="Terceros",B41="Continuidad"),"Fase 3 - Continuidad y terceros",IF(OR(B41="Tecnología",B41="Accesos",B41="Ciberseguridad",B41="Vulnerabilidades",B41="Incidentes",B41="Monitoreo"),"Fase 4 - Controles técnicos","Fase 5 - Canales y datos"))))))) -> Fase 2 - Riesgos y operación
A42: 41 | B42: Personas | C42: Archivo de capital humano | D42: Mantener archivo digital centralizado de personal | E42: SB exige archivo digital con formación, experiencia, contratación, capacitación, cargos, evaluaciones y desvinculaciones para análisis cualitativos/cuantitativos. | F42: SB Art. 14 | G42: SB | H42: SB Art. 14 | I42: Expediente digital de personal, registros de capacitación, evaluaciones, histórico de cargos y evidencias de desvinculación. | J42: 1 | K42: =IF(TRIM(J42&"")="","Por evaluar",IF(UPPER(TRIM(J42&""))="N/A","No aplica",IF(OR(J42=1,J42="1"),"Cumple",IF(OR(J42=0.5,J42="0.5"),"Parcial",IF(OR(J42=0,J42="0"),"No cumple","Revisar valor"))))) -> Cumple | N42: Talento Humano | O42: Media | P42: Permanente | Q42: Apoya idoneidad y continuidad. | R42: R1 normativa + R2 anexos + R3 cruce | S42: A.5.33 Protección de registros; A.5.34 Privacidad y protección de datos personales; A.8.3 Restricción de acceso a información | T42: =IF(K42="Cumple","Mantener / evidenciar",IF(K42="Parcial","Cerrar brecha parcial",IF(K42="No cumple","Implementar control",IF(K42="No aplica","Sin acción","Levantar evidencia")))) -> Mantener / evidenciar | U42: =IF(K42="Cumple","Mantener evidencia y revisión periódica",IF(K42="No aplica","Documentar justificación de no aplicabilidad",IF(K42="Por evaluar","Levantar evidencia y confirmar aplicabilidad",IF(K42="Parcial","Completar documentación/control y validar efectividad",IF(K42="No cumple","Diseñar, aprobar e implementar control requerido","Corregir valor de cumplimiento"))))) -> Mantener evidencia y revisión periódica | V42: =IF(K42="No cumple",IF(O42="Alta","0-30 días",IF(O42="Media","31-60 días","61-90 días")),IF(K42="Parcial",IF(O42="Alta","0-45 días",IF(O42="Media","31-75 días","61-120 días")),IF(K42="Por evaluar",IF(O42="Alta","0-15 días","0-30 días"),IF(K42="Cumple","Revisión periódica","No aplica")))) -> Revisión periódica | W42: =IF(K42="No cumple",IF(O42="Alta",3,IF(O42="Media",2,1)),IF(K42="Parcial",IF(O42="Alta",2,IF(O42="Media",1.5,1)),IF(K42="Por evaluar",IF(O42="Alta",1.5,IF(O42="Media",1,0.5)),0))) -> 0 | X42: =IF(K42="No aplica","No aplica",IF(K42="Cumple","Mantenimiento",IF(K42="Por evaluar","Fase 0 - Evidencia/aplicabilidad",IF(OR(B42="Gobernanza",B42="SGSI",B42="Contexto y alcance"),"Fase 1 - Gobierno y SGSI",IF(OR(B42="Riesgos",B42="Procesos",B42="Personas"),"Fase 2 - Riesgos y operación",IF(OR(B42="Terceros",B42="Continuidad"),"Fase 3 - Continuidad y terceros",IF(OR(B42="Tecnología",B42="Accesos",B42="Ciberseguridad",B42="Vulnerabilidades",B42="Incidentes",B42="Monitoreo"),"Fase 4 - Controles técnicos","Fase 5 - Canales y datos"))))))) -> Mantenimiento
A43: 42 | B43: Personas | C43: Seguridad física | D43: Implementar controles de seguridad física relacionados con información | E43: SEPS Anexo 1 incluye seguridad física y control de accesos físicos; SB exige centros de procesamiento protegidos y controles de acceso no autorizado. | F43: SEPS Anexo 1; SB Art. 15 | G43: Ambas | H43: SEPS Anexo 1; SB Art. 15 | I43: Procedimiento de seguridad física, control de acceso a zonas restringidas/CPD, CCTV/logs, visitantes, evidencias de revisión y pruebas. | J43: 0 | K43: =IF(TRIM(J43&"")="","Por evaluar",IF(UPPER(TRIM(J43&""))="N/A","No aplica",IF(OR(J43=1,J43="1"),"Cumple",IF(OR(J43=0.5,J43="0.5"),"Parcial",IF(OR(J43=0,J43="0"),"No cumple","Revisar valor"))))) -> No cumple | N43: Seguridad Física / TIC / CISO | O43: Media | P43: Semestral/Anual | Q43: Vinculado a CPD y activos críticos. | R43: R1 normativa + R2 anexos + R3 cruce | S43: A.7.1 Perímetros físicos; A.7.2 Entrada física; A.7.3 Oficinas e instalaciones seguras; A.7.4 Monitoreo físico; A.7.5 Protección contra amenazas físicas; A.7.6 Áreas seguras | T43: =IF(K43="Cumple","Mantener / evidenciar",IF(K43="Parcial","Cerrar brecha parcial",IF(K43="No cumple","Implementar control",IF(K43="No aplica","Sin acción","Levantar evidencia")))) -> Implementar control | U43: =IF(K43="Cumple","Mantener evidencia y revisión periódica",IF(K43="No aplica","Documentar justificación de no aplicabilidad",IF(K43="Por evaluar","Levantar evidencia y confirmar aplicabilidad",IF(K43="Parcial","Completar documentación/control y validar efectividad",IF(K43="No cumple","Diseñar, aprobar e implementar control requerido","Corregir valor de cumplimiento"))))) -> Diseñar, aprobar e implementar control requerido | V43: =IF(K43="No cumple",IF(O43="Alta","0-30 días",IF(O43="Media","31-60 días","61-90 días")),IF(K43="Parcial",IF(O43="Alta","0-45 días",IF(O43="Media","31-75 días","61-120 días")),IF(K43="Por evaluar",IF(O43="Alta","0-15 días","0-30 días"),IF(K43="Cumple","Revisión periódica","No aplica")))) -> 31-60 días | W43: =IF(K43="No cumple",IF(O43="Alta",3,IF(O43="Media",2,1)),IF(K43="Parcial",IF(O43="Alta",2,IF(O43="Media",1.5,1)),IF(K43="Por evaluar",IF(O43="Alta",1.5,IF(O43="Media",1,0.5)),0))) -> 2 | X43: =IF(K43="No aplica","No aplica",IF(K43="Cumple","Mantenimiento",IF(K43="Por evaluar","Fase 0 - Evidencia/aplicabilidad",IF(OR(B43="Gobernanza",B43="SGSI",B43="Contexto y alcance"),"Fase 1 - Gobierno y SGSI",IF(OR(B43="Riesgos",B43="Procesos",B43="Personas"),"Fase 2 - Riesgos y operación",IF(OR(B43="Terceros",B43="Continuidad"),"Fase 3 - Continuidad y terceros",IF(OR(B43="Tecnología",B43="Accesos",B43="Ciberseguridad",B43="Vulnerabilidades",B43="Incidentes",B43="Monitoreo"),"Fase 4 - Controles técnicos","Fase 5 - Canales y datos"))))))) -> Fase 2 - Riesgos y operación
A44: 43 | B44: Accesos | C44: Control de accesos | D44: Administrar usuarios, perfiles y privilegios | E44: Debe existir procedimiento de concesión, modificación, eliminación y revocación de accesos; debe garantizar segregación de funciones y control de accesos de proveedores. | F44: SEPS Anexo 1; SB Art. 25 | G44: Ambas | H44: SEPS Anexo 1; SB Art. 25 | I44: Procedimiento IAM, matriz de perfiles, solicitudes/aprobaciones, revisiones periódicas, baja de usuarios, control de terceros y evidencia de recertificación. | J44: 0 | K44: =IF(TRIM(J44&"")="","Por evaluar",IF(UPPER(TRIM(J44&""))="N/A","No aplica",IF(OR(J44=1,J44="1"),"Cumple",IF(OR(J44=0.5,J44="0.5"),"Parcial",IF(OR(J44=0,J44="0"),"No cumple","Revisar valor"))))) -> No cumple | M44: Accesos | N44: CISO / TIC / Dueños de sistemas | O44: Alta | P44: Mensual/Trimestral según criticidad | Q44: Cubre accesos lógicos y físicos. | R44: R1 normativa + R2 anexos + R3 cruce | S44: A.5.15 Control de acceso; A.5.16 Gestión de identidades; A.5.17 Información de autenticación; A.5.18 Derechos de acceso; A.8.3 Restricción de acceso; A.8.5 Autenticación segura | T44: =IF(K44="Cumple","Mantener / evidenciar",IF(K44="Parcial","Cerrar brecha parcial",IF(K44="No cumple","Implementar control",IF(K44="No aplica","Sin acción","Levantar evidencia")))) -> Implementar control | U44: =IF(K44="Cumple","Mantener evidencia y revisión periódica",IF(K44="No aplica","Documentar justificación de no aplicabilidad",IF(K44="Por evaluar","Levantar evidencia y confirmar aplicabilidad",IF(K44="Parcial","Completar documentación/control y validar efectividad",IF(K44="No cumple","Diseñar, aprobar e implementar control requerido","Corregir valor de cumplimiento"))))) -> Diseñar, aprobar e implementar control requerido | V44: =IF(K44="No cumple",IF(O44="Alta","0-30 días",IF(O44="Media","31-60 días","61-90 días")),IF(K44="Parcial",IF(O44="Alta","0-45 días",IF(O44="Media","31-75 días","61-120 días")),IF(K44="Por evaluar",IF(O44="Alta","0-15 días","0-30 días"),IF(K44="Cumple","Revisión periódica","No aplica")))) -> 0-30 días | W44: =IF(K44="No cumple",IF(O44="Alta",3,IF(O44="Media",2,1)),IF(K44="Parcial",IF(O44="Alta",2,IF(O44="Media",1.5,1)),IF(K44="Por evaluar",IF(O44="Alta",1.5,IF(O44="Media",1,0.5)),0))) -> 3 | X44: =IF(K44="No aplica","No aplica",IF(K44="Cumple","Mantenimiento",IF(K44="Por evaluar","Fase 0 - Evidencia/aplicabilidad",IF(OR(B44="Gobernanza",B44="SGSI",B44="Contexto y alcance"),"Fase 1 - Gobierno y SGSI",IF(OR(B44="Riesgos",B44="Procesos",B44="Personas"),"Fase 2 - Riesgos y operación",IF(OR(B44="Terceros",B44="Continuidad"),"Fase 3 - Continuidad y terceros",IF(OR(B44="Tecnología",B44="Accesos",B44="Ciberseguridad",B44="Vulnerabilidades",B44="Incidentes",B44="Monitoreo"),"Fase 4 - Controles técnicos","Fase 5 - Canales y datos"))))))) -> Fase 4 - Controles técnicos
A45: 44 | B45: Accesos | C45: Usuarios privilegiados | D45: Gestionar cuentas privilegiadas con MFA y trazabilidad | E45: SB exige credenciales personalizadas, autenticación multifactor, trazabilidad, monitoreo permanente y custodia de credenciales por defecto para uso excepcional autorizado. | F45: SB Art. 25 | G45: SB | H45: SB Art. 25 | I45: Procedimiento PAM, inventario de cuentas privilegiadas, MFA, bóveda de contraseñas, logs, monitoreo, autorizaciones de uso excepcional. | J45: 0 | K45: =IF(TRIM(J45&"")="","Por evaluar",IF(UPPER(TRIM(J45&""))="N/A","No aplica",IF(OR(J45=1,J45="1"),"Cumple",IF(OR(J45=0.5,J45="0.5"),"Parcial",IF(OR(J45=0,J45="0"),"No cumple","Revisar valor"))))) -> No cumple | M45: Accesos | N45: CISO / TIC | O45: Alta | P45: Permanente / revisión mensual | Q45: Control crítico para auditoría. | R45: R1 normativa + R2 anexos + R3 cruce | S45: A.8.2 Derechos de acceso privilegiado; A.8.5 Autenticación segura; A.8.15 Registro de eventos; A.8.18 Programas utilitarios privilegiados | T45: =IF(K45="Cumple","Mantener / evidenciar",IF(K45="Parcial","Cerrar brecha parcial",IF(K45="No cumple","Implementar control",IF(K45="No aplica","Sin acción","Levantar evidencia")))) -> Implementar control | U45: =IF(K45="Cumple","Mantener evidencia y revisión periódica",IF(K45="No aplica","Documentar justificación de no aplicabilidad",IF(K45="Por evaluar","Levantar evidencia y confirmar aplicabilidad",IF(K45="Parcial","Completar documentación/control y validar efectividad",IF(K45="No cumple","Diseñar, aprobar e implementar control requerido","Corregir valor de cumplimiento"))))) -> Diseñar, aprobar e implementar control requerido | V45: =IF(K45="No cumple",IF(O45="Alta","0-30 días",IF(O45="Media","31-60 días","61-90 días")),IF(K45="Parcial",IF(O45="Alta","0-45 días",IF(O45="Media","31-75 días","61-120 días")),IF(K45="Por evaluar",IF(O45="Alta","0-15 días","0-30 días"),IF(K45="Cumple","Revisión periódica","No aplica")))) -> 0-30 días | W45: =IF(K45="No cumple",IF(O45="Alta",3,IF(O45="Media",2,1)),IF(K45="Parcial",IF(O45="Alta",2,IF(O45="Media",1.5,1)),IF(K45="Por evaluar",IF(O45="Alta",1.5,IF(O45="Media",1,0.5)),0))) -> 3 | X45: =IF(K45="No aplica","No aplica",IF(K45="Cumple","Mantenimiento",IF(K45="Por evaluar","Fase 0 - Evidencia/aplicabilidad",IF(OR(B45="Gobernanza",B45="SGSI",B45="Contexto y alcance"),"Fase 1 - Gobierno y SGSI",IF(OR(B45="Riesgos",B45="Procesos",B45="Personas"),"Fase 2 - Riesgos y operación",IF(OR(B45="Terceros",B45="Continuidad"),"Fase 3 - Continuidad y terceros",IF(OR(B45="Tecnología",B45="Accesos",B45="Ciberseguridad",B45="Vulnerabilidades",B45="Incidentes",B45="Monitoreo"),"Fase 4 - Controles técnicos","Fase 5 - Canales y datos"))))))) -> Fase 4 - Controles técnicos
A46: 45 | B46: Accesos | C46: Pistas de auditoría | D46: Registrar cambios y actividades sobre información crítica | E46: Deben existir pistas de auditoría en infraestructura, aplicativos, bases de datos y sistemas operativos; administradores no deben poder borrar/desactivar sus propias pistas. | F46: SEPS Anexo 1; SB Art. 25 | G46: Ambas | H46: SEPS Anexo 1; SB Art. 25 | I46: Configuración de logs, SIEM, retención, alertas, segregación de funciones, monitoreo de cambios y evidencia de revisión. | J46: 0.5 | K46: =IF(TRIM(J46&"")="","Por evaluar",IF(UPPER(TRIM(J46&""))="N/A","No aplica",IF(OR(J46=1,J46="1"),"Cumple",IF(OR(J46=0.5,J46="0.5"),"Parcial",IF(OR(J46=0,J46="0"),"No cumple","Revisar valor"))))) -> Parcial | M46: Accesos | N46: CISO / TIC | O46: Alta | P46: Permanente / revisión mensual | Q46: Relacionado con monitoreo y detección. | R46: R1 normativa + R2 anexos + R3 cruce | S46: A.8.15 Registro de eventos; A.8.17 Sincronización de relojes; A.5.28 Recolección de evidencia; A.5.33 Protección de registros | T46: =IF(K46="Cumple","Mantener / evidenciar",IF(K46="Parcial","Cerrar brecha parcial",IF(K46="No cumple","Implementar control",IF(K46="No aplica","Sin acción","Levantar evidencia")))) -> Cerrar brecha parcial | U46: =IF(K46="Cumple","Mantener evidencia y revisión periódica",IF(K46="No aplica","Documentar justificación de no aplicabilidad",IF(K46="Por evaluar","Levantar evidencia y confirmar aplicabilidad",IF(K46="Parcial","Completar documentación/control y validar efectividad",IF(K46="No cumple","Diseñar, aprobar e implementar control requerido","Corregir valor de cumplimiento"))))) -> Completar documentación/control y validar efectividad | V46: =IF(K46="No cumple",IF(O46="Alta","0-30 días",IF(O46="Media","31-60 días","61-90 días")),IF(K46="Parcial",IF(O46="Alta","0-45 días",IF(O46="Media","31-75 días","61-120 días")),IF(K46="Por evaluar",IF(O46="Alta","0-15 días","0-30 días"),IF(K46="Cumple","Revisión periódica","No aplica")))) -> 0-45 días | W46: =IF(K46="No cumple",IF(O46="Alta",3,IF(O46="Media",2,1)),IF(K46="Parcial",IF(O46="Alta",2,IF(O46="Media",1.5,1)),IF(K46="Por evaluar",IF(O46="Alta",1.5,IF(O46="Media",1,0.5)),0))) -> 2 | X46: =IF(K46="No aplica","No aplica",IF(K46="Cumple","Mantenimiento",IF(K46="Por evaluar","Fase 0 - Evidencia/aplicabilidad",IF(OR(B46="Gobernanza",B46="SGSI",B46="Contexto y alcance"),"Fase 1 - Gobierno y SGSI",IF(OR(B46="Riesgos",B46="Procesos",B46="Personas"),"Fase 2 - Riesgos y operación",IF(OR(B46="Terceros",B46="Continuidad"),"Fase 3 - Continuidad y terceros",IF(OR(B46="Tecnología",B46="Accesos",B46="Ciberseguridad",B46="Vulnerabilidades",B46="Incidentes",B46="Monitoreo"),"Fase 4 - Controles técnicos","Fase 5 - Canales y datos"))))))) -> Fase 4 - Controles técnicos
A47: 46 | B47: Accesos | C47: Monitoreo de accesos | D47: Monitorear accesos, operaciones privilegiadas e intentos no autorizados | E47: SB exige monitoreo permanente de accesos, operaciones privilegiadas e intentos no autorizados, internos y de proveedores. | F47: SB Art. 25 | G47: SB | H47: SB Art. 25 | I47: Casos de uso SIEM, alertas, reportes de accesos anómalos, revisión de privilegios y seguimiento de incidentes. | J47: 0.5 | K47: =IF(TRIM(J47&"")="","Por evaluar",IF(UPPER(TRIM(J47&""))="N/A","No aplica",IF(OR(J47=1,J47="1"),"Cumple",IF(OR(J47=0.5,J47="0.5"),"Parcial",IF(OR(J47=0,J47="0"),"No cumple","Revisar valor"))))) -> Parcial | M47: Accesos | N47: CISO / SOC / TIC | O47: Alta | P47: Permanente | Q47: Complementa control de accesos SEPS. | R47: R1 normativa + R2 anexos + R3 cruce | S47: A.8.15 Registro de eventos; A.8.16 Actividades de monitoreo; A.8.18 Programas utilitarios privilegiados; A.5.25 Evaluación de eventos | T47: =IF(K47="Cumple","Mantener / evidenciar",IF(K47="Parcial","Cerrar brecha parcial",IF(K47="No cumple","Implementar control",IF(K47="No aplica","Sin acción","Levantar evidencia")))) -> Cerrar brecha parcial | U47: =IF(K47="Cumple","Mantener evidencia y revisión periódica",IF(K47="No aplica","Documentar justificación de no aplicabilidad",IF(K47="Por evaluar","Levantar evidencia y confirmar aplicabilidad",IF(K47="Parcial","Completar documentación/control y validar efectividad",IF(K47="No cumple","Diseñar, aprobar e implementar control requerido","Corregir valor de cumplimiento"))))) -> Completar documentación/control y validar efectividad | V47: =IF(K47="No cumple",IF(O47="Alta","0-30 días",IF(O47="Media","31-60 días","61-90 días")),IF(K47="Parcial",IF(O47="Alta","0-45 días",IF(O47="Media","31-75 días","61-120 días")),IF(K47="Por evaluar",IF(O47="Alta","0-15 días","0-30 días"),IF(K47="Cumple","Revisión periódica","No aplica")))) -> 0-45 días | W47: =IF(K47="No cumple",IF(O47="Alta",3,IF(O47="Media",2,1)),IF(K47="Parcial",IF(O47="Alta",2,IF(O47="Media",1.5,1)),IF(K47="Por evaluar",IF(O47="Alta",1.5,IF(O47="Media",1,0.5)),0))) -> 2 | X47: =IF(K47="No aplica","No aplica",IF(K47="Cumple","Mantenimiento",IF(K47="Por evaluar","Fase 0 - Evidencia/aplicabilidad",IF(OR(B47="Gobernanza",B47="SGSI",B47="Contexto y alcance"),"Fase 1 - Gobierno y SGSI",IF(OR(B47="Riesgos",B47="Procesos",B47="Personas"),"Fase 2 - Riesgos y operación",IF(OR(B47="Terceros",B47="Continuidad"),"Fase 3 - Continuidad y terceros",IF(OR(B47="Tecnología",B47="Accesos",B47="Ciberseguridad",B47="Vulnerabilidades",B47="Incidentes",B47="Monitoreo"),"Fase 4 - Controles técnicos","Fase 5 - Canales y datos"))))))) -> Fase 4 - Controles técnicos
A48: 47 | B48: Tecnología | C48: Gobierno TI | D48: Contar con área y comité de tecnología | E48: SB exige área TI según tamaño/complejidad y comité tecnológico con miembros mínimos, reglamento, sesiones al menos trimestrales y evidencia al Directorio. | F48: SB Art. 15 núm. 1 | G48: SB | H48: SB Art. 15 | I48: Organigrama TI, reglamento Comité TI, actas, calendario, roles, reportes al Directorio y participación SI/Riesgos. | J48: 0.5 | K48: =IF(TRIM(J48&"")="","Por evaluar",IF(UPPER(TRIM(J48&""))="N/A","No aplica",IF(OR(J48=1,J48="1"),"Cumple",IF(OR(J48=0.5,J48="0.5"),"Parcial",IF(OR(J48=0,J48="0"),"No cumple","Revisar valor"))))) -> Parcial | M48: Tecnología | N48: TIC / Gerencia / CISO | O48: Alta | P48: Trimestral | Q48: Interdependiente con SI. | R48: R1 normativa + R2 anexos + R3 cruce | S48: A.5.2 Roles y responsabilidades; A.5.8 Seguridad en gestión de proyectos; A.5.36 Cumplimiento; A.5.37 Procedimientos operativos documentados | T48: =IF(K48="Cumple","Mantener / evidenciar",IF(K48="Parcial","Cerrar brecha parcial",IF(K48="No cumple","Implementar control",IF(K48="No aplica","Sin acción","Levantar evidencia")))) -> Cerrar brecha parcial | U48: =IF(K48="Cumple","Mantener evidencia y revisión periódica",IF(K48="No aplica","Documentar justificación de no aplicabilidad",IF(K48="Por evaluar","Levantar evidencia y confirmar aplicabilidad",IF(K48="Parcial","Completar documentación/control y validar efectividad",IF(K48="No cumple","Diseñar, aprobar e implementar control requerido","Corregir valor de cumplimiento"))))) -> Completar documentación/control y validar efectividad | V48: =IF(K48="No cumple",IF(O48="Alta","0-30 días",IF(O48="Media","31-60 días","61-90 días")),IF(K48="Parcial",IF(O48="Alta","0-45 días",IF(O48="Media","31-75 días","61-120 días")),IF(K48="Por evaluar",IF(O48="Alta","0-15 días","0-30 días"),IF(K48="Cumple","Revisión periódica","No aplica")))) -> 0-45 días | W48: =IF(K48="No cumple",IF(O48="Alta",3,IF(O48="Media",2,1)),IF(K48="Parcial",IF(O48="Alta",2,IF(O48="Media",1.5,1)),IF(K48="Por evaluar",IF(O48="Alta",1.5,IF(O48="Media",1,0.5)),0))) -> 2 | X48: =IF(K48="No aplica","No aplica",IF(K48="Cumple","Mantenimiento",IF(K48="Por evaluar","Fase 0 - Evidencia/aplicabilidad",IF(OR(B48="Gobernanza",B48="SGSI",B48="Contexto y alcance"),"Fase 1 - Gobierno y SGSI",IF(OR(B48="Riesgos",B48="Procesos",B48="Personas"),"Fase 2 - Riesgos y operación",IF(OR(B48="Terceros",B48="Continuidad"),"Fase 3 - Continuidad y terceros",IF(OR(B48="Tecnología",B48="Accesos",B48="Ciberseguridad",B48="Vulnerabilidades",B48="Incidentes",B48="Monitoreo"),"Fase 4 - Controles técnicos","Fase 5 - Canales y datos"))))))) -> Fase 4 - Controles técnicos
A49: 48 | B49: Tecnología | C49: Plan TI | D49: Aprobar plan estratégico y operativo de TI | E49: SB exige plan estratégico TI alineado al plan institucional y plan operativo anual con actividades, cronogramas, responsables y presupuesto. | F49: SB Art. 15 núm. 2 | G49: SB | H49: SB Art. 15 | I49: PETI, POA TI, presupuesto, iniciativas, indicadores, actas de aprobación y seguimiento. | J49: 0.5 | K49: =IF(TRIM(J49&"")="","Por evaluar",IF(UPPER(TRIM(J49&""))="N/A","No aplica",IF(OR(J49=1,J49="1"),"Cumple",IF(OR(J49=0.5,J49="0.5"),"Parcial",IF(OR(J49=0,J49="0"),"No cumple","Revisar valor"))))) -> Parcial | M49: Tecnología | N49: TIC / Comité TI | O49: Alta | P49: Anual | Q49: Soporta controles tecnológicos del SGSI. | R49: R1 normativa + R2 anexos + R3 cruce | S49: A.5.8 Seguridad en proyectos; A.8.6 Gestión de capacidad; A.8.14 Redundancia de instalaciones de procesamiento | T49: =IF(K49="Cumple","Mantener / evidenciar",IF(K49="Parcial","Cerrar brecha parcial",IF(K49="No cumple","Implementar control",IF(K49="No aplica","Sin acción","Levantar evidencia")))) -> Cerrar brecha parcial | U49: =IF(K49="Cumple","Mantener evidencia y revisión periódica",IF(K49="No aplica","Documentar justificación de no aplicabilidad",IF(K49="Por evaluar","Levantar evidencia y confirmar aplicabilidad",IF(K49="Parcial","Completar documentación/control y validar efectividad",IF(K49="No cumple","Diseñar, aprobar e implementar control requerido","Corregir valor de cumplimiento"))))) -> Completar documentación/control y validar efectividad | V49: =IF(K49="No cumple",IF(O49="Alta","0-30 días",IF(O49="Media","31-60 días","61-90 días")),IF(K49="Parcial",IF(O49="Alta","0-45 días",IF(O49="Media","31-75 días","61-120 días")),IF(K49="Por evaluar",IF(O49="Alta","0-15 días","0-30 días"),IF(K49="Cumple","Revisión periódica","No aplica")))) -> 0-45 días | W49: =IF(K49="No cumple",IF(O49="Alta",3,IF(O49="Media",2,1)),IF(K49="Parcial",IF(O49="Alta",2,IF(O49="Media",1.5,1)),IF(K49="Por evaluar",IF(O49="Alta",1.5,IF(O49="Media",1,0.5)),0))) -> 2 | X49: =IF(K49="No aplica","No aplica",IF(K49="Cumple","Mantenimiento",IF(K49="Por evaluar","Fase 0 - Evidencia/aplicabilidad",IF(OR(B49="Gobernanza",B49="SGSI",B49="Contexto y alcance"),"Fase 1 - Gobierno y SGSI",IF(OR(B49="Riesgos",B49="Procesos",B49="Personas"),"Fase 2 - Riesgos y operación",IF(OR(B49="Terceros",B49="Continuidad"),"Fase 3 - Continuidad y terceros",IF(OR(B49="Tecnología",B49="Accesos",B49="Ciberseguridad",B49="Vulnerabilidades",B49="Incidentes",B49="Monitoreo"),"Fase 4 - Controles técnicos","Fase 5 - Canales y datos"))))))) -> Fase 4 - Controles técnicos
A50: 49 | B50: Tecnología | C50: Políticas TI | D50: Mantener políticas, procesos, procedimientos y metodologías de TI | E50: Deben estar alineados a objetivos, aceptados por Comité TI, aprobados por Directorio o delegado, difundidos al personal involucrado y con consecuencias por incumplimiento. | F50: SB Art. 15 núm. 2 | G50: SB | H50: SB Art. 15 | I50: Manual de TI, procedimientos operativos, control de versiones, evidencia de aprobación y difusión. | J50: 0 | K50: =IF(TRIM(J50&"")="","Por evaluar",IF(UPPER(TRIM(J50&""))="N/A","No aplica",IF(OR(J50=1,J50="1"),"Cumple",IF(OR(J50=0.5,J50="0.5"),"Parcial",IF(OR(J50=0,J50="0"),"No cumple","Revisar valor"))))) -> No cumple | M50: Tecnología | N50: TIC / Procesos / CISO | O50: Media | P50: Anual | Q50: Cruce con SGSI. | R50: R1 normativa + R2 anexos + R3 cruce | S50: A.5.1 Políticas de SI; A.5.36 Cumplimiento; A.5.37 Procedimientos operativos documentados | T50: =IF(K50="Cumple","Mantener / evidenciar",IF(K50="Parcial","Cerrar brecha parcial",IF(K50="No cumple","Implementar control",IF(K50="No aplica","Sin acción","Levantar evidencia")))) -> Implementar control | U50: =IF(K50="Cumple","Mantener evidencia y revisión periódica",IF(K50="No aplica","Documentar justificación de no aplicabilidad",IF(K50="Por evaluar","Levantar evidencia y confirmar aplicabilidad",IF(K50="Parcial","Completar documentación/control y validar efectividad",IF(K50="No cumple","Diseñar, aprobar e implementar control requerido","Corregir valor de cumplimiento"))))) -> Diseñar, aprobar e implementar control requerido | V50: =IF(K50="No cumple",IF(O50="Alta","0-30 días",IF(O50="Media","31-60 días","61-90 días")),IF(K50="Parcial",IF(O50="Alta","0-45 días",IF(O50="Media","31-75 días","61-120 días")),IF(K50="Por evaluar",IF(O50="Alta","0-15 días","0-30 días"),IF(K50="Cumple","Revisión periódica","No aplica")))) -> 31-60 días | W50: =IF(K50="No cumple",IF(O50="Alta",3,IF(O50="Media",2,1)),IF(K50="Parcial",IF(O50="Alta",2,IF(O50="Media",1.5,1)),IF(K50="Por evaluar",IF(O50="Alta",1.5,IF(O50="Media",1,0.5)),0))) -> 2 | X50: =IF(K50="No aplica","No aplica",IF(K50="Cumple","Mantenimiento",IF(K50="Por evaluar","Fase 0 - Evidencia/aplicabilidad",IF(OR(B50="Gobernanza",B50="SGSI",B50="Contexto y alcance"),"Fase 1 - Gobierno y SGSI",IF(OR(B50="Riesgos",B50="Procesos",B50="Personas"),"Fase 2 - Riesgos y operación",IF(OR(B50="Terceros",B50="Continuidad"),"Fase 3 - Continuidad y terceros",IF(OR(B50="Tecnología",B50="Accesos",B50="Ciberseguridad",B50="Vulnerabilidades",B50="Incidentes",B50="Monitoreo"),"Fase 4 - Controles técnicos","Fase 5 - Canales y datos"))))))) -> Fase 4 - Controles técnicos
A51: 50 | B51: Tecnología | C51: Operación CPD | D51: Proteger operación y uso de centros de datos | E51: SB exige procedimientos de operación y uso de centros de datos con controles contra accesos no autorizados. | F51: SB Art. 15 núm. 3 | G51: SB | H51: SB Art. 15 | I51: Procedimiento CPD, controles de acceso, bitácoras, monitoreo ambiental, inventario, mantenimiento y evidencias. | J51: 0 | K51: =IF(TRIM(J51&"")="","Por evaluar",IF(UPPER(TRIM(J51&""))="N/A","No aplica",IF(OR(J51=1,J51="1"),"Cumple",IF(OR(J51=0.5,J51="0.5"),"Parcial",IF(OR(J51=0,J51="0"),"No cumple","Revisar valor"))))) -> No cumple | M51: Tecnología | N51: TIC / Infraestructura | O51: Alta | P51: Permanente | Q51: También relevante para SEPS seguridad física. | R51: R1 normativa + R2 anexos + R3 cruce | S51: A.7.1 Perímetros físicos; A.7.2 Entrada física; A.7.4 Monitoreo físico; A.7.11 Servicios de soporte; A.7.12 Seguridad de cableado; A.7.13 Mantenimiento; A.8.14 Redundancia | T51: =IF(K51="Cumple","Mantener / evidenciar",IF(K51="Parcial","Cerrar brecha parcial",IF(K51="No cumple","Implementar control",IF(K51="No aplica","Sin acción","Levantar evidencia")))) -> Implementar control | U51: =IF(K51="Cumple","Mantener evidencia y revisión periódica",IF(K51="No aplica","Documentar justificación de no aplicabilidad",IF(K51="Por evaluar","Levantar evidencia y confirmar aplicabilidad",IF(K51="Parcial","Completar documentación/control y validar efectividad",IF(K51="No cumple","Diseñar, aprobar e implementar control requerido","Corregir valor de cumplimiento"))))) -> Diseñar, aprobar e implementar control requerido | V51: =IF(K51="No cumple",IF(O51="Alta","0-30 días",IF(O51="Media","31-60 días","61-90 días")),IF(K51="Parcial",IF(O51="Alta","0-45 días",IF(O51="Media","31-75 días","61-120 días")),IF(K51="Por evaluar",IF(O51="Alta","0-15 días","0-30 días"),IF(K51="Cumple","Revisión periódica","No aplica")))) -> 0-30 días | W51: =IF(K51="No cumple",IF(O51="Alta",3,IF(O51="Media",2,1)),IF(K51="Parcial",IF(O51="Alta",2,IF(O51="Media",1.5,1)),IF(K51="Por evaluar",IF(O51="Alta",1.5,IF(O51="Media",1,0.5)),0))) -> 3 | X51: =IF(K51="No aplica","No aplica",IF(K51="Cumple","Mantenimiento",IF(K51="Por evaluar","Fase 0 - Evidencia/aplicabilidad",IF(OR(B51="Gobernanza",B51="SGSI",B51="Contexto y alcance"),"Fase 1 - Gobierno y SGSI",IF(OR(B51="Riesgos",B51="Procesos",B51="Personas"),"Fase 2 - Riesgos y operación",IF(OR(B51="Terceros",B51="Continuidad"),"Fase 3 - Continuidad y terceros",IF(OR(B51="Tecnología",B51="Accesos",B51="Ciberseguridad",B51="Vulnerabilidades",B51="Incidentes",B51="Monitoreo"),"Fase 4 - Controles técnicos","Fase 5 - Canales y datos"))))))) -> Fase 4 - Controles técnicos
A52: 51 | B52: Tecnología | C52: Gestión problemas TI | D52: Gestionar incidentes y problemas TI con causa raíz | E52: SB exige procedimientos de incidentes/problemas TI, análisis de causa raíz, base de conocimiento, errores conocidos, planes de acción, correlación e indicadores. | F52: SB Art. 15 núm. 3; SB Art. 17 | G52: SB | H52: SB Art. 15/17 | I52: Procedimiento ITSM, tickets, RCA, base de conocimiento, indicadores, planes de acción y revisiones post-incidente. | J52: 0 | K52: =IF(TRIM(J52&"")="","Por evaluar",IF(UPPER(TRIM(J52&""))="N/A","No aplica",IF(OR(J52=1,J52="1"),"Cumple",IF(OR(J52=0.5,J52="0.5"),"Parcial",IF(OR(J52=0,J52="0"),"No cumple","Revisar valor"))))) -> No cumple | M52: Tecnología | N52: TIC / Mesa de Servicios / CISO | O52: Alta | P52: Permanente | Q52: Alineado a resiliencia operativa. | R52: R1 normativa + R2 anexos + R3 cruce | S52: A.5.24 Planificación de incidentes; A.5.25 Evaluación de eventos; A.5.26 Respuesta a incidentes; A.5.27 Aprendizaje de incidentes | T52: =IF(K52="Cumple","Mantener / evidenciar",IF(K52="Parcial","Cerrar brecha parcial",IF(K52="No cumple","Implementar control",IF(K52="No aplica","Sin acción","Levantar evidencia")))) -> Implementar control | U52: =IF(K52="Cumple","Mantener evidencia y revisión periódica",IF(K52="No aplica","Documentar justificación de no aplicabilidad",IF(K52="Por evaluar","Levantar evidencia y confirmar aplicabilidad",IF(K52="Parcial","Completar documentación/control y validar efectividad",IF(K52="No cumple","Diseñar, aprobar e implementar control requerido","Corregir valor de cumplimiento"))))) -> Diseñar, aprobar e implementar control requerido | V52: =IF(K52="No cumple",IF(O52="Alta","0-30 días",IF(O52="Media","31-60 días","61-90 días")),IF(K52="Parcial",IF(O52="Alta","0-45 días",IF(O52="Media","31-75 días","61-120 días")),IF(K52="Por evaluar",IF(O52="Alta","0-15 días","0-30 días"),IF(K52="Cumple","Revisión periódica","No aplica")))) -> 0-30 días | W52: =IF(K52="No cumple",IF(O52="Alta",3,IF(O52="Media",2,1)),IF(K52="Parcial",IF(O52="Alta",2,IF(O52="Media",1.5,1)),IF(K52="Por evaluar",IF(O52="Alta",1.5,IF(O52="Media",1,0.5)),0))) -> 3 | X52: =IF(K52="No aplica","No aplica",IF(K52="Cumple","Mantenimiento",IF(K52="Por evaluar","Fase 0 - Evidencia/aplicabilidad",IF(OR(B52="Gobernanza",B52="SGSI",B52="Contexto y alcance"),"Fase 1 - Gobierno y SGSI",IF(OR(B52="Riesgos",B52="Procesos",B52="Personas"),"Fase 2 - Riesgos y operación",IF(OR(B52="Terceros",B52="Continuidad"),"Fase 3 - Continuidad y terceros",IF(OR(B52="Tecnología",B52="Accesos",B52="Ciberseguridad",B52="Vulnerabilidades",B52="Incidentes",B52="Monitoreo"),"Fase 4 - Controles técnicos","Fase 5 - Canales y datos"))))))) -> Fase 4 - Controles técnicos
A53: 52 | B53: Tecnología | C53: SDLC | D53: Administrar ciclo de vida de aplicaciones | E53: SB exige metodología de adquisición, desarrollo, implementación y mantenimiento de aplicaciones, con requerimientos funcionales/técnicos, documentación, pruebas y proveedores. | F53: SEPS Anexo 1; SB Art. 15 núm. 4 | G53: Ambas | H53: SEPS Anexo 1; SB Art. 15 | I53: Metodología SDLC, procedimiento de adquisición/desarrollo, requisitos, análisis de capacidad, documentación técnica/usuario, QA, aceptación y revisión de proveedores. | J53: 0 | K53: =IF(TRIM(J53&"")="","Por evaluar",IF(UPPER(TRIM(J53&""))="N/A","No aplica",IF(OR(J53=1,J53="1"),"Cumple",IF(OR(J53=0.5,J53="0.5"),"Parcial",IF(OR(J53=0,J53="0"),"No cumple","Revisar valor"))))) -> No cumple | M53: Tecnología | N53: TIC / Desarrollo / CISO | O53: Alta | P53: Por proyecto | Q53: SEPS lo exige en Anexo 1. | R53: R1 normativa + R2 anexos + R3 cruce | S53: A.5.8 Seguridad en proyectos; A.8.25 Ciclo de vida de desarrollo seguro; A.8.26 Requisitos de seguridad de aplicaciones; A.8.27 Arquitectura e ingeniería segura; A.8.29 Pruebas de seguridad | T53: =IF(K53="Cumple","Mantener / evidenciar",IF(K53="Parcial","Cerrar brecha parcial",IF(K53="No cumple","Implementar control",IF(K53="No aplica","Sin acción","Levantar evidencia")))) -> Implementar control | U53: =IF(K53="Cumple","Mantener evidencia y revisión periódica",IF(K53="No aplica","Documentar justificación de no aplicabilidad",IF(K53="Por evaluar","Levantar evidencia y confirmar aplicabilidad",IF(K53="Parcial","Completar documentación/control y validar efectividad",IF(K53="No cumple","Diseñar, aprobar e implementar control requerido","Corregir valor de cumplimiento"))))) -> Diseñar, aprobar e implementar control requerido | V53: =IF(K53="No cumple",IF(O53="Alta","0-30 días",IF(O53="Media","31-60 días","61-90 días")),IF(K53="Parcial",IF(O53="Alta","0-45 días",IF(O53="Media","31-75 días","61-120 días")),IF(K53="Por evaluar",IF(O53="Alta","0-15 días","0-30 días"),IF(K53="Cumple","Revisión periódica","No aplica")))) -> 0-30 días | W53: =IF(K53="No cumple",IF(O53="Alta",3,IF(O53="Media",2,1)),IF(K53="Parcial",IF(O53="Alta",2,IF(O53="Media",1.5,1)),IF(K53="Por evaluar",IF(O53="Alta",1.5,IF(O53="Media",1,0.5)),0))) -> 3 | X53: =IF(K53="No aplica","No aplica",IF(K53="Cumple","Mantenimiento",IF(K53="Por evaluar","Fase 0 - Evidencia/aplicabilidad",IF(OR(B53="Gobernanza",B53="SGSI",B53="Contexto y alcance"),"Fase 1 - Gobierno y SGSI",IF(OR(B53="Riesgos",B53="Procesos",B53="Personas"),"Fase 2 - Riesgos y operación",IF(OR(B53="Terceros",B53="Continuidad"),"Fase 3 - Continuidad y terceros",IF(OR(B53="Tecnología",B53="Accesos",B53="Ciberseguridad",B53="Vulnerabilidades",B53="Incidentes",B53="Monitoreo"),"Fase 4 - Controles técnicos","Fase 5 - Canales y datos"))))))) -> Fase 4 - Controles técnicos
A54: 53 | B54: Tecnología | C54: Desarrollo seguro | D54: Incluir codificación segura y prevención de vulnerabilidades | E54: SB exige técnicas de seguridad de la información en desarrollo con directrices de codificación segura; SEPS requiere pruebas/pentesting y adquisición/desarrollo con controles SI. | F54: SEPS Anexo 1; SB Art. 15 núm. 4; SB Art. 25 | G54: Ambas | H54: SEPS Anexo 1; SB Art. 15/25 | I54: Estándar de desarrollo seguro, revisión de código, SAST/DAST, capacitación devsecops, checklist OWASP y evidencia de pruebas antes de producción. | J54: 0 | K54: =IF(TRIM(J54&"")="","Por evaluar",IF(UPPER(TRIM(J54&""))="N/A","No aplica",IF(OR(J54=1,J54="1"),"Cumple",IF(OR(J54=0.5,J54="0.5"),"Parcial",IF(OR(J54=0,J54="0"),"No cumple","Revisar valor"))))) -> No cumple | M54: Tecnología | N54: TIC Desarrollo / CISO | O54: Alta | P54: Por release | Q54: Control clave para aplicaciones. | R54: R1 normativa + R2 anexos + R3 cruce | S54: A.8.25 Ciclo de vida de desarrollo seguro; A.8.26 Requisitos de seguridad; A.8.27 Arquitectura segura; A.8.28 Codificación segura | T54: =IF(K54="Cumple","Mantener / evidenciar",IF(K54="Parcial","Cerrar brecha parcial",IF(K54="No cumple","Implementar control",IF(K54="No aplica","Sin acción","Levantar evidencia")))) -> Implementar control | U54: =IF(K54="Cumple","Mantener evidencia y revisión periódica",IF(K54="No aplica","Documentar justificación de no aplicabilidad",IF(K54="Por evaluar","Levantar evidencia y confirmar aplicabilidad",IF(K54="Parcial","Completar documentación/control y validar efectividad",IF(K54="No cumple","Diseñar, aprobar e implementar control requerido","Corregir valor de cumplimiento"))))) -> Diseñar, aprobar e implementar control requerido | V54: =IF(K54="No cumple",IF(O54="Alta","0-30 días",IF(O54="Media","31-60 días","61-90 días")),IF(K54="Parcial",IF(O54="Alta","0-45 días",IF(O54="Media","31-75 días","61-120 días")),IF(K54="Por evaluar",IF(O54="Alta","0-15 días","0-30 días"),IF(K54="Cumple","Revisión periódica","No aplica")))) -> 0-30 días | W54: =IF(K54="No cumple",IF(O54="Alta",3,IF(O54="Media",2,1)),IF(K54="Parcial",IF(O54="Alta",2,IF(O54="Media",1.5,1)),IF(K54="Por evaluar",IF(O54="Alta",1.5,IF(O54="Media",1,0.5)),0))) -> 3 | X54: =IF(K54="No aplica","No aplica",IF(K54="Cumple","Mantenimiento",IF(K54="Por evaluar","Fase 0 - Evidencia/aplicabilidad",IF(OR(B54="Gobernanza",B54="SGSI",B54="Contexto y alcance"),"Fase 1 - Gobierno y SGSI",IF(OR(B54="Riesgos",B54="Procesos",B54="Personas"),"Fase 2 - Riesgos y operación",IF(OR(B54="Terceros",B54="Continuidad"),"Fase 3 - Continuidad y terceros",IF(OR(B54="Tecnología",B54="Accesos",B54="Ciberseguridad",B54="Vulnerabilidades",B54="Incidentes",B54="Monitoreo"),"Fase 4 - Controles técnicos","Fase 5 - Canales y datos"))))))) -> Fase 4 - Controles técnicos
A55: 54 | B55: Tecnología | C55: Ambientes | D55: Segregar ambientes de desarrollo, pruebas y producción | E55: SB exige ambientes aislados con segregación de accesos; mínimo desarrollo y producción. | F55: SB Art. 15 núm. 5 | G55: SB | H55: SB Art. 15 | I55: Arquitectura de ambientes, matriz de accesos, controles de paso a producción, datos enmascarados en dev/test y evidencia de segregación. | J55: 0.5 | K55: =IF(TRIM(J55&"")="","Por evaluar",IF(UPPER(TRIM(J55&""))="N/A","No aplica",IF(OR(J55=1,J55="1"),"Cumple",IF(OR(J55=0.5,J55="0.5"),"Parcial",IF(OR(J55=0,J55="0"),"No cumple","Revisar valor"))))) -> Parcial | M55: Tecnología | N55: TIC / CISO | O55: Alta | P55: Permanente | Q55: También apoya protección de datos. | R55: R1 normativa + R2 anexos + R3 cruce | S55: A.8.31 Separación de ambientes; A.8.33 Información de prueba | T55: =IF(K55="Cumple","Mantener / evidenciar",IF(K55="Parcial","Cerrar brecha parcial",IF(K55="No cumple","Implementar control",IF(K55="No aplica","Sin acción","Levantar evidencia")))) -> Cerrar brecha parcial | U55: =IF(K55="Cumple","Mantener evidencia y revisión periódica",IF(K55="No aplica","Documentar justificación de no aplicabilidad",IF(K55="Por evaluar","Levantar evidencia y confirmar aplicabilidad",IF(K55="Parcial","Completar documentación/control y validar efectividad",IF(K55="No cumple","Diseñar, aprobar e implementar control requerido","Corregir valor de cumplimiento"))))) -> Completar documentación/control y validar efectividad | V55: =IF(K55="No cumple",IF(O55="Alta","0-30 días",IF(O55="Media","31-60 días","61-90 días")),IF(K55="Parcial",IF(O55="Alta","0-45 días",IF(O55="Media","31-75 días","61-120 días")),IF(K55="Por evaluar",IF(O55="Alta","0-15 días","0-30 días"),IF(K55="Cumple","Revisión periódica","No aplica")))) -> 0-45 días | W55: =IF(K55="No cumple",IF(O55="Alta",3,IF(O55="Media",2,1)),IF(K55="Parcial",IF(O55="Alta",2,IF(O55="Media",1.5,1)),IF(K55="Por evaluar",IF(O55="Alta",1.5,IF(O55="Media",1,0.5)),0))) -> 2 | X55: =IF(K55="No aplica","No aplica",IF(K55="Cumple","Mantenimiento",IF(K55="Por evaluar","Fase 0 - Evidencia/aplicabilidad",IF(OR(B55="Gobernanza",B55="SGSI",B55="Contexto y alcance"),"Fase 1 - Gobierno y SGSI",IF(OR(B55="Riesgos",B55="Procesos",B55="Personas"),"Fase 2 - Riesgos y operación",IF(OR(B55="Terceros",B55="Continuidad"),"Fase 3 - Continuidad y terceros",IF(OR(B55="Tecnología",B55="Accesos",B55="Ciberseguridad",B55="Vulnerabilidades",B55="Incidentes",B55="Monitoreo"),"Fase 4 - Controles técnicos","Fase 5 - Canales y datos"))))))) -> Fase 4 - Controles técnicos
A56: 55 | B56: Tecnología | C56: Infraestructura crítica | D56: Administrar infraestructura con redundancia, inventario y mantenimiento | E56: SB exige infraestructura para procesos críticos con redundancia, inventario, respaldos de configuración, mantenimiento periódico, trayectorias distintas para enlaces y controles para terceros. | F56: SB Art. 15 núm. 5 | G56: SB | H56: SB Art. 15 | I56: CMDB, diagramas de arquitectura, mantenimiento, redundancia, respaldos de configuración, pruebas de failover y evidencias. | J56: 0.5 | K56: =IF(TRIM(J56&"")="","Por evaluar",IF(UPPER(TRIM(J56&""))="N/A","No aplica",IF(OR(J56=1,J56="1"),"Cumple",IF(OR(J56=0.5,J56="0.5"),"Parcial",IF(OR(J56=0,J56="0"),"No cumple","Revisar valor"))))) -> Parcial | M56: Tecnología | N56: TIC Infraestructura | O56: Alta | P56: Semestral/Anual | Q56: Relacionado con continuidad. | R56: R1 normativa + R2 anexos + R3 cruce | S56: A.8.9 Gestión de configuración; A.8.14 Redundancia; A.8.20 Seguridad de redes; A.8.21 Seguridad de servicios de red; A.7.11 Servicios de soporte | T56: =IF(K56="Cumple","Mantener / evidenciar",IF(K56="Parcial","Cerrar brecha parcial",IF(K56="No cumple","Implementar control",IF(K56="No aplica","Sin acción","Levantar evidencia")))) -> Cerrar brecha parcial | U56: =IF(K56="Cumple","Mantener evidencia y revisión periódica",IF(K56="No aplica","Documentar justificación de no aplicabilidad",IF(K56="Por evaluar","Levantar evidencia y confirmar aplicabilidad",IF(K56="Parcial","Completar documentación/control y validar efectividad",IF(K56="No cumple","Diseñar, aprobar e implementar control requerido","Corregir valor de cumplimiento"))))) -> Completar documentación/control y validar efectividad | V56: =IF(K56="No cumple",IF(O56="Alta","0-30 días",IF(O56="Media","31-60 días","61-90 días")),IF(K56="Parcial",IF(O56="Alta","0-45 días",IF(O56="Media","31-75 días","61-120 días")),IF(K56="Por evaluar",IF(O56="Alta","0-15 días","0-30 días"),IF(K56="Cumple","Revisión periódica","No aplica")))) -> 0-45 días | W56: =IF(K56="No cumple",IF(O56="Alta",3,IF(O56="Media",2,1)),IF(K56="Parcial",IF(O56="Alta",2,IF(O56="Media",1.5,1)),IF(K56="Por evaluar",IF(O56="Alta",1.5,IF(O56="Media",1,0.5)),0))) -> 2 | X56: =IF(K56="No aplica","No aplica",IF(K56="Cumple","Mantenimiento",IF(K56="Por evaluar","Fase 0 - Evidencia/aplicabilidad",IF(OR(B56="Gobernanza",B56="SGSI",B56="Contexto y alcance"),"Fase 1 - Gobierno y SGSI",IF(OR(B56="Riesgos",B56="Procesos",B56="Personas"),"Fase 2 - Riesgos y operación",IF(OR(B56="Terceros",B56="Continuidad"),"Fase 3 - Continuidad y terceros",IF(OR(B56="Tecnología",B56="Accesos",B56="Ciberseguridad",B56="Vulnerabilidades",B56="Incidentes",B56="Monitoreo"),"Fase 4 - Controles técnicos","Fase 5 - Canales y datos"))))))) -> Fase 4 - Controles técnicos
A57: 56 | B57: Tecnología | C57: Capacidad y desempeño | D57: Emitir informe semestral de capacidad y desempeño | E57: SB exige informe de capacidad y desempeño de infraestructura tecnológica al menos semestral, analizado por Comité TI, incluyendo alertas de operación segura y madurez/obsolescencia. | F57: SB Art. 15 núm. 5 | G57: SB | H57: SB Art. 15 | I57: Informe semestral de capacidad, umbrales, tendencias, obsolescencia, necesidades de actualización y acta de revisión por Comité TI. | J57: 0 | K57: =IF(TRIM(J57&"")="","Por evaluar",IF(UPPER(TRIM(J57&""))="N/A","No aplica",IF(OR(J57=1,J57="1"),"Cumple",IF(OR(J57=0.5,J57="0.5"),"Parcial",IF(OR(J57=0,J57="0"),"No cumple","Revisar valor"))))) -> No cumple | M57: Tecnología | N57: TIC / Comité TI | O57: Media | P57: Semestral | Q57: Importante para continuidad y disponibilidad. | R57: R1 normativa + R2 anexos + R3 cruce | S57: A.8.6 Gestión de capacidad | T57: =IF(K57="Cumple","Mantener / evidenciar",IF(K57="Parcial","Cerrar brecha parcial",IF(K57="No cumple","Implementar control",IF(K57="No aplica","Sin acción","Levantar evidencia")))) -> Implementar control | U57: =IF(K57="Cumple","Mantener evidencia y revisión periódica",IF(K57="No aplica","Documentar justificación de no aplicabilidad",IF(K57="Por evaluar","Levantar evidencia y confirmar aplicabilidad",IF(K57="Parcial","Completar documentación/control y validar efectividad",IF(K57="No cumple","Diseñar, aprobar e implementar control requerido","Corregir valor de cumplimiento"))))) -> Diseñar, aprobar e implementar control requerido | V57: =IF(K57="No cumple",IF(O57="Alta","0-30 días",IF(O57="Media","31-60 días","61-90 días")),IF(K57="Parcial",IF(O57="Alta","0-45 días",IF(O57="Media","31-75 días","61-120 días")),IF(K57="Por evaluar",IF(O57="Alta","0-15 días","0-30 días"),IF(K57="Cumple","Revisión periódica","No aplica")))) -> 31-60 días | W57: =IF(K57="No cumple",IF(O57="Alta",3,IF(O57="Media",2,1)),IF(K57="Parcial",IF(O57="Alta",2,IF(O57="Media",1.5,1)),IF(K57="Por evaluar",IF(O57="Alta",1.5,IF(O57="Media",1,0.5)),0))) -> 2 | X57: =IF(K57="No aplica","No aplica",IF(K57="Cumple","Mantenimiento",IF(K57="Por evaluar","Fase 0 - Evidencia/aplicabilidad",IF(OR(B57="Gobernanza",B57="SGSI",B57="Contexto y alcance"),"Fase 1 - Gobierno y SGSI",IF(OR(B57="Riesgos",B57="Procesos",B57="Personas"),"Fase 2 - Riesgos y operación",IF(OR(B57="Terceros",B57="Continuidad"),"Fase 3 - Continuidad y terceros",IF(OR(B57="Tecnología",B57="Accesos",B57="Ciberseguridad",B57="Vulnerabilidades",B57="Incidentes",B57="Monitoreo"),"Fase 4 - Controles técnicos","Fase 5 - Canales y datos"))))))) -> Fase 4 - Controles técnicos
A58: 57 | B58: Tecnología | C58: Gestión de configuración | D58: Implementar gestión de configuración de activos TI | E58: SEPS Anexo 1 exige procedimientos de configuración; SB exige respaldos de configuración, registros y control de infraestructura. | F58: SEPS Anexo 1; SB Art. 15 | G58: Ambas | H58: SEPS Anexo 1; SB Art. 15 | I58: Procedimiento de configuración, línea base/hardening, CMDB, control de cambios de configuración, respaldos y revisiones. | J58: 0.5 | K58: =IF(TRIM(J58&"")="","Por evaluar",IF(UPPER(TRIM(J58&""))="N/A","No aplica",IF(OR(J58=1,J58="1"),"Cumple",IF(OR(J58=0.5,J58="0.5"),"Parcial",IF(OR(J58=0,J58="0"),"No cumple","Revisar valor"))))) -> Parcial | M58: Tecnología | N58: TIC / CISO | O58: Alta | P58: Trimestral/Semestral | Q58: Base para hardening y auditoría. | R58: R1 normativa + R2 anexos + R3 cruce | S58: A.8.9 Gestión de configuración; A.8.19 Instalación de software; A.8.32 Gestión de cambios | T58: =IF(K58="Cumple","Mantener / evidenciar",IF(K58="Parcial","Cerrar brecha parcial",IF(K58="No cumple","Implementar control",IF(K58="No aplica","Sin acción","Levantar evidencia")))) -> Cerrar brecha parcial | U58: =IF(K58="Cumple","Mantener evidencia y revisión periódica",IF(K58="No aplica","Documentar justificación de no aplicabilidad",IF(K58="Por evaluar","Levantar evidencia y confirmar aplicabilidad",IF(K58="Parcial","Completar documentación/control y validar efectividad",IF(K58="No cumple","Diseñar, aprobar e implementar control requerido","Corregir valor de cumplimiento"))))) -> Completar documentación/control y validar efectividad | V58: =IF(K58="No cumple",IF(O58="Alta","0-30 días",IF(O58="Media","31-60 días","61-90 días")),IF(K58="Parcial",IF(O58="Alta","0-45 días",IF(O58="Media","31-75 días","61-120 días")),IF(K58="Por evaluar",IF(O58="Alta","0-15 días","0-30 días"),IF(K58="Cumple","Revisión periódica","No aplica")))) -> 0-45 días | W58: =IF(K58="No cumple",IF(O58="Alta",3,IF(O58="Media",2,1)),IF(K58="Parcial",IF(O58="Alta",2,IF(O58="Media",1.5,1)),IF(K58="Por evaluar",IF(O58="Alta",1.5,IF(O58="Media",1,0.5)),0))) -> 2 | X58: =IF(K58="No aplica","No aplica",IF(K58="Cumple","Mantenimiento",IF(K58="Por evaluar","Fase 0 - Evidencia/aplicabilidad",IF(OR(B58="Gobernanza",B58="SGSI",B58="Contexto y alcance"),"Fase 1 - Gobierno y SGSI",IF(OR(B58="Riesgos",B58="Procesos",B58="Personas"),"Fase 2 - Riesgos y operación",IF(OR(B58="Terceros",B58="Continuidad"),"Fase 3 - Continuidad y terceros",IF(OR(B58="Tecnología",B58="Accesos",B58="Ciberseguridad",B58="Vulnerabilidades",B58="Incidentes",B58="Monitoreo"),"Fase 4 - Controles técnicos","Fase 5 - Canales y datos"))))))) -> Fase 4 - Controles técnicos
A59: 58 | B59: Tecnología | C59: Gestión de cambios | D59: Controlar cambios y versiones en aplicaciones e infraestructura | E59: Deben existir solicitudes, análisis, priorización, aprobación, evaluación de impacto, rollback, pruebas, segregación de librerías/ambientes, aprobación del propietario y cambios de emergencia regularizados. | F59: SEPS Anexo 1; SB Art. 15 núm. 6 | G59: Ambas | H59: SEPS Anexo 1; SB Art. 15 | I59: Procedimiento de cambios, CAB, registros, aprobaciones, pruebas, rollback, versionamiento, evidencias y regularización de emergencias. | J59: 0.5 | K59: =IF(TRIM(J59&"")="","Por evaluar",IF(UPPER(TRIM(J59&""))="N/A","No aplica",IF(OR(J59=1,J59="1"),"Cumple",IF(OR(J59=0.5,J59="0.5"),"Parcial",IF(OR(J59=0,J59="0"),"No cumple","Revisar valor"))))) -> Parcial | M59: Tecnología | N59: TIC / Dueños de información / CISO | O59: Alta | P59: Por cambio | Q59: Control obligatorio en ambas. | R59: R1 normativa + R2 anexos + R3 cruce | S59: A.8.32 Gestión de cambios; A.8.9 Gestión de configuración; A.8.19 Instalación de software | T59: =IF(K59="Cumple","Mantener / evidenciar",IF(K59="Parcial","Cerrar brecha parcial",IF(K59="No cumple","Implementar control",IF(K59="No aplica","Sin acción","Levantar evidencia")))) -> Cerrar brecha parcial | U59: =IF(K59="Cumple","Mantener evidencia y revisión periódica",IF(K59="No aplica","Documentar justificación de no aplicabilidad",IF(K59="Por evaluar","Levantar evidencia y confirmar aplicabilidad",IF(K59="Parcial","Completar documentación/control y validar efectividad",IF(K59="No cumple","Diseñar, aprobar e implementar control requerido","Corregir valor de cumplimiento"))))) -> Completar documentación/control y validar efectividad | V59: =IF(K59="No cumple",IF(O59="Alta","0-30 días",IF(O59="Media","31-60 días","61-90 días")),IF(K59="Parcial",IF(O59="Alta","0-45 días",IF(O59="Media","31-75 días","61-120 días")),IF(K59="Por evaluar",IF(O59="Alta","0-15 días","0-30 días"),IF(K59="Cumple","Revisión periódica","No aplica")))) -> 0-45 días | W59: =IF(K59="No cumple",IF(O59="Alta",3,IF(O59="Media",2,1)),IF(K59="Parcial",IF(O59="Alta",2,IF(O59="Media",1.5,1)),IF(K59="Por evaluar",IF(O59="Alta",1.5,IF(O59="Media",1,0.5)),0))) -> 2 | X59: =IF(K59="No aplica","No aplica",IF(K59="Cumple","Mantenimiento",IF(K59="Por evaluar","Fase 0 - Evidencia/aplicabilidad",IF(OR(B59="Gobernanza",B59="SGSI",B59="Contexto y alcance"),"Fase 1 - Gobierno y SGSI",IF(OR(B59="Riesgos",B59="Procesos",B59="Personas"),"Fase 2 - Riesgos y operación",IF(OR(B59="Terceros",B59="Continuidad"),"Fase 3 - Continuidad y terceros",IF(OR(B59="Tecnología",B59="Accesos",B59="Ciberseguridad",B59="Vulnerabilidades",B59="Incidentes",B59="Monitoreo"),"Fase 4 - Controles técnicos","Fase 5 - Canales y datos"))))))) -> Fase 4 - Controles técnicos
A60: 59 | B60: Tecnología | C60: Migraciones | D60: Controlar migraciones de información y plataformas críticas | E60: SB exige controles para garantizar integridad, disponibilidad y confidencialidad en migraciones de información y notificación previa de 21 días para migración de plataforma tecnológica crítica. | F60: SB Art. 15 núm. 4-5 | G60: SB | H60: SB Art. 15 | I60: Plan de migración, análisis de riesgos, pruebas, validación de datos, plan de rollback, comunicación/notificación y acta de cierre. | J60: 0 | K60: =IF(TRIM(J60&"")="","Por evaluar",IF(UPPER(TRIM(J60&""))="N/A","No aplica",IF(OR(J60=1,J60="1"),"Cumple",IF(OR(J60=0.5,J60="0.5"),"Parcial",IF(OR(J60=0,J60="0"),"No cumple","Revisar valor"))))) -> No cumple | M60: Tecnología | N60: TIC / CISO / Dueños de información | O60: Alta | P60: Por migración | Q60: Relevante para proyectos tecnológicos. | R60: R1 normativa + R2 anexos + R3 cruce | S60: A.8.32 Gestión de cambios; A.8.29 Pruebas de seguridad en desarrollo/aceptación; A.8.33 Información de prueba; A.8.13 Respaldo | T60: =IF(K60="Cumple","Mantener / evidenciar",IF(K60="Parcial","Cerrar brecha parcial",IF(K60="No cumple","Implementar control",IF(K60="No aplica","Sin acción","Levantar evidencia")))) -> Implementar control | U60: =IF(K60="Cumple","Mantener evidencia y revisión periódica",IF(K60="No aplica","Documentar justificación de no aplicabilidad",IF(K60="Por evaluar","Levantar evidencia y confirmar aplicabilidad",IF(K60="Parcial","Completar documentación/control y validar efectividad",IF(K60="No cumple","Diseñar, aprobar e implementar control requerido","Corregir valor de cumplimiento"))))) -> Diseñar, aprobar e implementar control requerido | V60: =IF(K60="No cumple",IF(O60="Alta","0-30 días",IF(O60="Media","31-60 días","61-90 días")),IF(K60="Parcial",IF(O60="Alta","0-45 días",IF(O60="Media","31-75 días","61-120 días")),IF(K60="Por evaluar",IF(O60="Alta","0-15 días","0-30 días"),IF(K60="Cumple","Revisión periódica","No aplica")))) -> 0-30 días | W60: =IF(K60="No cumple",IF(O60="Alta",3,IF(O60="Media",2,1)),IF(K60="Parcial",IF(O60="Alta",2,IF(O60="Media",1.5,1)),IF(K60="Por evaluar",IF(O60="Alta",1.5,IF(O60="Media",1,0.5)),0))) -> 3 | X60: =IF(K60="No aplica","No aplica",IF(K60="Cumple","Mantenimiento",IF(K60="Por evaluar","Fase 0 - Evidencia/aplicabilidad",IF(OR(B60="Gobernanza",B60="SGSI",B60="Contexto y alcance"),"Fase 1 - Gobierno y SGSI",IF(OR(B60="Riesgos",B60="Procesos",B60="Personas"),"Fase 2 - Riesgos y operación",IF(OR(B60="Terceros",B60="Continuidad"),"Fase 3 - Continuidad y terceros",IF(OR(B60="Tecnología",B60="Accesos",B60="Ciberseguridad",B60="Vulnerabilidades",B60="Incidentes",B60="Monitoreo"),"Fase 4 - Controles técnicos","Fase 5 - Canales y datos"))))))) -> Fase 4 - Controles técnicos
A61: 60 | B61: Vulnerabilidades | C61: Auditorías informáticas | D61: Realizar auditorías, revisiones generales o focalizadas | E61: SEPS Anexo 1 exige auditorías/revisiones internas y externas; SB exige auditoría de seguridad de la información/ciberseguridad al menos anual según perfil de riesgo. | F61: SEPS Anexo 1; SB Art. 25 | G61: Ambas | H61: SEPS Anexo 1; SB Art. 25 | I61: Plan anual de auditorías SI/TI, alcance, informes, hallazgos, planes de acción, seguimiento y comparación con revisiones previas. | J61: 0 | K61: =IF(TRIM(J61&"")="","Por evaluar",IF(UPPER(TRIM(J61&""))="N/A","No aplica",IF(OR(J61=1,J61="1"),"Cumple",IF(OR(J61=0.5,J61="0.5"),"Parcial",IF(OR(J61=0,J61="0"),"No cumple","Revisar valor"))))) -> No cumple | M61: Vulnerabilidades | N61: CISO / Auditoría Interna | O61: Alta | P61: Anual | Q61: Debe ejecutarlo personal independiente cuando corresponda. | R61: R1 normativa + R2 anexos + R3 cruce | S61: Cl. 9.2; A.5.35 Revisión independiente de SI; A.8.34 Protección durante pruebas de auditoría | T61: =IF(K61="Cumple","Mantener / evidenciar",IF(K61="Parcial","Cerrar brecha parcial",IF(K61="No cumple","Implementar control",IF(K61="No aplica","Sin acción","Levantar evidencia")))) -> Implementar control | U61: =IF(K61="Cumple","Mantener evidencia y revisión periódica",IF(K61="No aplica","Documentar justificación de no aplicabilidad",IF(K61="Por evaluar","Levantar evidencia y confirmar aplicabilidad",IF(K61="Parcial","Completar documentación/control y validar efectividad",IF(K61="No cumple","Diseñar, aprobar e implementar control requerido","Corregir valor de cumplimiento"))))) -> Diseñar, aprobar e implementar control requerido | V61: =IF(K61="No cumple",IF(O61="Alta","0-30 días",IF(O61="Media","31-60 días","61-90 días")),IF(K61="Parcial",IF(O61="Alta","0-45 días",IF(O61="Media","31-75 días","61-120 días")),IF(K61="Por evaluar",IF(O61="Alta","0-15 días","0-30 días"),IF(K61="Cumple","Revisión periódica","No aplica")))) -> 0-30 días | W61: =IF(K61="No cumple",IF(O61="Alta",3,IF(O61="Media",2,1)),IF(K61="Parcial",IF(O61="Alta",2,IF(O61="Media",1.5,1)),IF(K61="Por evaluar",IF(O61="Alta",1.5,IF(O61="Media",1,0.5)),0))) -> 3 | X61: =IF(K61="No aplica","No aplica",IF(K61="Cumple","Mantenimiento",IF(K61="Por evaluar","Fase 0 - Evidencia/aplicabilidad",IF(OR(B61="Gobernanza",B61="SGSI",B61="Contexto y alcance"),"Fase 1 - Gobierno y SGSI",IF(OR(B61="Riesgos",B61="Procesos",B61="Personas"),"Fase 2 - Riesgos y operación",IF(OR(B61="Terceros",B61="Continuidad"),"Fase 3 - Continuidad y terceros",IF(OR(B61="Tecnología",B61="Accesos",B61="Ciberseguridad",B61="Vulnerabilidades",B61="Incidentes",B61="Monitoreo"),"Fase 4 - Controles técnicos","Fase 5 - Canales y datos"))))))) -> Fase 4 - Controles técnicos
A62: 61 | B62: Vulnerabilidades | C62: Pentesting | D62: Realizar pruebas de penetración y vulnerabilidades | E62: SEPS exige pruebas de penetración al menos anual en régimen general; SB exige auditorías anuales que incluyan pruebas de vulnerabilidad y penetración en equipos, dispositivos, canales, aplicaciones, etc. | F62: SEPS Anexo 1; SB Art. 25 y 27 | G62: Ambas | H62: SEPS Anexo 1; SB Art. 25/27 | I62: Alcance pentesting/ethical hacking, NDA, autorización, metodología, informe ejecutivo/técnico, plan de remediación y re-test. | J62: 0.5 | K62: =IF(TRIM(J62&"")="","Por evaluar",IF(UPPER(TRIM(J62&""))="N/A","No aplica",IF(OR(J62=1,J62="1"),"Cumple",IF(OR(J62=0.5,J62="0.5"),"Parcial",IF(OR(J62=0,J62="0"),"No cumple","Revisar valor"))))) -> Parcial | M62: Vulnerabilidades | N62: CISO / Proveedor externo | O62: Alta | P62: Anual y ante cambios críticos | Q62: Externo e independiente según SEPS/SB. | R62: R1 normativa + R2 anexos + R3 cruce | S62: A.8.8 Gestión de vulnerabilidades técnicas; A.8.29 Pruebas de seguridad; A.8.34 Protección durante pruebas de auditoría | T62: =IF(K62="Cumple","Mantener / evidenciar",IF(K62="Parcial","Cerrar brecha parcial",IF(K62="No cumple","Implementar control",IF(K62="No aplica","Sin acción","Levantar evidencia")))) -> Cerrar brecha parcial | U62: =IF(K62="Cumple","Mantener evidencia y revisión periódica",IF(K62="No aplica","Documentar justificación de no aplicabilidad",IF(K62="Por evaluar","Levantar evidencia y confirmar aplicabilidad",IF(K62="Parcial","Completar documentación/control y validar efectividad",IF(K62="No cumple","Diseñar, aprobar e implementar control requerido","Corregir valor de cumplimiento"))))) -> Completar documentación/control y validar efectividad | V62: =IF(K62="No cumple",IF(O62="Alta","0-30 días",IF(O62="Media","31-60 días","61-90 días")),IF(K62="Parcial",IF(O62="Alta","0-45 días",IF(O62="Media","31-75 días","61-120 días")),IF(K62="Por evaluar",IF(O62="Alta","0-15 días","0-30 días"),IF(K62="Cumple","Revisión periódica","No aplica")))) -> 0-45 días | W62: =IF(K62="No cumple",IF(O62="Alta",3,IF(O62="Media",2,1)),IF(K62="Parcial",IF(O62="Alta",2,IF(O62="Media",1.5,1)),IF(K62="Por evaluar",IF(O62="Alta",1.5,IF(O62="Media",1,0.5)),0))) -> 2 | X62: =IF(K62="No aplica","No aplica",IF(K62="Cumple","Mantenimiento",IF(K62="Por evaluar","Fase 0 - Evidencia/aplicabilidad",IF(OR(B62="Gobernanza",B62="SGSI",B62="Contexto y alcance"),"Fase 1 - Gobierno y SGSI",IF(OR(B62="Riesgos",B62="Procesos",B62="Personas"),"Fase 2 - Riesgos y operación",IF(OR(B62="Terceros",B62="Continuidad"),"Fase 3 - Continuidad y terceros",IF(OR(B62="Tecnología",B62="Accesos",B62="Ciberseguridad",B62="Vulnerabilidades",B62="Incidentes",B62="Monitoreo"),"Fase 4 - Controles técnicos","Fase 5 - Canales y datos"))))))) -> Fase 4 - Controles técnicos
A63: 62 | B63: Vulnerabilidades | C63: Plan de mitigación de hallazgos | D63: Gestionar remediación de hallazgos | E63: SEPS exige plan de mitigación con análisis comparativo de hallazgos previos; SB exige definir y ejecutar planes de acción sobre vulnerabilidades detectadas. | F63: SEPS Anexo 1; SB Art. 25/27 | G63: Ambas | H63: SEPS Anexo 1; SB Art. 25/27 | I63: Matriz de hallazgos, criticidad, responsables, fechas, estado, evidencia de remediación, re-test y comparación histórica. | J63: 0.5 | K63: =IF(TRIM(J63&"")="","Por evaluar",IF(UPPER(TRIM(J63&""))="N/A","No aplica",IF(OR(J63=1,J63="1"),"Cumple",IF(OR(J63=0.5,J63="0.5"),"Parcial",IF(OR(J63=0,J63="0"),"No cumple","Revisar valor"))))) -> Parcial | M63: Vulnerabilidades | N63: CISO / TIC / Dueños de sistemas | O63: Alta | P63: Mensual seguimiento | Q63: Debida diligencia central. | R63: R1 normativa + R2 anexos + R3 cruce | S63: Cl. 10.1; A.8.8 Gestión de vulnerabilidades técnicas; A.5.36 Cumplimiento | T63: =IF(K63="Cumple","Mantener / evidenciar",IF(K63="Parcial","Cerrar brecha parcial",IF(K63="No cumple","Implementar control",IF(K63="No aplica","Sin acción","Levantar evidencia")))) -> Cerrar brecha parcial | U63: =IF(K63="Cumple","Mantener evidencia y revisión periódica",IF(K63="No aplica","Documentar justificación de no aplicabilidad",IF(K63="Por evaluar","Levantar evidencia y confirmar aplicabilidad",IF(K63="Parcial","Completar documentación/control y validar efectividad",IF(K63="No cumple","Diseñar, aprobar e implementar control requerido","Corregir valor de cumplimiento"))))) -> Completar documentación/control y validar efectividad | V63: =IF(K63="No cumple",IF(O63="Alta","0-30 días",IF(O63="Media","31-60 días","61-90 días")),IF(K63="Parcial",IF(O63="Alta","0-45 días",IF(O63="Media","31-75 días","61-120 días")),IF(K63="Por evaluar",IF(O63="Alta","0-15 días","0-30 días"),IF(K63="Cumple","Revisión periódica","No aplica")))) -> 0-45 días | W63: =IF(K63="No cumple",IF(O63="Alta",3,IF(O63="Media",2,1)),IF(K63="Parcial",IF(O63="Alta",2,IF(O63="Media",1.5,1)),IF(K63="Por evaluar",IF(O63="Alta",1.5,IF(O63="Media",1,0.5)),0))) -> 2 | X63: =IF(K63="No aplica","No aplica",IF(K63="Cumple","Mantenimiento",IF(K63="Por evaluar","Fase 0 - Evidencia/aplicabilidad",IF(OR(B63="Gobernanza",B63="SGSI",B63="Contexto y alcance"),"Fase 1 - Gobierno y SGSI",IF(OR(B63="Riesgos",B63="Procesos",B63="Personas"),"Fase 2 - Riesgos y operación",IF(OR(B63="Terceros",B63="Continuidad"),"Fase 3 - Continuidad y terceros",IF(OR(B63="Tecnología",B63="Accesos",B63="Ciberseguridad",B63="Vulnerabilidades",B63="Incidentes",B63="Monitoreo"),"Fase 4 - Controles técnicos","Fase 5 - Canales y datos"))))))) -> Fase 4 - Controles técnicos
A64: 63 | B64: Vulnerabilidades | C64: Escaneo de código | D64: Escaneo automatizado de vulnerabilidades en código fuente | E64: SB exige escaneo automatizado en código fuente previo a liberación y sobre aplicaciones en producción. | F64: SB Art. 25 | G64: SB | H64: SB Art. 25 | I64: Herramienta SAST/DAST/SCA, pipeline DevSecOps, registros de escaneo, criterios de aceptación y excepciones aprobadas. | J64: 0 | K64: =IF(TRIM(J64&"")="","Por evaluar",IF(UPPER(TRIM(J64&""))="N/A","No aplica",IF(OR(J64=1,J64="1"),"Cumple",IF(OR(J64=0.5,J64="0.5"),"Parcial",IF(OR(J64=0,J64="0"),"No cumple","Revisar valor"))))) -> No cumple | M64: Vulnerabilidades | N64: TIC Desarrollo / CISO | O64: Alta | P64: Por release / continuo | Q64: Profundiza desarrollo seguro. | R64: R1 normativa + R2 anexos + R3 cruce | S64: A.8.4 Acceso a código fuente; A.8.28 Codificación segura; A.8.29 Pruebas de seguridad | T64: =IF(K64="Cumple","Mantener / evidenciar",IF(K64="Parcial","Cerrar brecha parcial",IF(K64="No cumple","Implementar control",IF(K64="No aplica","Sin acción","Levantar evidencia")))) -> Implementar control | U64: =IF(K64="Cumple","Mantener evidencia y revisión periódica",IF(K64="No aplica","Documentar justificación de no aplicabilidad",IF(K64="Por evaluar","Levantar evidencia y confirmar aplicabilidad",IF(K64="Parcial","Completar documentación/control y validar efectividad",IF(K64="No cumple","Diseñar, aprobar e implementar control requerido","Corregir valor de cumplimiento"))))) -> Diseñar, aprobar e implementar control requerido | V64: =IF(K64="No cumple",IF(O64="Alta","0-30 días",IF(O64="Media","31-60 días","61-90 días")),IF(K64="Parcial",IF(O64="Alta","0-45 días",IF(O64="Media","31-75 días","61-120 días")),IF(K64="Por evaluar",IF(O64="Alta","0-15 días","0-30 días"),IF(K64="Cumple","Revisión periódica","No aplica")))) -> 0-30 días | W64: =IF(K64="No cumple",IF(O64="Alta",3,IF(O64="Media",2,1)),IF(K64="Parcial",IF(O64="Alta",2,IF(O64="Media",1.5,1)),IF(K64="Por evaluar",IF(O64="Alta",1.5,IF(O64="Media",1,0.5)),0))) -> 3 | X64: =IF(K64="No aplica","No aplica",IF(K64="Cumple","Mantenimiento",IF(K64="Por evaluar","Fase 0 - Evidencia/aplicabilidad",IF(OR(B64="Gobernanza",B64="SGSI",B64="Contexto y alcance"),"Fase 1 - Gobierno y SGSI",IF(OR(B64="Riesgos",B64="Procesos",B64="Personas"),"Fase 2 - Riesgos y operación",IF(OR(B64="Terceros",B64="Continuidad"),"Fase 3 - Continuidad y terceros",IF(OR(B64="Tecnología",B64="Accesos",B64="Ciberseguridad",B64="Vulnerabilidades",B64="Incidentes",B64="Monitoreo"),"Fase 4 - Controles técnicos","Fase 5 - Canales y datos"))))))) -> Fase 4 - Controles técnicos
A65: 64 | B65: Monitoreo | C65: Arquitectura segura | D65: Diseñar arquitectura segura de defensa en profundidad | E65: SEPS Anexo 1 exige arquitectura segura con defensa en profundidad, controles de flujo, aislamiento/segmentación, monitoreo/detección y cifrado; SB exige segmentación, IPS, firewalls, WAF según riesgo. | F65: SEPS Anexo 1; SB Art. 25 | G65: Ambas | H65: SEPS Anexo 1; SB Art. 25 | I65: Documento de arquitectura de seguridad, diagramas, segmentación, WAF/IPS/firewall, cifrado, controles de flujo, monitoreo y excepciones. | J65: 1 | K65: =IF(TRIM(J65&"")="","Por evaluar",IF(UPPER(TRIM(J65&""))="N/A","No aplica",IF(OR(J65=1,J65="1"),"Cumple",IF(OR(J65=0.5,J65="0.5"),"Parcial",IF(OR(J65=0,J65="0"),"No cumple","Revisar valor"))))) -> Cumple | M65: Monitoreo | N65: CISO / Arquitectura / TIC | O65: Alta | P65: Anual y por proyecto | Q65: Se alinea con ISO 27002 y ciberseguridad. | R65: R1 normativa + R2 anexos + R3 cruce | S65: A.8.27 Arquitectura e ingeniería segura; A.8.20 Seguridad de redes; A.8.22 Segregación de redes; A.8.14 Redundancia | T65: =IF(K65="Cumple","Mantener / evidenciar",IF(K65="Parcial","Cerrar brecha parcial",IF(K65="No cumple","Implementar control",IF(K65="No aplica","Sin acción","Levantar evidencia")))) -> Mantener / evidenciar | U65: =IF(K65="Cumple","Mantener evidencia y revisión periódica",IF(K65="No aplica","Documentar justificación de no aplicabilidad",IF(K65="Por evaluar","Levantar evidencia y confirmar aplicabilidad",IF(K65="Parcial","Completar documentación/control y validar efectividad",IF(K65="No cumple","Diseñar, aprobar e implementar control requerido","Corregir valor de cumplimiento"))))) -> Mantener evidencia y revisión periódica | V65: =IF(K65="No cumple",IF(O65="Alta","0-30 días",IF(O65="Media","31-60 días","61-90 días")),IF(K65="Parcial",IF(O65="Alta","0-45 días",IF(O65="Media","31-75 días","61-120 días")),IF(K65="Por evaluar",IF(O65="Alta","0-15 días","0-30 días"),IF(K65="Cumple","Revisión periódica","No aplica")))) -> Revisión periódica | W65: =IF(K65="No cumple",IF(O65="Alta",3,IF(O65="Media",2,1)),IF(K65="Parcial",IF(O65="Alta",2,IF(O65="Media",1.5,1)),IF(K65="Por evaluar",IF(O65="Alta",1.5,IF(O65="Media",1,0.5)),0))) -> 0 | X65: =IF(K65="No aplica","No aplica",IF(K65="Cumple","Mantenimiento",IF(K65="Por evaluar","Fase 0 - Evidencia/aplicabilidad",IF(OR(B65="Gobernanza",B65="SGSI",B65="Contexto y alcance"),"Fase 1 - Gobierno y SGSI",IF(OR(B65="Riesgos",B65="Procesos",B65="Personas"),"Fase 2 - Riesgos y operación",IF(OR(B65="Terceros",B65="Continuidad"),"Fase 3 - Continuidad y terceros",IF(OR(B65="Tecnología",B65="Accesos",B65="Ciberseguridad",B65="Vulnerabilidades",B65="Incidentes",B65="Monitoreo"),"Fase 4 - Controles técnicos","Fase 5 - Canales y datos"))))))) -> Mantenimiento
A66: 65 | B66: Monitoreo | C66: Logs correlacionados | D66: Implementar monitoreo, detección y correlación de logs | E66: SEPS exige registros de logs correlacionados de infraestructura crítica con hora, permisos, acceso/salida, cambios, errores, violaciones y tareas fallidas; SB exige registro centralizado de eventos de ciberseguridad y pistas de auditoría. | F66: SEPS Anexo 1; SB Art. 25-26 | G66: Ambas | H66: SEPS Anexo 1; SB Art. 25/26 | I66: SIEM/SOC, fuentes de logs, sincronización horaria, casos de uso, retención, alertas, revisión y evidencias de investigación. | J66: 0.5 | K66: =IF(TRIM(J66&"")="","Por evaluar",IF(UPPER(TRIM(J66&""))="N/A","No aplica",IF(OR(J66=1,J66="1"),"Cumple",IF(OR(J66=0.5,J66="0.5"),"Parcial",IF(OR(J66=0,J66="0"),"No cumple","Revisar valor"))))) -> Parcial | M66: Monitoreo | N66: CISO / SOC / TIC | O66: Alta | P66: Permanente | Q66: Control clave de detección. | R66: R1 normativa + R2 anexos + R3 cruce | S66: A.8.15 Registro de eventos; A.8.16 Actividades de monitoreo; A.8.17 Sincronización de relojes | T66: =IF(K66="Cumple","Mantener / evidenciar",IF(K66="Parcial","Cerrar brecha parcial",IF(K66="No cumple","Implementar control",IF(K66="No aplica","Sin acción","Levantar evidencia")))) -> Cerrar brecha parcial | U66: =IF(K66="Cumple","Mantener evidencia y revisión periódica",IF(K66="No aplica","Documentar justificación de no aplicabilidad",IF(K66="Por evaluar","Levantar evidencia y confirmar aplicabilidad",IF(K66="Parcial","Completar documentación/control y validar efectividad",IF(K66="No cumple","Diseñar, aprobar e implementar control requerido","Corregir valor de cumplimiento"))))) -> Completar documentación/control y validar efectividad | V66: =IF(K66="No cumple",IF(O66="Alta","0-30 días",IF(O66="Media","31-60 días","61-90 días")),IF(K66="Parcial",IF(O66="Alta","0-45 días",IF(O66="Media","31-75 días","61-120 días")),IF(K66="Por evaluar",IF(O66="Alta","0-15 días","0-30 días"),IF(K66="Cumple","Revisión periódica","No aplica")))) -> 0-45 días | W66: =IF(K66="No cumple",IF(O66="Alta",3,IF(O66="Media",2,1)),IF(K66="Parcial",IF(O66="Alta",2,IF(O66="Media",1.5,1)),IF(K66="Por evaluar",IF(O66="Alta",1.5,IF(O66="Media",1,0.5)),0))) -> 2 | X66: =IF(K66="No aplica","No aplica",IF(K66="Cumple","Mantenimiento",IF(K66="Por evaluar","Fase 0 - Evidencia/aplicabilidad",IF(OR(B66="Gobernanza",B66="SGSI",B66="Contexto y alcance"),"Fase 1 - Gobierno y SGSI",IF(OR(B66="Riesgos",B66="Procesos",B66="Personas"),"Fase 2 - Riesgos y operación",IF(OR(B66="Terceros",B66="Continuidad"),"Fase 3 - Continuidad y terceros",IF(OR(B66="Tecnología",B66="Accesos",B66="Ciberseguridad",B66="Vulnerabilidades",B66="Incidentes",B66="Monitoreo"),"Fase 4 - Controles técnicos","Fase 5 - Canales y datos"))))))) -> Fase 4 - Controles técnicos
A67: 66 | B67: Monitoreo | C67: Antimalware y software autorizado | D67: Controlar malware y software no autorizado | E67: SB exige políticas/controles para evitar software no autorizado o sin licencia y mantener herramientas de detección/desinfección actualizadas; canales electrónicos deben tener antimalware actualizado. | F67: SB Art. 25 y 27; SEPS Anexo 1 | G67: Ambas | H67: SB Art. 25/27; SEPS Anexo 1 | I67: EDR/antimalware, inventario de software, procedimiento de autorización/licenciamiento, reportes de actualización y alertas. | J67: 1 | K67: =IF(TRIM(J67&"")="","Por evaluar",IF(UPPER(TRIM(J67&""))="N/A","No aplica",IF(OR(J67=1,J67="1"),"Cumple",IF(OR(J67=0.5,J67="0.5"),"Parcial",IF(OR(J67=0,J67="0"),"No cumple","Revisar valor"))))) -> Cumple | M67: Monitoreo | N67: TIC / CISO | O67: Alta | P67: Permanente | Q67: Se cruza con gestión de software SEPS. | R67: R1 normativa + R2 anexos + R3 cruce | S67: A.8.7 Protección contra malware; A.8.19 Instalación de software; A.8.1 Dispositivos de usuario final | T67: =IF(K67="Cumple","Mantener / evidenciar",IF(K67="Parcial","Cerrar brecha parcial",IF(K67="No cumple","Implementar control",IF(K67="No aplica","Sin acción","Levantar evidencia")))) -> Mantener / evidenciar | U67: =IF(K67="Cumple","Mantener evidencia y revisión periódica",IF(K67="No aplica","Documentar justificación de no aplicabilidad",IF(K67="Por evaluar","Levantar evidencia y confirmar aplicabilidad",IF(K67="Parcial","Completar documentación/control y validar efectividad",IF(K67="No cumple","Diseñar, aprobar e implementar control requerido","Corregir valor de cumplimiento"))))) -> Mantener evidencia y revisión periódica | V67: =IF(K67="No cumple",IF(O67="Alta","0-30 días",IF(O67="Media","31-60 días","61-90 días")),IF(K67="Parcial",IF(O67="Alta","0-45 días",IF(O67="Media","31-75 días","61-120 días")),IF(K67="Por evaluar",IF(O67="Alta","0-15 días","0-30 días"),IF(K67="Cumple","Revisión periódica","No aplica")))) -> Revisión periódica | W67: =IF(K67="No cumple",IF(O67="Alta",3,IF(O67="Media",2,1)),IF(K67="Parcial",IF(O67="Alta",2,IF(O67="Media",1.5,1)),IF(K67="Por evaluar",IF(O67="Alta",1.5,IF(O67="Media",1,0.5)),0))) -> 0 | X67: =IF(K67="No aplica","No aplica",IF(K67="Cumple","Mantenimiento",IF(K67="Por evaluar","Fase 0 - Evidencia/aplicabilidad",IF(OR(B67="Gobernanza",B67="SGSI",B67="Contexto y alcance"),"Fase 1 - Gobierno y SGSI",IF(OR(B67="Riesgos",B67="Procesos",B67="Personas"),"Fase 2 - Riesgos y operación",IF(OR(B67="Terceros",B67="Continuidad"),"Fase 3 - Continuidad y terceros",IF(OR(B67="Tecnología",B67="Accesos",B67="Ciberseguridad",B67="Vulnerabilidades",B67="Incidentes",B67="Monitoreo"),"Fase 4 - Controles técnicos","Fase 5 - Canales y datos"))))))) -> Mantenimiento
A68: 67 | B68: Incidentes | C68: Gestión de incidentes SI | D68: Definir y ejecutar gestión de incidentes de seguridad | E68: SEPS asigna al OSI definir y ejecutar procedimientos de incidentes; SB exige ciclo de vida de incidentes/problemas, priorización, escalamiento, solución, monitoreo, lecciones aprendidas y reportes. | F68: SEPS Art. 12/20/26; SB Art. 17 | G68: Ambas | H68: SEPS y SB | I68: Procedimiento de incidentes, matriz de severidad, playbooks, roles, canal de reporte, tickets, evidencia de atención y lecciones aprendidas. | J68: 0.5 | K68: =IF(TRIM(J68&"")="","Por evaluar",IF(UPPER(TRIM(J68&""))="N/A","No aplica",IF(OR(J68=1,J68="1"),"Cumple",IF(OR(J68=0.5,J68="0.5"),"Parcial",IF(OR(J68=0,J68="0"),"No cumple","Revisar valor"))))) -> Parcial | M68: Incidentes | N68: CISO / SOC / TIC | O68: Alta | P68: Permanente | Q68: Homologar incidentes TI, SI y negocio. | R68: R1 normativa + R2 anexos + R3 cruce | S68: A.5.24 Planificación de incidentes; A.5.25 Evaluación de eventos; A.5.26 Respuesta a incidentes; A.5.27 Aprendizaje; A.5.28 Evidencia; A.6.8 Reporte de eventos | T68: =IF(K68="Cumple","Mantener / evidenciar",IF(K68="Parcial","Cerrar brecha parcial",IF(K68="No cumple","Implementar control",IF(K68="No aplica","Sin acción","Levantar evidencia")))) -> Cerrar brecha parcial | U68: =IF(K68="Cumple","Mantener evidencia y revisión periódica",IF(K68="No aplica","Documentar justificación de no aplicabilidad",IF(K68="Por evaluar","Levantar evidencia y confirmar aplicabilidad",IF(K68="Parcial","Completar documentación/control y validar efectividad",IF(K68="No cumple","Diseñar, aprobar e implementar control requerido","Corregir valor de cumplimiento"))))) -> Completar documentación/control y validar efectividad | V68: =IF(K68="No cumple",IF(O68="Alta","0-30 días",IF(O68="Media","31-60 días","61-90 días")),IF(K68="Parcial",IF(O68="Alta","0-45 días",IF(O68="Media","31-75 días","61-120 días")),IF(K68="Por evaluar",IF(O68="Alta","0-15 días","0-30 días"),IF(K68="Cumple","Revisión periódica","No aplica")))) -> 0-45 días | W68: =IF(K68="No cumple",IF(O68="Alta",3,IF(O68="Media",2,1)),IF(K68="Parcial",IF(O68="Alta",2,IF(O68="Media",1.5,1)),IF(K68="Por evaluar",IF(O68="Alta",1.5,IF(O68="Media",1,0.5)),0))) -> 2 | X68: =IF(K68="No aplica","No aplica",IF(K68="Cumple","Mantenimiento",IF(K68="Por evaluar","Fase 0 - Evidencia/aplicabilidad",IF(OR(B68="Gobernanza",B68="SGSI",B68="Contexto y alcance"),"Fase 1 - Gobierno y SGSI",IF(OR(B68="Riesgos",B68="Procesos",B68="Personas"),"Fase 2 - Riesgos y operación",IF(OR(B68="Terceros",B68="Continuidad"),"Fase 3 - Continuidad y terceros",IF(OR(B68="Tecnología",B68="Accesos",B68="Ciberseguridad",B68="Vulnerabilidades",B68="Incidentes",B68="Monitoreo"),"Fase 4 - Controles técnicos","Fase 5 - Canales y datos"))))))) -> Fase 4 - Controles técnicos
A69: 68 | B69: Incidentes | C69: Gestor de incidentes/problemas | D69: Asignar responsable de trazabilidad | E69: SB exige un gestor de incidentes y problemas responsable de la trazabilidad hasta cierre y registro en base de conocimiento. | F69: SB Art. 17 | G69: SB | H69: SB Art. 17 | I69: Designación de gestor, RACI, flujo de escalamiento, tablero de incidentes/problemas y base de conocimiento. | J69: 0.5 | K69: =IF(TRIM(J69&"")="","Por evaluar",IF(UPPER(TRIM(J69&""))="N/A","No aplica",IF(OR(J69=1,J69="1"),"Cumple",IF(OR(J69=0.5,J69="0.5"),"Parcial",IF(OR(J69=0,J69="0"),"No cumple","Revisar valor"))))) -> Parcial | M69: Incidentes | N69: TIC / CISO | O69: Media | P69: Permanente | Q69: Puede integrarse con mesa de servicios. | R69: R1 normativa + R2 anexos + R3 cruce | S69: A.5.24 Planificación de incidentes; A.5.25 Evaluación de eventos; A.5.26 Respuesta a incidentes; A.5.27 Aprendizaje | T69: =IF(K69="Cumple","Mantener / evidenciar",IF(K69="Parcial","Cerrar brecha parcial",IF(K69="No cumple","Implementar control",IF(K69="No aplica","Sin acción","Levantar evidencia")))) -> Cerrar brecha parcial | U69: =IF(K69="Cumple","Mantener evidencia y revisión periódica",IF(K69="No aplica","Documentar justificación de no aplicabilidad",IF(K69="Por evaluar","Levantar evidencia y confirmar aplicabilidad",IF(K69="Parcial","Completar documentación/control y validar efectividad",IF(K69="No cumple","Diseñar, aprobar e implementar control requerido","Corregir valor de cumplimiento"))))) -> Completar documentación/control y validar efectividad | V69: =IF(K69="No cumple",IF(O69="Alta","0-30 días",IF(O69="Media","31-60 días","61-90 días")),IF(K69="Parcial",IF(O69="Alta","0-45 días",IF(O69="Media","31-75 días","61-120 días")),IF(K69="Por evaluar",IF(O69="Alta","0-15 días","0-30 días"),IF(K69="Cumple","Revisión periódica","No aplica")))) -> 31-75 días | W69: =IF(K69="No cumple",IF(O69="Alta",3,IF(O69="Media",2,1)),IF(K69="Parcial",IF(O69="Alta",2,IF(O69="Media",1.5,1)),IF(K69="Por evaluar",IF(O69="Alta",1.5,IF(O69="Media",1,0.5)),0))) -> 1.5 | X69: =IF(K69="No aplica","No aplica",IF(K69="Cumple","Mantenimiento",IF(K69="Por evaluar","Fase 0 - Evidencia/aplicabilidad",IF(OR(B69="Gobernanza",B69="SGSI",B69="Contexto y alcance"),"Fase 1 - Gobierno y SGSI",IF(OR(B69="Riesgos",B69="Procesos",B69="Personas"),"Fase 2 - Riesgos y operación",IF(OR(B69="Terceros",B69="Continuidad"),"Fase 3 - Continuidad y terceros",IF(OR(B69="Tecnología",B69="Accesos",B69="Ciberseguridad",B69="Vulnerabilidades",B69="Incidentes",B69="Monitoreo"),"Fase 4 - Controles técnicos","Fase 5 - Canales y datos"))))))) -> Fase 4 - Controles técnicos
A70: 69 | B70: Incidentes | C70: Notificación regulatoria | D70: Notificar incidentes críticos o sensibles | E70: SEPS exige reporte inmediato de eventos que afecten continuidad/prestación de servicios; SB exige notificar incidentes que afecten procesos/productos/servicios críticos y remitir informe formal en 5 días e informe definitivo de causa raíz en hasta 10 días. | F70: SEPS Disposición General Primera; SB Art. 17 | G70: Ambas | H70: SEPS Disp. General Primera; SB Art. 17 | I70: Procedimiento de notificación al regulador, criterios de severidad, plantillas, responsables, cronograma de 5/10 días SB y registro de envío. | J70: 0.5 | K70: =IF(TRIM(J70&"")="","Por evaluar",IF(UPPER(TRIM(J70&""))="N/A","No aplica",IF(OR(J70=1,J70="1"),"Cumple",IF(OR(J70=0.5,J70="0.5"),"Parcial",IF(OR(J70=0,J70="0"),"No cumple","Revisar valor"))))) -> Parcial | M70: Incidentes | N70: CISO / Legal / Riesgos / Gerencia | O70: Alta | P70: Por incidente | Q70: Usar plazo más estricto aplicable. | R70: R1 normativa + R2 anexos + R3 cruce | S70: A.5.5 Contacto con autoridades; A.5.24 Gestión de incidentes; A.5.26 Respuesta; A.5.31 Requisitos regulatorios | T70: =IF(K70="Cumple","Mantener / evidenciar",IF(K70="Parcial","Cerrar brecha parcial",IF(K70="No cumple","Implementar control",IF(K70="No aplica","Sin acción","Levantar evidencia")))) -> Cerrar brecha parcial | U70: =IF(K70="Cumple","Mantener evidencia y revisión periódica",IF(K70="No aplica","Documentar justificación de no aplicabilidad",IF(K70="Por evaluar","Levantar evidencia y confirmar aplicabilidad",IF(K70="Parcial","Completar documentación/control y validar efectividad",IF(K70="No cumple","Diseñar, aprobar e implementar control requerido","Corregir valor de cumplimiento"))))) -> Completar documentación/control y validar efectividad | V70: =IF(K70="No cumple",IF(O70="Alta","0-30 días",IF(O70="Media","31-60 días","61-90 días")),IF(K70="Parcial",IF(O70="Alta","0-45 días",IF(O70="Media","31-75 días","61-120 días")),IF(K70="Por evaluar",IF(O70="Alta","0-15 días","0-30 días"),IF(K70="Cumple","Revisión periódica","No aplica")))) -> 0-45 días | W70: =IF(K70="No cumple",IF(O70="Alta",3,IF(O70="Media",2,1)),IF(K70="Parcial",IF(O70="Alta",2,IF(O70="Media",1.5,1)),IF(K70="Por evaluar",IF(O70="Alta",1.5,IF(O70="Media",1,0.5)),0))) -> 2 | X70: =IF(K70="No aplica","No aplica",IF(K70="Cumple","Mantenimiento",IF(K70="Por evaluar","Fase 0 - Evidencia/aplicabilidad",IF(OR(B70="Gobernanza",B70="SGSI",B70="Contexto y alcance"),"Fase 1 - Gobierno y SGSI",IF(OR(B70="Riesgos",B70="Procesos",B70="Personas"),"Fase 2 - Riesgos y operación",IF(OR(B70="Terceros",B70="Continuidad"),"Fase 3 - Continuidad y terceros",IF(OR(B70="Tecnología",B70="Accesos",B70="Ciberseguridad",B70="Vulnerabilidades",B70="Incidentes",B70="Monitoreo"),"Fase 4 - Controles técnicos","Fase 5 - Canales y datos"))))))) -> Fase 4 - Controles técnicos
A71: 70 | B71: Incidentes | C71: Pruebas de respuesta | D71: Ejecutar pruebas controladas de incidentes y problemas | E71: SB exige pruebas controladas de gestión de incidentes/problemas y revisión/actualización de procedimientos. | F71: SB Art. 17 | G71: SB | H71: SB Art. 17 | I71: Plan de simulacros/tabletop, evidencia de ejecución, lecciones aprendidas y actualización de playbooks. | J71: 0 | K71: =IF(TRIM(J71&"")="","Por evaluar",IF(UPPER(TRIM(J71&""))="N/A","No aplica",IF(OR(J71=1,J71="1"),"Cumple",IF(OR(J71=0.5,J71="0.5"),"Parcial",IF(OR(J71=0,J71="0"),"No cumple","Revisar valor"))))) -> No cumple | M71: Incidentes | N71: CISO / TIC / Continuidad | O71: Media | P71: Anual/Semestral | Q71: Relacionado con resiliencia. | R71: R1 normativa + R2 anexos + R3 cruce | S71: A.5.24 Planificación de incidentes; A.5.26 Respuesta; A.5.27 Aprendizaje; A.5.29 SI durante interrupciones | T71: =IF(K71="Cumple","Mantener / evidenciar",IF(K71="Parcial","Cerrar brecha parcial",IF(K71="No cumple","Implementar control",IF(K71="No aplica","Sin acción","Levantar evidencia")))) -> Implementar control | U71: =IF(K71="Cumple","Mantener evidencia y revisión periódica",IF(K71="No aplica","Documentar justificación de no aplicabilidad",IF(K71="Por evaluar","Levantar evidencia y confirmar aplicabilidad",IF(K71="Parcial","Completar documentación/control y validar efectividad",IF(K71="No cumple","Diseñar, aprobar e implementar control requerido","Corregir valor de cumplimiento"))))) -> Diseñar, aprobar e implementar control requerido | V71: =IF(K71="No cumple",IF(O71="Alta","0-30 días",IF(O71="Media","31-60 días","61-90 días")),IF(K71="Parcial",IF(O71="Alta","0-45 días",IF(O71="Media","31-75 días","61-120 días")),IF(K71="Por evaluar",IF(O71="Alta","0-15 días","0-30 días"),IF(K71="Cumple","Revisión periódica","No aplica")))) -> 31-60 días | W71: =IF(K71="No cumple",IF(O71="Alta",3,IF(O71="Media",2,1)),IF(K71="Parcial",IF(O71="Alta",2,IF(O71="Media",1.5,1)),IF(K71="Por evaluar",IF(O71="Alta",1.5,IF(O71="Media",1,0.5)),0))) -> 2 | X71: =IF(K71="No aplica","No aplica",IF(K71="Cumple","Mantenimiento",IF(K71="Por evaluar","Fase 0 - Evidencia/aplicabilidad",IF(OR(B71="Gobernanza",B71="SGSI",B71="Contexto y alcance"),"Fase 1 - Gobierno y SGSI",IF(OR(B71="Riesgos",B71="Procesos",B71="Personas"),"Fase 2 - Riesgos y operación",IF(OR(B71="Terceros",B71="Continuidad"),"Fase 3 - Continuidad y terceros",IF(OR(B71="Tecnología",B71="Accesos",B71="Ciberseguridad",B71="Vulnerabilidades",B71="Incidentes",B71="Monitoreo"),"Fase 4 - Controles técnicos","Fase 5 - Canales y datos"))))))) -> Fase 4 - Controles técnicos
A72: 71 | B72: Ciberseguridad | C72: Marco de ciberseguridad | D72: Definir estrategia y marco de ciberseguridad | E72: SB exige estrategia y marco alineado a mejores prácticas internacionales para identificar, proteger, detectar, responder y recuperar; SEPS Anexo 1 exige ciberseguridad y arquitectura segura. | F72: SEPS Anexo 1; SB Art. 26 | G72: Ambas | H72: SEPS Anexo 1; SB Art. 26 | I72: Estrategia de ciberseguridad, mapa de capacidades, controles ID-PR-DE-RS-RC, roadmap, métricas y reportes al CSI. | J72: 1 | K72: =IF(TRIM(J72&"")="","Por evaluar",IF(UPPER(TRIM(J72&""))="N/A","No aplica",IF(OR(J72=1,J72="1"),"Cumple",IF(OR(J72=0.5,J72="0.5"),"Parcial",IF(OR(J72=0,J72="0"),"No cumple","Revisar valor"))))) -> Cumple | M72: Ciberseguridad | N72: CISO | O72: Alta | P72: Anual | Q72: Alineable a NIST CSF. | R72: R1 normativa + R2 anexos + R3 cruce | S72: A.5.7 Inteligencia de amenazas; A.5.8 Seguridad en proyectos; A.5.36 Cumplimiento; A.8.27 Arquitectura segura | T72: =IF(K72="Cumple","Mantener / evidenciar",IF(K72="Parcial","Cerrar brecha parcial",IF(K72="No cumple","Implementar control",IF(K72="No aplica","Sin acción","Levantar evidencia")))) -> Mantener / evidenciar | U72: =IF(K72="Cumple","Mantener evidencia y revisión periódica",IF(K72="No aplica","Documentar justificación de no aplicabilidad",IF(K72="Por evaluar","Levantar evidencia y confirmar aplicabilidad",IF(K72="Parcial","Completar documentación/control y validar efectividad",IF(K72="No cumple","Diseñar, aprobar e implementar control requerido","Corregir valor de cumplimiento"))))) -> Mantener evidencia y revisión periódica | V72: =IF(K72="No cumple",IF(O72="Alta","0-30 días",IF(O72="Media","31-60 días","61-90 días")),IF(K72="Parcial",IF(O72="Alta","0-45 días",IF(O72="Media","31-75 días","61-120 días")),IF(K72="Por evaluar",IF(O72="Alta","0-15 días","0-30 días"),IF(K72="Cumple","Revisión periódica","No aplica")))) -> Revisión periódica | W72: =IF(K72="No cumple",IF(O72="Alta",3,IF(O72="Media",2,1)),IF(K72="Parcial",IF(O72="Alta",2,IF(O72="Media",1.5,1)),IF(K72="Por evaluar",IF(O72="Alta",1.5,IF(O72="Media",1,0.5)),0))) -> 0 | X72: =IF(K72="No aplica","No aplica",IF(K72="Cumple","Mantenimiento",IF(K72="Por evaluar","Fase 0 - Evidencia/aplicabilidad",IF(OR(B72="Gobernanza",B72="SGSI",B72="Contexto y alcance"),"Fase 1 - Gobierno y SGSI",IF(OR(B72="Riesgos",B72="Procesos",B72="Personas"),"Fase 2 - Riesgos y operación",IF(OR(B72="Terceros",B72="Continuidad"),"Fase 3 - Continuidad y terceros",IF(OR(B72="Tecnología",B72="Accesos",B72="Ciberseguridad",B72="Vulnerabilidades",B72="Incidentes",B72="Monitoreo"),"Fase 4 - Controles técnicos","Fase 5 - Canales y datos"))))))) -> Mantenimiento
A73: 72 | B73: Ciberseguridad | C73: Detectar | D73: Registrar y gestionar eventos de ciberseguridad | E73: SB exige registro continuo y centralizado de eventos, gestión oportuna para alertas tempranas y roles/responsabilidades de eventos de ciberseguridad. | F73: SB Art. 26 | G73: SB | H73: SB Art. 26 | I73: SIEM/SOC, catálogo de eventos, playbooks, turnos/roles, SLA de triage y evidencia de atención. | J73: 1 | K73: =IF(TRIM(J73&"")="","Por evaluar",IF(UPPER(TRIM(J73&""))="N/A","No aplica",IF(OR(J73=1,J73="1"),"Cumple",IF(OR(J73=0.5,J73="0.5"),"Parcial",IF(OR(J73=0,J73="0"),"No cumple","Revisar valor"))))) -> Cumple | M73: Ciberseguridad | N73: CISO / SOC | O73: Alta | P73: Permanente | Q73: Complementa monitoreo SEPS. | R73: R1 normativa + R2 anexos + R3 cruce | S73: A.5.7 Inteligencia de amenazas; A.8.15 Registro de eventos; A.8.16 Monitoreo; A.5.25 Evaluación de eventos | T73: =IF(K73="Cumple","Mantener / evidenciar",IF(K73="Parcial","Cerrar brecha parcial",IF(K73="No cumple","Implementar control",IF(K73="No aplica","Sin acción","Levantar evidencia")))) -> Mantener / evidenciar | U73: =IF(K73="Cumple","Mantener evidencia y revisión periódica",IF(K73="No aplica","Documentar justificación de no aplicabilidad",IF(K73="Por evaluar","Levantar evidencia y confirmar aplicabilidad",IF(K73="Parcial","Completar documentación/control y validar efectividad",IF(K73="No cumple","Diseñar, aprobar e implementar control requerido","Corregir valor de cumplimiento"))))) -> Mantener evidencia y revisión periódica | V73: =IF(K73="No cumple",IF(O73="Alta","0-30 días",IF(O73="Media","31-60 días","61-90 días")),IF(K73="Parcial",IF(O73="Alta","0-45 días",IF(O73="Media","31-75 días","61-120 días")),IF(K73="Por evaluar",IF(O73="Alta","0-15 días","0-30 días"),IF(K73="Cumple","Revisión periódica","No aplica")))) -> Revisión periódica | W73: =IF(K73="No cumple",IF(O73="Alta",3,IF(O73="Media",2,1)),IF(K73="Parcial",IF(O73="Alta",2,IF(O73="Media",1.5,1)),IF(K73="Por evaluar",IF(O73="Alta",1.5,IF(O73="Media",1,0.5)),0))) -> 0 | X73: =IF(K73="No aplica","No aplica",IF(K73="Cumple","Mantenimiento",IF(K73="Por evaluar","Fase 0 - Evidencia/aplicabilidad",IF(OR(B73="Gobernanza",B73="SGSI",B73="Contexto y alcance"),"Fase 1 - Gobierno y SGSI",IF(OR(B73="Riesgos",B73="Procesos",B73="Personas"),"Fase 2 - Riesgos y operación",IF(OR(B73="Terceros",B73="Continuidad"),"Fase 3 - Continuidad y terceros",IF(OR(B73="Tecnología",B73="Accesos",B73="Ciberseguridad",B73="Vulnerabilidades",B73="Incidentes",B73="Monitoreo"),"Fase 4 - Controles técnicos","Fase 5 - Canales y datos"))))))) -> Mantenimiento
A74: 73 | B74: Ciberseguridad | C74: Responder y recuperar | D74: Integrar respuesta ciber con crisis, comunicaciones y continuidad | E74: SB exige actividades de respuesta, contención, recuperación y alineación entre protocolos de ciberseguridad, infraestructura, crisis, comunicación y BCP. | F74: SB Art. 26 | G74: SB | H74: SB Art. 26 | I74: Plan de respuesta ciber, plan de crisis, matriz de comunicaciones, DRP/BCP integrados, ejercicios y lecciones aprendidas. | J74: 0 | K74: =IF(TRIM(J74&"")="","Por evaluar",IF(UPPER(TRIM(J74&""))="N/A","No aplica",IF(OR(J74=1,J74="1"),"Cumple",IF(OR(J74=0.5,J74="0.5"),"Parcial",IF(OR(J74=0,J74="0"),"No cumple","Revisar valor"))))) -> No cumple | M74: Ciberseguridad | N74: CISO / Continuidad / Comunicaciones / TIC | O74: Alta | P74: Anual y por incidente | Q74: Cubre resiliencia operativa. | R74: R1 normativa + R2 anexos + R3 cruce | S74: A.5.26 Respuesta a incidentes; A.5.27 Aprendizaje; A.5.29 SI durante interrupciones; A.5.30 Preparación TIC para continuidad | T74: =IF(K74="Cumple","Mantener / evidenciar",IF(K74="Parcial","Cerrar brecha parcial",IF(K74="No cumple","Implementar control",IF(K74="No aplica","Sin acción","Levantar evidencia")))) -> Implementar control | U74: =IF(K74="Cumple","Mantener evidencia y revisión periódica",IF(K74="No aplica","Documentar justificación de no aplicabilidad",IF(K74="Por evaluar","Levantar evidencia y confirmar aplicabilidad",IF(K74="Parcial","Completar documentación/control y validar efectividad",IF(K74="No cumple","Diseñar, aprobar e implementar control requerido","Corregir valor de cumplimiento"))))) -> Diseñar, aprobar e implementar control requerido | V74: =IF(K74="No cumple",IF(O74="Alta","0-30 días",IF(O74="Media","31-60 días","61-90 días")),IF(K74="Parcial",IF(O74="Alta","0-45 días",IF(O74="Media","31-75 días","61-120 días")),IF(K74="Por evaluar",IF(O74="Alta","0-15 días","0-30 días"),IF(K74="Cumple","Revisión periódica","No aplica")))) -> 0-30 días | W74: =IF(K74="No cumple",IF(O74="Alta",3,IF(O74="Media",2,1)),IF(K74="Parcial",IF(O74="Alta",2,IF(O74="Media",1.5,1)),IF(K74="Por evaluar",IF(O74="Alta",1.5,IF(O74="Media",1,0.5)),0))) -> 3 | X74: =IF(K74="No aplica","No aplica",IF(K74="Cumple","Mantenimiento",IF(K74="Por evaluar","Fase 0 - Evidencia/aplicabilidad",IF(OR(B74="Gobernanza",B74="SGSI",B74="Contexto y alcance"),"Fase 1 - Gobierno y SGSI",IF(OR(B74="Riesgos",B74="Procesos",B74="Personas"),"Fase 2 - Riesgos y operación",IF(OR(B74="Terceros",B74="Continuidad"),"Fase 3 - Continuidad y terceros",IF(OR(B74="Tecnología",B74="Accesos",B74="Ciberseguridad",B74="Vulnerabilidades",B74="Incidentes",B74="Monitoreo"),"Fase 4 - Controles técnicos","Fase 5 - Canales y datos"))))))) -> Fase 4 - Controles técnicos
